Workbook

Sheet Summary
A1: PLASMAIDE — Annual P&L Summary (Multi-Channel)
A2: Australian Financial Year (Jul–Jun)
B4: FY26 | C4: FY27 | D4: FY28 | E4: FY29 | F4: FY30 | G4: 5-Year Total
A6: REVENUE BY CHANNEL
A7: DTC Revenue | B7: =SUM('P&L'!B7:M7) -> 945274 | C7: =SUM('P&L'!N7:Y7) -> 3440934 | D7: =SUM('P&L'!Z7:AK7) -> 7749378 | E7: =SUM('P&L'!AL7:AW7) -> 14601510 | F7: =SUM('P&L'!AX7:BI7) -> 26655552 | G7: =SUM(B7:F7) -> 53392648
A8: Wholesale Revenue | B8: =SUM('P&L'!B8:M8) -> 157207 | C8: =SUM('P&L'!N8:Y8) -> 217728 | D8: =SUM('P&L'!Z8:AK8) -> 290304 | E8: =SUM('P&L'!AL8:AW8) -> 362880 | F8: =SUM('P&L'!AX8:BI8) -> 435456 | G8: =SUM(B8:F8) -> 1463575
A9: Retail Revenue | B9: =SUM('P&L'!B9:M9) -> 0 | C9: =SUM('P&L'!N9:Y9) -> 0 | D9: =SUM('P&L'!Z9:AK9) -> 0 | E9: =SUM('P&L'!AL9:AW9) -> 172368 | F9: =SUM('P&L'!AX9:BI9) -> 438858 | G9: =SUM(B9:F9) -> 611226
A10: Total Net Revenue | B10: =SUM('P&L'!B10:M10) -> 1102481 | C10: =SUM('P&L'!N10:Y10) -> 3658662 | D10: =SUM('P&L'!Z10:AK10) -> 8039682 | E10: =SUM('P&L'!AL10:AW10) -> 15136758 | F10: =SUM('P&L'!AX10:BI10) -> 27529866 | G10: =SUM(B10:F10) -> 55467449
A12: COST OF GOODS SOLD
A13: Product Cost | B13: =SUM('P&L'!B13:M13) -> 275620.25 | C13: =SUM('P&L'!N13:Y13) -> 914665.5 | D13: =SUM('P&L'!Z13:AK13) -> 2009920.5 | E13: =SUM('P&L'!AL13:AW13) -> 3784189.5 | F13: =SUM('P&L'!AX13:BI13) -> 6882466.5 | G13: =SUM(B13:F13) -> 13866862
A14: Fulfillment | B14: =SUM('P&L'!B14:M14) -> 87064 | C14: =SUM('P&L'!N14:Y14) -> 330108 | D14: =SUM('P&L'!Z14:AK14) -> 741236 | E14: =SUM('P&L'!AL14:AW14) -> 1396924 | F14: =SUM('P&L'!AX14:BI14) -> 2549256 | G14: =SUM(B14:F14) -> 5104588
A15: Transaction Fees | B15: =SUM('P&L'!B15:M15) -> 28358.22 | C15: =SUM('P&L'!N15:Y15) -> 103228.02 | D15: =SUM('P&L'!Z15:AK15) -> 232481.34 | E15: =SUM('P&L'!AL15:AW15) -> 438045.3 | F15: =SUM('P&L'!AX15:BI15) -> 799666.56 | G15: =SUM(B15:F15) -> 1601779.4
A16: Total COGS | B16: =SUM('P&L'!B16:M16) -> 391042.47 | C16: =SUM('P&L'!N16:Y16) -> 1348001.5 | D16: =SUM('P&L'!Z16:AK16) -> 2983637.8 | E16: =SUM('P&L'!AL16:AW16) -> 5619158.8 | F16: =SUM('P&L'!AX16:BI16) -> 10231389 | G16: =SUM(B16:F16) -> 20573230
A18: GROSS PROFIT | B18: =SUM('P&L'!B18:M18) -> 711438.53 | C18: =SUM('P&L'!N18:Y18) -> 2310660.5 | D18: =SUM('P&L'!Z18:AK18) -> 5056044.2 | E18: =SUM('P&L'!AL18:AW18) -> 9517599.2 | F18: =SUM('P&L'!AX18:BI18) -> 17298477 | G18: =SUM(B18:F18) -> 34894219
A19: Gross Margin % | B19: =IF(B10=0,0,B18/B10) -> 0.64530684 | C19: =IF(C10=0,0,C18/C10) -> 0.63155888 | D19: =IF(D10=0,0,D18/D10) -> 0.62888609 | E19: =IF(E10=0,0,E18/E10) -> 0.62877396 | F19: =IF(F10=0,0,F18/F10) -> 0.62835311 | G19: =IF(G10=0,0,G18/G10) -> 0.62909364
A21: OPERATING EXPENSES
A22: Performance Marketing | B22: =SUM('P&L'!B22:M22) -> 53050 | C22: =SUM('P&L'!N22:Y22) -> 368521.27 | D22: =SUM('P&L'!Z22:AK22) -> 661811.26 | E22: =SUM('P&L'!AL22:AW22) -> 1188517.9 | F22: =SUM('P&L'!AX22:BI22) -> 2134407.4 | G22: =SUM(B22:F22) -> 4406307.9
A23: Brand Marketing | B23: =SUM('P&L'!B23:M23) -> 180000 | C23: =SUM('P&L'!N23:Y23) -> 198000 | D23: =SUM('P&L'!Z23:AK23) -> 217800 | E23: =SUM('P&L'!AL23:AW23) -> 239580 | F23: =SUM('P&L'!AX23:BI23) -> 263538 | G23: =SUM(B23:F23) -> 1098918
A24: Salaries & Wages | B24: =SUM('P&L'!B24:M24) -> 120000 | C24: =SUM('P&L'!N24:Y24) -> 600000 | D24: =SUM('P&L'!Z24:AK24) -> 1200000 | E24: =SUM('P&L'!AL24:AW24) -> 2400000 | F24: =SUM('P&L'!AX24:BI24) -> 4800000 | G24: =SUM(B24:F24) -> 9120000
A25: R&D / Clinical Testing | B25: =SUM('P&L'!B25:M25) -> 12000 | C25: =SUM('P&L'!N25:Y25) -> 13200 | D25: =SUM('P&L'!Z25:AK25) -> 14520 | E25: =SUM('P&L'!AL25:AW25) -> 15972 | F25: =SUM('P&L'!AX25:BI25) -> 17569.2 | G25: =SUM(B25:F25) -> 73261.2
A26: General & Admin | B26: =SUM('P&L'!B26:M26) -> 96000 | C26: =SUM('P&L'!N26:Y26) -> 100800 | D26: =SUM('P&L'!Z26:AK26) -> 105840 | E26: =SUM('P&L'!AL26:AW26) -> 111132 | F26: =SUM('P&L'!AX26:BI26) -> 116688.6 | G26: =SUM(B26:F26) -> 530460.6
A27: Platform & Technology | B27: =SUM('P&L'!B27:M27) -> 60000 | C27: =SUM('P&L'!N27:Y27) -> 63000 | D27: =SUM('P&L'!Z27:AK27) -> 66150 | E27: =SUM('P&L'!AL27:AW27) -> 69457.5 | F27: =SUM('P&L'!AX27:BI27) -> 72930.375 | G27: =SUM(B27:F27) -> 331537.88
A28: Wholesale Sales Cost | B28: =SUM('P&L'!B28:M28) -> 60000 | C28: =SUM('P&L'!N28:Y28) -> 60000 | D28: =SUM('P&L'!Z28:AK28) -> 60000 | E28: =SUM('P&L'!AL28:AW28) -> 60000 | F28: =SUM('P&L'!AX28:BI28) -> 60000 | G28: =SUM(B28:F28) -> 300000
A29: Retail Sales Cost | B29: =SUM('P&L'!B29:M29) -> 0 | C29: =SUM('P&L'!N29:Y29) -> 0 | D29: =SUM('P&L'!Z29:AK29) -> 0 | E29: =SUM('P&L'!AL29:AW29) -> 180000 | F29: =SUM('P&L'!AX29:BI29) -> 180000 | G29: =SUM(B29:F29) -> 360000
A30: Depreciation | B30: =SUM('P&L'!B30:M30) -> 6000 | C30: =SUM('P&L'!N30:Y30) -> 6000 | D30: =SUM('P&L'!Z30:AK30) -> 6000 | E30: =SUM('P&L'!AL30:AW30) -> 6000 | F30: =SUM('P&L'!AX30:BI30) -> 6000 | G30: =SUM(B30:F30) -> 30000
A31: Total Operating Expenses | B31: =SUM('P&L'!B32:M32) -> 587050 | C31: =SUM('P&L'!N32:Y32) -> 1409521.3 | D31: =SUM('P&L'!Z32:AK32) -> 2332121.3 | E31: =SUM('P&L'!AL32:AW32) -> 4270659.4 | F31: =SUM('P&L'!AX32:BI32) -> 7651133.6 | G31: =SUM(B31:F31) -> 16250486
A33: EBITDA | B33: =SUM('P&L'!B34:M34) -> 130388.53 | C33: =SUM('P&L'!N34:Y34) -> 907139.21 | D33: =SUM('P&L'!Z34:AK34) -> 2729922.9 | E33: =SUM('P&L'!AL34:AW34) -> 5252939.8 | F33: =SUM('P&L'!AX34:BI34) -> 9653343.3 | G33: =SUM(B33:F33) -> 18673734
A34: EBITDA Margin % | B34: =IF(B10=0,0,B33/B10) -> 0.11826828 | C34: =IF(C10=0,0,C33/C10) -> 0.24794288 | D34: =IF(D10=0,0,D33/D10) -> 0.33955608 | E34: =IF(E10=0,0,E33/E10) -> 0.34703202 | F34: =IF(F10=0,0,F33/F10) -> 0.35064985 | G34: =IF(G10=0,0,G33/G10) -> 0.33666112
A36: EBIT | B36: =SUM('P&L'!B37:M37) -> 124388.53 | C36: =SUM('P&L'!N37:Y37) -> 901139.21 | D36: =SUM('P&L'!Z37:AK37) -> 2723922.9 | E36: =SUM('P&L'!AL37:AW37) -> 5246939.8 | F36: =SUM('P&L'!AX37:BI37) -> 9647343.3 | G36: =SUM(B36:F36) -> 18643734
A37: Tax | B37: =SUM('P&L'!B38:M38) -> 49661.617 | C37: =SUM('P&L'!N38:Y38) -> 231168.02 | D37: =SUM('P&L'!Z38:AK38) -> 680980.73 | E37: =SUM('P&L'!AL38:AW38) -> 1311734.9 | F37: =SUM('P&L'!AX38:BI38) -> 2411835.8 | G37: =SUM(B37:F37) -> 4685381.1
A39: NET INCOME | B39: =SUM('P&L'!B40:M40) -> 74726.912 | C39: =SUM('P&L'!N40:Y40) -> 669971.19 | D39: =SUM('P&L'!Z40:AK40) -> 2042942.2 | E39: =SUM('P&L'!AL40:AW40) -> 3935204.8 | F39: =SUM('P&L'!AX40:BI40) -> 7235507.5 | G39: =SUM(B39:F39) -> 13958353
A40: Net Margin % | B40: =IF(B10=0,0,B39/B10) -> 0.067780681 | C40: =IF(C10=0,0,C39/C10) -> 0.18311918 | D40: =IF(D10=0,0,D39/D10) -> 0.25410734 | E40: =IF(E10=0,0,E39/E10) -> 0.25997673 | F40: =IF(F10=0,0,F39/F10) -> 0.26282393 | G40: =IF(G10=0,0,G39/G10) -> 0.25164944
A42: YEAR-ON-YEAR GROWTH
A43: Revenue Growth % | B43: — | C43: =IF(B10=0,0,(C10-B10)/B10) -> 2.3185715 | D43: =IF(C10=0,0,(D10-C10)/C10) -> 1.1974378 | E43: =IF(D10=0,0,(E10-D10)/D10) -> 0.88275581 | F43: =IF(E10=0,0,(F10-E10)/E10) -> 0.81874256
A44: Net Income Growth % | B44: — | C44: =IF(B39=0,0,(C39-B39)/B39) -> 7.9655944 | D44: =IF(C39=0,0,(D39-C39)/C39) -> 2.0492985 | E44: =IF(D39=0,0,(E39-D39)/D39) -> 0.92624386 | F44: =IF(E39=0,0,(F39-E39)/E39) -> 0.83866096

Sheet Drivers & Assumptions
B1: PLASMAIDE — 3-Way Integrated Financial Model (Multi-Channel)
B2: Drivers & Assumptions Dashboard
B3: Australian Financial Year (1 Jul – 30 Jun) | Monthly for 5 Years
B5: DTC (DIRECT-TO-CONSUMER) ASSUMPTIONS | C5: Value | D5: Rationale / Source
B6: DTC Average Order Value (AOV) | C6: 126 | D6: 2×14-pack sachet bundle list price
B7: DTC Customer Acquisition Cost (CAC) | C7: 40 | D7: Blended paid channel CAC for AU/UK markets
B8: Subscription Split (% of New Customers) | C8: 0.4 | D8: 40% subscribe; 60% one-off
B9: Monthly Subscription Churn Rate | C9: 0.1 | D9: Performance supplements with tangible results tracking
B10: One-off Repeat Purchase Rate (monthly) | C10: 0.05 | D10: 5% of one-off pool repurchases each month
B11: Initial Monthly Ad Spend | C11: 20000 | D11: Starting performance marketing budget
B12: Ad Spend Monthly Growth Rate | C12: 0.05 | D12: 5% monthly increase as brand scales
B13: DTC Fulfillment per Order | C13: 12 | D13: Pick-and-pack + shipping
B14: DTC Transaction Fee % | C14: 0.03 | D14: Shopify / payment gateway 3%
B15: DTC COGS % (product cost) | C15: 0.25 | D15: 70% gross margin on product cost; Pine Bark extract
B16: DTC AR Days | C16: 3 | D16: Mostly instant DTC settlement
B18: WHOLESALE ASSUMPTIONS | C18: Value | D18: Rationale / Source
B19: Wholesale Price per 14-pack | C19: 37.8 | D19: ~48% discount off DTC list for distributors
B20: Units per Case | C20: 12 | D20: 12 × 14-packs per case
B21: Cases per Pallet | C21: 36 | D21: 36 cases = 432 units per pallet
B22: Wholesale COGS % (product cost) | C22: 0.25 | D22: Same manufacturing cost base as DTC
B23: Wholesale Fulfillment per Case | C23: 5 | D23: Bulk palletised shipping — lower per unit
B24: Wholesale Transaction Fee % | C24: 0 | D24: Bank transfer / invoice — no gateway fee
B25: Wholesale AR Days | C25: 30 | D25: Standard distributor invoice terms
B26: Wholesale Order Frequency (months) | C26: 3 | D26: Quarterly ordering cycle (adjustable)
B27: Avg Cases per Order (new country, Year 1) | C27: 5 | D27: Initial trial orders — small case quantities
B28: Avg Cases per Order Growth (annual) | C28: 0.25 | D28: 25% annual increase in avg order size
B30: RETAIL ASSUMPTIONS | C30: Value | D30: Rationale / Source
B31: Retail Launch Month (month # from Jul-25) | C31: 37 | D31: Month 37 = Jul-28. Change to move launch date.
B32: Retail Price per 14-pack | C32: 37.8 | D32: ~13% discount off DTC list for retail margin sharing
B33: Retail COGS % (product cost) | C33: 0.25 | D33: Same manufacturing cost base
B34: Retail Fulfillment per Case | C34: 6 | D34: Delivery to retail stores / warehouses
B35: Retail Transaction Fee % | C35: 0 | D35: 1.5% — lower rate on B2B invoicing
B36: Retail AR Days | C36: 45 | D36: Retail chain payment terms
B37: Initial Retail Doors (stores) | C37: 20 | D37: Starting retail footprint at launch
B38: New Doors per Month (post-launch) | C38: 5 | D38: Gradual retail rollout
B39: Avg Units per Door per Month | C39: 8 | D39: 8 × 14-packs per store per month
B40: Units per Door Annual Growth | C40: 0.1 | D40: 10% annual increase as brand gains traction
B42: SHARED MARKETING & BRAND | C42: Value | D42: Rationale / Source
B43: Fixed Brand Spend (monthly) | C43: 15000 | D43: Content, influencers, partnerships
B44: Brand Spend Annual Escalation | C44: 0.1 | D44: 10% annual increase
B46: OPERATING EXPENSES (SHARED) | C46: Value | D46: Rationale / Source
B47: Salaries & Wages (monthly) | C47: 25000 | D47: Founders + team
B48: Salary Annual Escalation | C48: 1 | D48: 100% annual
B49: R&D / Clinical Testing (monthly) | C49: 1000 | D49: Informed Sport, clinical/sports science
B50: R&D Annual Escalation | C50: 0.1 | D50: 10% annual
B51: General & Admin (monthly) | C51: 8000 | D51: Rent, insurance, software, legal
B52: G&A Annual Escalation | C52: 0.05 | D52: 5% annual
B53: Platform / Tech (monthly) | C53: 5000 | D53: Shopify Plus, DotDigital, apps
B54: Tech Annual Escalation | C54: 0.05 | D54: 5% annual
B55: Wholesale Sales Cost (monthly, from Month 1) | C55: 5000 | D55: BDM / distributor management
B56: Retail Sales Cost (monthly, from retail launch) | C56: 15000 | D56: Retail account management / merchandising
B58: BALANCE SHEET & WORKING CAPITAL | C58: Value | D58: Rationale / Source
B59: Inventory Days on Hand | C59: 120 | D59: Specialized manufacturing + Informed Sport testing
B60: Opening Cash Balance | C60: 100000 | D60: Starting cash — adjust to actual
B61: Tax Rate | C61: 0.25 | D61: Australian corporate tax rate (base rate entity)
B62: Depreciation (monthly) | C62: 500 | D62: Minimal fixed assets
B63: Capex (monthly) | C63: 1000 | D63: Equipment & tooling

Sheet DTC Revenue
A1: PLASMAIDE — DTC Revenue Build
A2: Shopify Direct-to-Consumer Channel
B4: Jul-25 | C4: Aug-25 | D4: Sep-25 | E4: Oct-25 | F4: Nov-25 | G4: Dec-25 | H4: Jan-26 | I4: Feb-26 | J4: Mar-26 | K4: Apr-26 | L4: May-26 | M4: Jun-26 | N4: Jul-26 | O4: Aug-26 | P4: Sep-26 | Q4: Oct-26 | R4: Nov-26 | S4: Dec-26 | T4: Jan-27 | U4: Feb-27 | V4: Mar-27 | W4: Apr-27 | X4: May-27 | Y4: Jun-27 | Z4: Jul-27 | AA4: Aug-27 | AB4: Sep-27 | AC4: Oct-27 | AD4: Nov-27 | AE4: Dec-27 | AF4: Jan-28 | AG4: Feb-28 | AH4: Mar-28 | AI4: Apr-28 | AJ4: May-28 | AK4: Jun-28 | AL4: Jul-28 | AM4: Aug-28 | AN4: Sep-28 | AO4: Oct-28 | AP4: Nov-28 | AQ4: Dec-28 | AR4: Jan-29 | AS4: Feb-29 | AT4: Mar-29 | AU4: Apr-29 | AV4: May-29 | AW4: Jun-29 | AX4: Jul-29 | AY4: Aug-29 | AZ4: Sep-29 | BA4: Oct-29 | BB4: Nov-29 | BC4: Dec-29 | BD4: Jan-30 | BE4: Feb-30 | BF4: Mar-30 | BG4: Apr-30 | BH4: May-30 | BI4: Jun-30
A6: DTC ACTUALS (AUD)
A7: DTC Revenue (Actuals) | B7: 37954 | C7: 61361 | D7: 108804 | E7: 57522 | F7: 71229 | G7: 61780 | H7: 62159 | I7: 181457 | J7: 50000
A8: Implied Orders (Actuals ÷ AOV) | B8: =ROUND(B7/'Drivers & Assumptions'!C6,0) -> 301 | C8: =ROUND(C7/'Drivers & Assumptions'!C6,0) -> 487 | D8: =ROUND(D7/'Drivers & Assumptions'!C6,0) -> 864 | E8: =ROUND(E7/'Drivers & Assumptions'!C6,0) -> 457 | F8: =ROUND(F7/'Drivers & Assumptions'!C6,0) -> 565 | G8: =ROUND(G7/'Drivers & Assumptions'!C6,0) -> 490 | H8: =ROUND(H7/'Drivers & Assumptions'!C6,0) -> 493 | I8: =ROUND(I7/'Drivers & Assumptions'!C6,0) -> 1440
A10: AD SPEND & ACQUISITION
A11: Monthly Performance Ad Spend | B11: 0 | C11: =B11*(1+'Drivers & Assumptions'!C12) -> 0 | D11: =C11*(1+'Drivers & Assumptions'!C12) -> 0 | E11: =D11*(1+'Drivers & Assumptions'!C12) -> 0 | F11: =E11*(1+'Drivers & Assumptions'!C12) -> 0 | G11: =F11*(1+'Drivers & Assumptions'!C12) -> 0 | H11: =G11*(1+'Drivers & Assumptions'!C12) -> 0 | I11: =H11*(1+'Drivers & Assumptions'!C12) -> 0 | J11: 0 | K11: 10000 | L11: ='Drivers & Assumptions'!C11*(1+'Drivers & Assumptions'!C12) -> 21000 | M11: =L11*(1+'Drivers & Assumptions'!C12) -> 22050 | N11: =M11*(1+'Drivers & Assumptions'!C12) -> 23152.5 | O11: =N11*(1+'Drivers & Assumptions'!C12) -> 24310.125 | P11: =O11*(1+'Drivers & Assumptions'!C12) -> 25525.631 | Q11: =P11*(1+'Drivers & Assumptions'!C12) -> 26801.913 | R11: =Q11*(1+'Drivers & Assumptions'!C12) -> 28142.008 | S11: =R11*(1+'Drivers & Assumptions'!C12) -> 29549.109 | T11: =S11*(1+'Drivers & Assumptions'!C12) -> 31026.564 | U11: =T11*(1+'Drivers & Assumptions'!C12) -> 32577.893 | V11: =U11*(1+'Drivers & Assumptions'!C12) -> 34206.787 | W11: =V11*(1+'Drivers & Assumptions'!C12) -> 35917.127 | X11: =W11*(1+'Drivers & Assumptions'!C12) -> 37712.983 | Y11: =X11*(1+'Drivers & Assumptions'!C12) -> 39598.632 | Z11: =Y11*(1+'Drivers & Assumptions'!C12) -> 41578.564 | AA11: =Z11*(1+'Drivers & Assumptions'!C12) -> 43657.492 | AB11: =AA11*(1+'Drivers & Assumptions'!C12) -> 45840.366 | AC11: =AB11*(1+'Drivers & Assumptions'!C12) -> 48132.385 | AD11: =AC11*(1+'Drivers & Assumptions'!C12) -> 50539.004 | AE11: =AD11*(1+'Drivers & Assumptions'!C12) -> 53065.954 | AF11: =AE11*(1+'Drivers & Assumptions'!C12) -> 55719.252 | AG11: =AF11*(1+'Drivers & Assumptions'!C12) -> 58505.214 | AH11: =AG11*(1+'Drivers & Assumptions'!C12) -> 61430.475 | AI11: =AH11*(1+'Drivers & Assumptions'!C12) -> 64501.999 | AJ11: =AI11*(1+'Drivers & Assumptions'!C12) -> 67727.099 | AK11: =AJ11*(1+'Drivers & Assumptions'!C12) -> 71113.454 | AL11: =AK11*(1+'Drivers & Assumptions'!C12) -> 74669.126 | AM11: =AL11*(1+'Drivers & Assumptions'!C12) -> 78402.583 | AN11: =AM11*(1+'Drivers & Assumptions'!C12) -> 82322.712 | AO11: =AN11*(1+'Drivers & Assumptions'!C12) -> 86438.848 | AP11: =AO11*(1+'Drivers & Assumptions'!C12) -> 90760.79 | AQ11: =AP11*(1+'Drivers & Assumptions'!C12) -> 95298.829 | AR11: =AQ11*(1+'Drivers & Assumptions'!C12) -> 100063.77 | AS11: =AR11*(1+'Drivers & Assumptions'!C12) -> 105066.96 | AT11: =AS11*(1+'Drivers & Assumptions'!C12) -> 110320.31 | AU11: =AT11*(1+'Drivers & Assumptions'!C12) -> 115836.32 | AV11: =AU11*(1+'Drivers & Assumptions'!C12) -> 121628.14 | AW11: =AV11*(1+'Drivers & Assumptions'!C12) -> 127709.55 | AX11: =AW11*(1+'Drivers & Assumptions'!C12) -> 134095.02 | AY11: =AX11*(1+'Drivers & Assumptions'!C12) -> 140799.77 | AZ11: =AY11*(1+'Drivers & Assumptions'!C12) -> 147839.76 | BA11: =AZ11*(1+'Drivers & Assumptions'!C12) -> 155231.75 | BB11: =BA11*(1+'Drivers & Assumptions'!C12) -> 162993.34 | BC11: =BB11*(1+'Drivers & Assumptions'!C12) -> 171143.01 | BD11: =BC11*(1+'Drivers & Assumptions'!C12) -> 179700.16 | BE11: =BD11*(1+'Drivers & Assumptions'!C12) -> 188685.16 | BF11: =BE11*(1+'Drivers & Assumptions'!C12) -> 198119.42 | BG11: =BF11*(1+'Drivers & Assumptions'!C12) -> 208025.39 | BH11: =BG11*(1+'Drivers & Assumptions'!C12) -> 218426.66 | BI11: =BH11*(1+'Drivers & Assumptions'!C12) -> 229348
A12: New Customers (Ad Spend ÷ CAC) | B12: =ROUND(B11/'Drivers & Assumptions'!C7,0) -> 0 | C12: =ROUND(C11/'Drivers & Assumptions'!C7,0) -> 0 | D12: =ROUND(D11/'Drivers & Assumptions'!C7,0) -> 0 | E12: =ROUND(E11/'Drivers & Assumptions'!C7,0) -> 0 | F12: =ROUND(F11/'Drivers & Assumptions'!C7,0) -> 0 | G12: =ROUND(G11/'Drivers & Assumptions'!C7,0) -> 0 | H12: =ROUND(H11/'Drivers & Assumptions'!C7,0) -> 0 | I12: =ROUND(I11/'Drivers & Assumptions'!C7,0) -> 0 | J12: =ROUND(J11/'Drivers & Assumptions'!C7,0) -> 0 | K12: =ROUND(K11/'Drivers & Assumptions'!C7,0) -> 250 | L12: =ROUND(L11/'Drivers & Assumptions'!C7,0) -> 525 | M12: =ROUND(M11/'Drivers & Assumptions'!C7,0) -> 551 | N12: =ROUND(N11/'Drivers & Assumptions'!C7,0) -> 579 | O12: =ROUND(O11/'Drivers & Assumptions'!C7,0) -> 608 | P12: =ROUND(P11/'Drivers & Assumptions'!C7,0) -> 638 | Q12: =ROUND(Q11/'Drivers & Assumptions'!C7,0) -> 670 | R12: =ROUND(R11/'Drivers & Assumptions'!C7,0) -> 704 | S12: =ROUND(S11/'Drivers & Assumptions'!C7,0) -> 739 | T12: =ROUND(T11/'Drivers & Assumptions'!C7,0) -> 776 | U12: =ROUND(U11/'Drivers & Assumptions'!C7,0) -> 814 | V12: =ROUND(V11/'Drivers & Assumptions'!C7,0) -> 855 | W12: =ROUND(W11/'Drivers & Assumptions'!C7,0) -> 898 | X12: =ROUND(X11/'Drivers & Assumptions'!C7,0) -> 943 | Y12: =ROUND(Y11/'Drivers & Assumptions'!C7,0) -> 990 | Z12: =ROUND(Z11/'Drivers & Assumptions'!C7,0) -> 1039 | AA12: =ROUND(AA11/'Drivers & Assumptions'!C7,0) -> 1091 | AB12: =ROUND(AB11/'Drivers & Assumptions'!C7,0) -> 1146 | AC12: =ROUND(AC11/'Drivers & Assumptions'!C7,0) -> 1203 | AD12: =ROUND(AD11/'Drivers & Assumptions'!C7,0) -> 1263 | AE12: =ROUND(AE11/'Drivers & Assumptions'!C7,0) -> 1327 | AF12: =ROUND(AF11/'Drivers & Assumptions'!C7,0) -> 1393 | AG12: =ROUND(AG11/'Drivers & Assumptions'!C7,0) -> 1463 | AH12: =ROUND(AH11/'Drivers & Assumptions'!C7,0) -> 1536 | AI12: =ROUND(AI11/'Drivers & Assumptions'!C7,0) -> 1613 | AJ12: =ROUND(AJ11/'Drivers & Assumptions'!C7,0) -> 1693 | AK12: =ROUND(AK11/'Drivers & Assumptions'!C7,0) -> 1778 | AL12: =ROUND(AL11/'Drivers & Assumptions'!C7,0) -> 1867 | AM12: =ROUND(AM11/'Drivers & Assumptions'!C7,0) -> 1960 | AN12: =ROUND(AN11/'Drivers & Assumptions'!C7,0) -> 2058 | AO12: =ROUND(AO11/'Drivers & Assumptions'!C7,0) -> 2161 | AP12: =ROUND(AP11/'Drivers & Assumptions'!C7,0) -> 2269 | AQ12: =ROUND(AQ11/'Drivers & Assumptions'!C7,0) -> 2382 | AR12: =ROUND(AR11/'Drivers & Assumptions'!C7,0) -> 2502 | AS12: =ROUND(AS11/'Drivers & Assumptions'!C7,0) -> 2627 | AT12: =ROUND(AT11/'Drivers & Assumptions'!C7,0) -> 2758 | AU12: =ROUND(AU11/'Drivers & Assumptions'!C7,0) -> 2896 | AV12: =ROUND(AV11/'Drivers & Assumptions'!C7,0) -> 3041 | AW12: =ROUND(AW11/'Drivers & Assumptions'!C7,0) -> 3193 | AX12: =ROUND(AX11/'Drivers & Assumptions'!C7,0) -> 3352 | AY12: =ROUND(AY11/'Drivers & Assumptions'!C7,0) -> 3520 | AZ12: =ROUND(AZ11/'Drivers & Assumptions'!C7,0) -> 3696 | BA12: =ROUND(BA11/'Drivers & Assumptions'!C7,0) -> 3881 | BB12: =ROUND(BB11/'Drivers & Assumptions'!C7,0) -> 4075 | BC12: =ROUND(BC11/'Drivers & Assumptions'!C7,0) -> 4279 | BD12: =ROUND(BD11/'Drivers & Assumptions'!C7,0) -> 4493 | BE12: =ROUND(BE11/'Drivers & Assumptions'!C7,0) -> 4717 | BF12: =ROUND(BF11/'Drivers & Assumptions'!C7,0) -> 4953 | BG12: =ROUND(BG11/'Drivers & Assumptions'!C7,0) -> 5201 | BH12: =ROUND(BH11/'Drivers & Assumptions'!C7,0) -> 5461 | BI12: =ROUND(BI11/'Drivers & Assumptions'!C7,0) -> 5734
A14: CUSTOMER COHORT MODEL
A15: New Subscribers | J15: 6 | K15: =ROUND(K12*'Drivers & Assumptions'!C8,0) -> 100 | L15: =ROUND(L12*'Drivers & Assumptions'!C8,0) -> 210 | M15: =ROUND(M12*'Drivers & Assumptions'!C8,0) -> 220 | N15: =ROUND(N12*'Drivers & Assumptions'!C8,0) -> 232 | O15: =ROUND(O12*'Drivers & Assumptions'!C8,0) -> 243 | P15: =ROUND(P12*'Drivers & Assumptions'!C8,0) -> 255 | Q15: =ROUND(Q12*'Drivers & Assumptions'!C8,0) -> 268 | R15: =ROUND(R12*'Drivers & Assumptions'!C8,0) -> 282 | S15: =ROUND(S12*'Drivers & Assumptions'!C8,0) -> 296 | T15: =ROUND(T12*'Drivers & Assumptions'!C8,0) -> 310 | U15: =ROUND(U12*'Drivers & Assumptions'!C8,0) -> 326 | V15: =ROUND(V12*'Drivers & Assumptions'!C8,0) -> 342 | W15: =ROUND(W12*'Drivers & Assumptions'!C8,0) -> 359 | X15: =ROUND(X12*'Drivers & Assumptions'!C8,0) -> 377 | Y15: =ROUND(Y12*'Drivers & Assumptions'!C8,0) -> 396 | Z15: =ROUND(Z12*'Drivers & Assumptions'!C8,0) -> 416 | AA15: =ROUND(AA12*'Drivers & Assumptions'!C8,0) -> 436 | AB15: =ROUND(AB12*'Drivers & Assumptions'!C8,0) -> 458 | AC15: =ROUND(AC12*'Drivers & Assumptions'!C8,0) -> 481 | AD15: =ROUND(AD12*'Drivers & Assumptions'!C8,0) -> 505 | AE15: =ROUND(AE12*'Drivers & Assumptions'!C8,0) -> 531 | AF15: =ROUND(AF12*'Drivers & Assumptions'!C8,0) -> 557 | AG15: =ROUND(AG12*'Drivers & Assumptions'!C8,0) -> 585 | AH15: =ROUND(AH12*'Drivers & Assumptions'!C8,0) -> 614 | AI15: =ROUND(AI12*'Drivers & Assumptions'!C8,0) -> 645 | AJ15: =ROUND(AJ12*'Drivers & Assumptions'!C8,0) -> 677 | AK15: =ROUND(AK12*'Drivers & Assumptions'!C8,0) -> 711 | AL15: =ROUND(AL12*'Drivers & Assumptions'!C8,0) -> 747 | AM15: =ROUND(AM12*'Drivers & Assumptions'!C8,0) -> 784 | AN15: =ROUND(AN12*'Drivers & Assumptions'!C8,0) -> 823 | AO15: =ROUND(AO12*'Drivers & Assumptions'!C8,0) -> 864 | AP15: =ROUND(AP12*'Drivers & Assumptions'!C8,0) -> 908 | AQ15: =ROUND(AQ12*'Drivers & Assumptions'!C8,0) -> 953 | AR15: =ROUND(AR12*'Drivers & Assumptions'!C8,0) -> 1001 | AS15: =ROUND(AS12*'Drivers & Assumptions'!C8,0) -> 1051 | AT15: =ROUND(AT12*'Drivers & Assumptions'!C8,0) -> 1103 | AU15: =ROUND(AU12*'Drivers & Assumptions'!C8,0) -> 1158 | AV15: =ROUND(AV12*'Drivers & Assumptions'!C8,0) -> 1216 | AW15: =ROUND(AW12*'Drivers & Assumptions'!C8,0) -> 1277 | AX15: =ROUND(AX12*'Drivers & Assumptions'!C8,0) -> 1341 | AY15: =ROUND(AY12*'Drivers & Assumptions'!C8,0) -> 1408 | AZ15: =ROUND(AZ12*'Drivers & Assumptions'!C8,0) -> 1478 | BA15: =ROUND(BA12*'Drivers & Assumptions'!C8,0) -> 1552 | BB15: =ROUND(BB12*'Drivers & Assumptions'!C8,0) -> 1630 | BC15: =ROUND(BC12*'Drivers & Assumptions'!C8,0) -> 1712 | BD15: =ROUND(BD12*'Drivers & Assumptions'!C8,0) -> 1797 | BE15: =ROUND(BE12*'Drivers & Assumptions'!C8,0) -> 1887 | BF15: =ROUND(BF12*'Drivers & Assumptions'!C8,0) -> 1981 | BG15: =ROUND(BG12*'Drivers & Assumptions'!C8,0) -> 2080 | BH15: =ROUND(BH12*'Drivers & Assumptions'!C8,0) -> 2184 | BI15: =ROUND(BI12*'Drivers & Assumptions'!C8,0) -> 2294
A16: New One-off Buyers | K16: =K12-K15 -> 150 | L16: =L12-L15 -> 315 | M16: =M12-M15 -> 331 | N16: =N12-N15 -> 347 | O16: =O12-O15 -> 365 | P16: =P12-P15 -> 383 | Q16: =Q12-Q15 -> 402 | R16: =R12-R15 -> 422 | ... BI16: =BI12-BI15 -> 3440
A17: Active Subscribers (end of month) | J17: 67 | K17: =ROUND(J17*(1-'Drivers & Assumptions'!C9),0)+K15 -> 160 | L17: =ROUND(K17*(1-'Drivers & Assumptions'!C9),0)+L15 -> 354 | M17: =ROUND(L17*(1-'Drivers & Assumptions'!C9),0)+M15 -> 539 | N17: =ROUND(M17*(1-'Drivers & Assumptions'!C9),0)+N15 -> 717 | O17: =ROUND(N17*(1-'Drivers & Assumptions'!C9),0)+O15 -> 888 | P17: =ROUND(O17*(1-'Drivers & Assumptions'!C9),0)+P15 -> 1054 | Q17: =ROUND(P17*(1-'Drivers & Assumptions'!C9),0)+Q15 -> 1217 | R17: =ROUND(Q17*(1-'Drivers & Assumptions'!C9),0)+R15 -> 1377 | S17: =ROUND(R17*(1-'Drivers & Assumptions'!C9),0)+S15 -> 1535 | T17: =ROUND(S17*(1-'Drivers & Assumptions'!C9),0)+T15 -> 1692 | U17: =ROUND(T17*(1-'Drivers & Assumptions'!C9),0)+U15 -> 1849 | V17: =ROUND(U17*(1-'Drivers & Assumptions'!C9),0)+V15 -> 2006 | W17: =ROUND(V17*(1-'Drivers & Assumptions'!C9),0)+W15 -> 2164 | X17: =ROUND(W17*(1-'Drivers & Assumptions'!C9),0)+X15 -> 2325 | Y17: =ROUND(X17*(1-'Drivers & Assumptions'!C9),0)+Y15 -> 2489 | Z17: =ROUND(Y17*(1-'Drivers & Assumptions'!C9),0)+Z15 -> 2656 | AA17: =ROUND(Z17*(1-'Drivers & Assumptions'!C9),0)+AA15 -> 2826 | AB17: =ROUND(AA17*(1-'Drivers & Assumptions'!C9),0)+AB15 -> 3001 | AC17: =ROUND(AB17*(1-'Drivers & Assumptions'!C9),0)+AC15 -> 3182 | AD17: =ROUND(AC17*(1-'Drivers & Assumptions'!C9),0)+AD15 -> 3369 | AE17: =ROUND(AD17*(1-'Drivers & Assumptions'!C9),0)+AE15 -> 3563 | AF17: =ROUND(AE17*(1-'Drivers & Assumptions'!C9),0)+AF15 -> 3764 | AG17: =ROUND(AF17*(1-'Drivers & Assumptions'!C9),0)+AG15 -> 3973 | AH17: =ROUND(AG17*(1-'Drivers & Assumptions'!C9),0)+AH15 -> 4190 | AI17: =ROUND(AH17*(1-'Drivers & Assumptions'!C9),0)+AI15 -> 4416 | AJ17: =ROUND(AI17*(1-'Drivers & Assumptions'!C9),0)+AJ15 -> 4651 | AK17: =ROUND(AJ17*(1-'Drivers & Assumptions'!C9),0)+AK15 -> 4897 | AL17: =ROUND(AK17*(1-'Drivers & Assumptions'!C9),0)+AL15 -> 5154 | AM17: =ROUND(AL17*(1-'Drivers & Assumptions'!C9),0)+AM15 -> 5423 | AN17: =ROUND(AM17*(1-'Drivers & Assumptions'!C9),0)+AN15 -> 5704 | AO17: =ROUND(AN17*(1-'Drivers & Assumptions'!C9),0)+AO15 -> 5998 | AP17: =ROUND(AO17*(1-'Drivers & Assumptions'!C9),0)+AP15 -> 6306 | AQ17: =ROUND(AP17*(1-'Drivers & Assumptions'!C9),0)+AQ15 -> 6628 | AR17: =ROUND(AQ17*(1-'Drivers & Assumptions'!C9),0)+AR15 -> 6966 | AS17: =ROUND(AR17*(1-'Drivers & Assumptions'!C9),0)+AS15 -> 7320 | AT17: =ROUND(AS17*(1-'Drivers & Assumptions'!C9),0)+AT15 -> 7691 | AU17: =ROUND(AT17*(1-'Drivers & Assumptions'!C9),0)+AU15 -> 8080 | AV17: =ROUND(AU17*(1-'Drivers & Assumptions'!C9),0)+AV15 -> 8488 | AW17: =ROUND(AV17*(1-'Drivers & Assumptions'!C9),0)+AW15 -> 8916 | AX17: =ROUND(AW17*(1-'Drivers & Assumptions'!C9),0)+AX15 -> 9365 | AY17: =ROUND(AX17*(1-'Drivers & Assumptions'!C9),0)+AY15 -> 9837 | AZ17: =ROUND(AY17*(1-'Drivers & Assumptions'!C9),0)+AZ15 -> 10331 | BA17: =ROUND(AZ17*(1-'Drivers & Assumptions'!C9),0)+BA15 -> 10850 | BB17: =ROUND(BA17*(1-'Drivers & Assumptions'!C9),0)+BB15 -> 11395 | BC17: =ROUND(BB17*(1-'Drivers & Assumptions'!C9),0)+BC15 -> 11968 | BD17: =ROUND(BC17*(1-'Drivers & Assumptions'!C9),0)+BD15 -> 12568 | BE17: =ROUND(BD17*(1-'Drivers & Assumptions'!C9),0)+BE15 -> 13198 | BF17: =ROUND(BE17*(1-'Drivers & Assumptions'!C9),0)+BF15 -> 13859 | BG17: =ROUND(BF17*(1-'Drivers & Assumptions'!C9),0)+BG15 -> 14553 | BH17: =ROUND(BG17*(1-'Drivers & Assumptions'!C9),0)+BH15 -> 15282 | BI17: =ROUND(BH17*(1-'Drivers & Assumptions'!C9),0)+BI15 -> 16048
A18: Cumulative One-off Pool | J18: 586 | K18: =J18+K16 -> 736 | L18: =K18+L16 -> 1051 | M18: =L18+M16 -> 1382 | N18: =M18+N16 -> 1729 | O18: =N18+O16 -> 2094 | P18: =O18+P16 -> 2477 | Q18: =P18+Q16 -> 2879 | R18: =Q18+R16 -> 3301 | ... BI18: =BH18+BI16 -> 66686
A19: Repeat One-off Orders | K19: =ROUND(K18*'Drivers & Assumptions'!C10,0) -> 37 | L19: =ROUND(L18*'Drivers & Assumptions'!C10,0) -> 53 | M19: =ROUND(M18*'Drivers & Assumptions'!C10,0) -> 69 | N19: =ROUND(N18*'Drivers & Assumptions'!C10,0) -> 86 | O19: =ROUND(O18*'Drivers & Assumptions'!C10,0) -> 105 | P19: =ROUND(P18*'Drivers & Assumptions'!C10,0) -> 124 | Q19: =ROUND(Q18*'Drivers & Assumptions'!C10,0) -> 144 | R19: =ROUND(R18*'Drivers & Assumptions'!C10,0) -> 165 | S19: =ROUND(S18*'Drivers & Assumptions'!C10,0) -> 187 | T19: =ROUND(T18*'Drivers & Assumptions'!C10,0) -> 211 | U19: =ROUND(U18*'Drivers & Assumptions'!C10,0) -> 235 | V19: =ROUND(V18*'Drivers & Assumptions'!C10,0) -> 261 | W19: =ROUND(W18*'Drivers & Assumptions'!C10,0) -> 288 | X19: =ROUND(X18*'Drivers & Assumptions'!C10,0) -> 316 | Y19: =ROUND(Y18*'Drivers & Assumptions'!C10,0) -> 346 | Z19: =ROUND(Z18*'Drivers & Assumptions'!C10,0) -> 377 | AA19: =ROUND(AA18*'Drivers & Assumptions'!C10,0) -> 409 | AB19: =ROUND(AB18*'Drivers & Assumptions'!C10,0) -> 444 | AC19: =ROUND(AC18*'Drivers & Assumptions'!C10,0) -> 480 | AD19: =ROUND(AD18*'Drivers & Assumptions'!C10,0) -> 518 | AE19: =ROUND(AE18*'Drivers & Assumptions'!C10,0) -> 558 | AF19: =ROUND(AF18*'Drivers & Assumptions'!C10,0) -> 599 | AG19: =ROUND(AG18*'Drivers & Assumptions'!C10,0) -> 643 | AH19: =ROUND(AH18*'Drivers & Assumptions'!C10,0) -> 689 | AI19: =ROUND(AI18*'Drivers & Assumptions'!C10,0) -> 738 | AJ19: =ROUND(AJ18*'Drivers & Assumptions'!C10,0) -> 789 | AK19: =ROUND(AK18*'Drivers & Assumptions'!C10,0) -> 842 | AL19: =ROUND(AL18*'Drivers & Assumptions'!C10,0) -> 898 | AM19: =ROUND(AM18*'Drivers & Assumptions'!C10,0) -> 957 | AN19: =ROUND(AN18*'Drivers & Assumptions'!C10,0) -> 1019 | AO19: =ROUND(AO18*'Drivers & Assumptions'!C10,0) -> 1083 | AP19: =ROUND(AP18*'Drivers & Assumptions'!C10,0) -> 1151 | AQ19: =ROUND(AQ18*'Drivers & Assumptions'!C10,0) -> 1223 | AR19: =ROUND(AR18*'Drivers & Assumptions'!C10,0) -> 1298 | AS19: =ROUND(AS18*'Drivers & Assumptions'!C10,0) -> 1377 | AT19: =ROUND(AT18*'Drivers & Assumptions'!C10,0) -> 1459 | AU19: =ROUND(AU18*'Drivers & Assumptions'!C10,0) -> 1546 | AV19: =ROUND(AV18*'Drivers & Assumptions'!C10,0) -> 1638 | AW19: =ROUND(AW18*'Drivers & Assumptions'!C10,0) -> 1733 | AX19: =ROUND(AX18*'Drivers & Assumptions'!C10,0) -> 1834 | AY19: =ROUND(AY18*'Drivers & Assumptions'!C10,0) -> 1940 | AZ19: =ROUND(AZ18*'Drivers & Assumptions'!C10,0) -> 2050 | BA19: =ROUND(BA18*'Drivers & Assumptions'!C10,0) -> 2167 | BB19: =ROUND(BB18*'Drivers & Assumptions'!C10,0) -> 2289 | BC19: =ROUND(BC18*'Drivers & Assumptions'!C10,0) -> 2418 | BD19: =ROUND(BD18*'Drivers & Assumptions'!C10,0) -> 2552 | BE19: =ROUND(BE18*'Drivers & Assumptions'!C10,0) -> 2694 | BF19: =ROUND(BF18*'Drivers & Assumptions'!C10,0) -> 2842 | BG19: =ROUND(BG18*'Drivers & Assumptions'!C10,0) -> 2998 | BH19: =ROUND(BH18*'Drivers & Assumptions'!C10,0) -> 3162 | BI19: =ROUND(BI18*'Drivers & Assumptions'!C10,0) -> 3334
A21: DTC TOTALS
A22: Subscription Orders | B22: =B17 -> 0 | C22: =C17 -> 0 | D22: =D17 -> 0 | E22: =E17 -> 0 | F22: =F17 -> 0 | G22: =G17 -> 0 | H22: =H17 -> 0 | I22: =I17 -> 0 | ... BI22: =BI17 -> 16048
A23: New One-off Orders | B23: =B16 -> 0 | C23: =C16 -> 0 | D23: =D16 -> 0 | E23: =E16 -> 0 | F23: =F16 -> 0 | G23: =G16 -> 0 | H23: =H16 -> 0 | I23: =I16 -> 0 | ... BI23: =BI16 -> 3440
A24: Repeat One-off Orders | B24: =B19 -> 0 | C24: =C19 -> 0 | D24: =D19 -> 0 | E24: =E19 -> 0 | F24: =F19 -> 0 | G24: =G19 -> 0 | H24: =H19 -> 0 | I24: =I19 -> 0 | ... BI24: =BI19 -> 3334
A25: Total DTC Orders | B25: =B22+B23+B24 -> 0 | C25: =C22+C23+C24 -> 0 | D25: =D22+D23+D24 -> 0 | E25: =E22+E23+E24 -> 0 | F25: =F22+F23+F24 -> 0 | G25: =G22+G23+G24 -> 0 | H25: =H22+H23+H24 -> 0 | I25: =I22+I23+I24 -> 0 | ... BI25: =BI22+BI23+BI24 -> 22822
A27: DTC Modelled Revenue (Orders × AOV) | B27: =B25*'Drivers & Assumptions'!C6 -> 0 | C27: =C25*'Drivers & Assumptions'!C6 -> 0 | D27: =D25*'Drivers & Assumptions'!C6 -> 0 | E27: =E25*'Drivers & Assumptions'!C6 -> 0 | F27: =F25*'Drivers & Assumptions'!C6 -> 0 | G27: =G25*'Drivers & Assumptions'!C6 -> 0 | H27: =H25*'Drivers & Assumptions'!C6 -> 0 | I27: =I25*'Drivers & Assumptions'!C6 -> 0 | J27: =J25*'Drivers & Assumptions'!C6 -> 8442 | K27: =K25*'Drivers & Assumptions'!C6 -> 43722 | L27: =L25*'Drivers & Assumptions'!C6 -> 90972 | M27: =M25*'Drivers & Assumptions'!C6 -> 118314 | N27: =N25*'Drivers & Assumptions'!C6 -> 144900 | O27: =O25*'Drivers & Assumptions'!C6 -> 171108 | P27: =P25*'Drivers & Assumptions'!C6 -> 196686 | Q27: =Q25*'Drivers & Assumptions'!C6 -> 222138 | R27: =R25*'Drivers & Assumptions'!C6 -> 247464 | S27: =S25*'Drivers & Assumptions'!C6 -> 272790 | T27: =T25*'Drivers & Assumptions'!C6 -> 298494 | U27: =U25*'Drivers & Assumptions'!C6 -> 324072 | V27: =V25*'Drivers & Assumptions'!C6 -> 350280 | W27: =W25*'Drivers & Assumptions'!C6 -> 376866 | X27: =X25*'Drivers & Assumptions'!C6 -> 404082 | Y27: =Y25*'Drivers & Assumptions'!C6 -> 432054 | Z27: =Z25*'Drivers & Assumptions'!C6 -> 460656 | AA27: =AA25*'Drivers & Assumptions'!C6 -> 490140 | AB27: =AB25*'Drivers & Assumptions'!C6 -> 520758 | AC27: =AC25*'Drivers & Assumptions'!C6 -> 552384 | AD27: =AD25*'Drivers & Assumptions'!C6 -> 585270 | AE27: =AE25*'Drivers & Assumptions'!C6 -> 619542 | AF27: =AF25*'Drivers & Assumptions'!C6 -> 655074 | AG27: =AG25*'Drivers & Assumptions'!C6 -> 692244 | AH27: =AH25*'Drivers & Assumptions'!C6 -> 730926 | AI27: =AI25*'Drivers & Assumptions'!C6 -> 771372 | AJ27: =AJ25*'Drivers & Assumptions'!C6 -> 813456 | AK27: =AK25*'Drivers & Assumptions'!C6 -> 857556 | AL27: =AL25*'Drivers & Assumptions'!C6 -> 903672 | AM27: =AM25*'Drivers & Assumptions'!C6 -> 952056 | AN27: =AN25*'Drivers & Assumptions'!C6 -> 1002708 | AO27: =AO25*'Drivers & Assumptions'!C6 -> 1055628 | AP27: =AP25*'Drivers & Assumptions'!C6 -> 1111068 | AQ27: =AQ25*'Drivers & Assumptions'!C6 -> 1169280 | AR27: =AR25*'Drivers & Assumptions'!C6 -> 1230390 | AS27: =AS25*'Drivers & Assumptions'!C6 -> 1294398 | AT27: =AT25*'Drivers & Assumptions'!C6 -> 1361430 | AU27: =AU25*'Drivers & Assumptions'!C6 -> 1431864 | AV27: =AV25*'Drivers & Assumptions'!C6 -> 1505826 | AW27: =AW25*'Drivers & Assumptions'!C6 -> 1583190 | AX27: =AX25*'Drivers & Assumptions'!C6 -> 1664460 | AY27: =AY25*'Drivers & Assumptions'!C6 -> 1750014 | AZ27: =AZ25*'Drivers & Assumptions'!C6 -> 1839474 | BA27: =BA25*'Drivers & Assumptions'!C6 -> 1933596 | BB27: =BB25*'Drivers & Assumptions'!C6 -> 2032254 | BC27: =BC25*'Drivers & Assumptions'!C6 -> 2136078 | BD27: =BD25*'Drivers & Assumptions'!C6 -> 2244816 | BE27: =BE25*'Drivers & Assumptions'!C6 -> 2358972 | BF27: =BF25*'Drivers & Assumptions'!C6 -> 2478798 | BG27: =BG25*'Drivers & Assumptions'!C6 -> 2604672 | BH27: =BH25*'Drivers & Assumptions'!C6 -> 2736846 | BI27: =BI25*'Drivers & Assumptions'!C6 -> 2875572
A29: DTC REVENUE (Actuals then Model)
A30: DTC Revenue (AUD) | B30: =B7 -> 37954 | C30: =C7 -> 61361 | D30: =D7 -> 108804 | E30: =E7 -> 57522 | F30: =F7 -> 71229 | G30: =G7 -> 61780 | H30: =H7 -> 62159 | I30: =I7 -> 181457 | J30: =J7 -> 50000 | K30: =K27 -> 43722 | L30: =L27 -> 90972 | M30: =M27 -> 118314 | N30: =N27 -> 144900 | O30: =O27 -> 171108 | P30: =P27 -> 196686 | Q30: =Q27 -> 222138 | R30: =R27 -> 247464 | ... BI30: =BI27 -> 2875572
A31: DTC Total Orders (for COGS calc) | B31: =B8 -> 301 | C31: =C8 -> 487 | D31: =D8 -> 864 | E31: =E8 -> 457 | F31: =F8 -> 565 | G31: =G8 -> 490 | H31: =H8 -> 493 | I31: =I8 -> 1440 | J31: =J25 -> 67 | K31: =K25 -> 347 | L31: =L25 -> 722 | M31: =M25 -> 939 | N31: =N25 -> 1150 | O31: =O25 -> 1358 | P31: =P25 -> 1561 | Q31: =Q25 -> 1763 | ... BI31: =BI25 -> 22822

Sheet Wholesale by Country
A1: PLASMAIDE — Wholesale Revenue by Country
A2: Distributor orders by country — enter actuals in blue cells, model fills forward
B4: Jul-25 | C4: Aug-25 | D4: Sep-25 | E4: Oct-25 | F4: Nov-25 | G4: Dec-25 | H4: Jan-26 | I4: Feb-26 | J4: Mar-26 | K4: Apr-26 | L4: May-26 | M4: Jun-26 | N4: Jul-26 | O4: Aug-26 | P4: Sep-26 | Q4: Oct-26 | R4: Nov-26 | S4: Dec-26 | T4: Jan-27 | U4: Feb-27 | V4: Mar-27 | W4: Apr-27 | X4: May-27 | Y4: Jun-27 | Z4: Jul-27 | AA4: Aug-27 | AB4: Sep-27 | AC4: Oct-27 | AD4: Nov-27 | AE4: Dec-27 | AF4: Jan-28 | AG4: Feb-28 | AH4: Mar-28 | AI4: Apr-28 | AJ4: May-28 | AK4: Jun-28 | AL4: Jul-28 | AM4: Aug-28 | AN4: Sep-28 | AO4: Oct-28 | AP4: Nov-28 | AQ4: Dec-28 | AR4: Jan-29 | AS4: Feb-29 | AT4: Mar-29 | AU4: Apr-29 | AV4: May-29 | AW4: Jun-29 | AX4: Jul-29 | AY4: Aug-29 | AZ4: Sep-29 | BA4: Oct-29 | BB4: Nov-29 | BC4: Dec-29 | BD4: Jan-30 | BE4: Feb-30 | BF4: Mar-30 | BG4: Apr-30 | BH4: May-30 | BI4: Jun-30
A6: WHOLESALE ORDERS BY COUNTRY (Cases per month — enter actuals, model fills forward)
A7: Australia — Cases Ordered | B7: 0 | C7: 0 | D7: 0 | E7: 0 | F7: 0 | G7: 0 | H7: 0 | I7: 0 | J7: =IF(MOD(9,'Drivers & Assumptions'!C26)=0,ROUND('Drivers & Assumptions'!C27*(1+'Drivers & Assumptions'!C28)^0,0),0) -> 5 | K7: =IF(MOD(10,'Drivers & Assumptions'!C26)=0,ROUND('Drivers & Assumptions'!C27*(1+'Drivers & Assumptions'!C28)^0,0),0) -> 0 | L7: =IF(MOD(11,'Drivers & Assumptions'!C26)=0,ROUND('Drivers & Assumptions'!C27*(1+'Drivers & Assumptions'!C28)^0,0),0) -> 0 | M7: =IF(MOD(12,'Drivers & Assumptions'!C26)=0,ROUND('Drivers & Assumptions'!C27*(1+'Drivers & Assumptions'!C28)^0,0),0) -> 5 | N7: =IF(MOD(13,'Drivers & Assumptions'!C26)=0,ROUND('Drivers & Assumptions'!C27*(1+'Drivers & Assumptions'!C28)^1,0),0) -> 0 | O7: =IF(MOD(14,'Drivers & Assumptions'!C26)=0,ROUND('Drivers & Assumptions'!C27*(1+'Drivers & Assumptions'!C28)^1,0),0) -> 0 | P7: =IF(MOD(15,'Drivers & Assumptions'!C26)=0,ROUND('Drivers & Assumptions'!C27*(1+'Drivers & Assumptions'!C28)^1,0),0) -> 6 | Q7: =IF(MOD(16,'Drivers & Assumptions'!C26)=0,ROUND('Drivers & Assumptions'!C27*(1+'Drivers & Assumptions'!C28)^1,0),0) -> 0 | R7: =IF(MOD(17,'Drivers & Assumptions'!C26)=0,ROUND('Drivers & Assumptions'!C27*(1+'Drivers & Assumptions'!C28)^1,0),0) -> 0 | S7: =IF(MOD(18,'Drivers & Assumptions'!C26)=0,ROUND('Drivers & Assumptions'!C27*(1+'Drivers & Assumptions'!C28)^1,0),0) -> 6 | T7: =IF(MOD(19,'Drivers & Assumptions'!C26)=0,ROUND('Drivers & Assumptions'!C27*(1+'Drivers & Assumptions'!C28)^1,0),0) -> 0 | U7: =IF(MOD(20,'Drivers & Assumptions'!C26)=0,ROUND('Drivers & Assumptions'!C27*(1+'Drivers & Assumptions'!C28)^1,0),0) -> 0 | V7: =IF(MOD(21,'Drivers & Assumptions'!C26)=0,ROUND('Drivers & Assumptions'!C27*(1+'Drivers & Assumptions'!C28)^1,0),0) -> 6 | W7: =IF(MOD(22,'Drivers & Assumptions'!C26)=0,ROUND('Drivers & Assumptions'!C27*(1+'Drivers & Assumptions'!C28)^1,0),0) -> 0 | X7: =IF(MOD(23,'Drivers & Assumptions'!C26)=0,ROUND('Drivers & Assumptions'!C27*(1+'Drivers & Assumptions'!C28)^1,0),0) -> 0 | Y7: =IF(MOD(24,'Drivers & Assumptions'!C26)=0,ROUND('Drivers & Assumptions'!C27*(1+'Drivers & Assumptions'!C28)^1,0),0) -> 6 | Z7: =IF(MOD(25,'Drivers & Assumptions'!C26)=0,ROUND('Drivers & Assumptions'!C27*(1+'Drivers & Assumptions'!C28)^2,0),0) -> 0 | AA7: =IF(MOD(26,'Drivers & Assumptions'!C26)=0,ROUND('Drivers & Assumptions'!C27*(1+'Drivers & Assumptions'!C28)^2,0),0) -> 0 | AB7: =IF(MOD(27,'Drivers & Assumptions'!C26)=0,ROUND('Drivers & Assumptions'!C27*(1+'Drivers & Assumptions'!C28)^2,0),0) -> 8 | AC7: =IF(MOD(28,'Drivers & Assumptions'!C26)=0,ROUND('Drivers & Assumptions'!C27*(1+'Drivers & Assumptions'!C28)^2,0),0) -> 0 | AD7: =IF(MOD(29,'Drivers & Assumptions'!C26)=0,ROUND('Drivers & Assumptions'!C27*(1+'Drivers & Assumptions'!C28)^2,0),0) -> 0 | AE7: =IF(MOD(30,'Drivers & Assumptions'!C26)=0,ROUND('Drivers & Assumptions'!C27*(1+'Drivers & Assumptions'!C28)^2,0),0) -> 8 | AF7: =IF(MOD(31,'Drivers & Assumptions'!C26)=0,ROUND('Drivers & Assumptions'!C27*(1+'Drivers & Assumptions'!C28)^2,0),0) -> 0 | AG7: =IF(MOD(32,'Drivers & Assumptions'!C26)=0,ROUND('Drivers & Assumptions'!C27*(1+'Drivers & Assumptions'!C28)^2,0),0) -> 0 | AH7: =IF(MOD(33,'Drivers & Assumptions'!C26)=0,ROUND('Drivers & Assumptions'!C27*(1+'Drivers & Assumptions'!C28)^2,0),0) -> 8 | AI7: =IF(MOD(34,'Drivers & Assumptions'!C26)=0,ROUND('Drivers & Assumptions'!C27*(1+'Drivers & Assumptions'!C28)^2,0),0) -> 0 | AJ7: =IF(MOD(35,'Drivers & Assumptions'!C26)=0,ROUND('Drivers & Assumptions'!C27*(1+'Drivers & Assumptions'!C28)^2,0),0) -> 0 | AK7: =IF(MOD(36,'Drivers & Assumptions'!C26)=0,ROUND('Drivers & Assumptions'!C27*(1+'Drivers & Assumptions'!C28)^2,0),0) -> 8 | AL7: =IF(MOD(37,'Drivers & Assumptions'!C26)=0,ROUND('Drivers & Assumptions'!C27*(1+'Drivers & Assumptions'!C28)^3,0),0) -> 0 | AM7: =IF(MOD(38,'Drivers & Assumptions'!C26)=0,ROUND('Drivers & Assumptions'!C27*(1+'Drivers & Assumptions'!C28)^3,0),0) -> 0 | AN7: =IF(MOD(39,'Drivers & Assumptions'!C26)=0,ROUND('Drivers & Assumptions'!C27*(1+'Drivers & Assumptions'!C28)^3,0),0) -> 10 | AO7: =IF(MOD(40,'Drivers & Assumptions'!C26)=0,ROUND('Drivers & Assumptions'!C27*(1+'Drivers & Assumptions'!C28)^3,0),0) -> 0 | AP7: =IF(MOD(41,'Drivers & Assumptions'!C26)=0,ROUND('Drivers & Assumptions'!C27*(1+'Drivers & Assumptions'!C28)^3,0),0) -> 0 | AQ7: =IF(MOD(42,'Drivers & Assumptions'!C26)=0,ROUND('Drivers & Assumptions'!C27*(1+'Drivers & Assumptions'!C28)^3,0),0) -> 10 | AR7: =IF(MOD(43,'Drivers & Assumptions'!C26)=0,ROUND('Drivers & Assumptions'!C27*(1+'Drivers & Assumptions'!C28)^3,0),0) -> 0 | AS7: =IF(MOD(44,'Drivers & Assumptions'!C26)=0,ROUND('Drivers & Assumptions'!C27*(1+'Drivers & Assumptions'!C28)^3,0),0) -> 0 | AT7: =IF(MOD(45,'Drivers & Assumptions'!C26)=0,ROUND('Drivers & Assumptions'!C27*(1+'Drivers & Assumptions'!C28)^3,0),0) -> 10 | AU7: =IF(MOD(46,'Drivers & Assumptions'!C26)=0,ROUND('Drivers & Assumptions'!C27*(1+'Drivers & Assumptions'!C28)^3,0),0) -> 0 | AV7: =IF(MOD(47,'Drivers & Assumptions'!C26)=0,ROUND('Drivers & Assumptions'!C27*(1+'Drivers & Assumptions'!C28)^3,0),0) -> 0 | AW7: =IF(MOD(48,'Drivers & Assumptions'!C26)=0,ROUND('Drivers & Assumptions'!C27*(1+'Drivers & Assumptions'!C28)^3,0),0) -> 10 | AX7: =IF(MOD(49,'Drivers & Assumptions'!C26)=0,ROUND('Drivers & Assumptions'!C27*(1+'Drivers & Assumptions'!C28)^4,0),0) -> 0 | AY7: =IF(MOD(50,'Drivers & Assumptions'!C26)=0,ROUND('Drivers & Assumptions'!C27*(1+'Drivers & Assumptions'!C28)^4,0),0) -> 0 | AZ7: =IF(MOD(51,'Drivers & Assumptions'!C26)=0,ROUND('Drivers & Assumptions'!C27*(1+'Drivers & Assumptions'!C28)^4,0),0) -> 12 | BA7: =IF(MOD(52,'Drivers & Assumptions'!C26)=0,ROUND('Drivers & Assumptions'!C27*(1+'Drivers & Assumptions'!C28)^4,0),0) -> 0 | BB7: =IF(MOD(53,'Drivers & Assumptions'!C26)=0,ROUND('Drivers & Assumptions'!C27*(1+'Drivers & Assumptions'!C28)^4,0),0) -> 0 | BC7: =IF(MOD(54,'Drivers & Assumptions'!C26)=0,ROUND('Drivers & Assumptions'!C27*(1+'Drivers & Assumptions'!C28)^4,0),0) -> 12 | BD7: =IF(MOD(55,'Drivers & Assumptions'!C26)=0,ROUND('Drivers & Assumptions'!C27*(1+'Drivers & Assumptions'!C28)^4,0),0) -> 0 | BE7: =IF(MOD(56,'Drivers & Assumptions'!C26)=0,ROUND('Drivers & Assumptions'!C27*(1+'Drivers & Assumptions'!C28)^4,0),0) -> 0 | BF7: =IF(MOD(57,'Drivers & Assumptions'!C26)=0,ROUND('Drivers & Assumptions'!C27*(1+'Drivers & Assumptions'!C28)^4,0),0) -> 12 | BG7: =IF(MOD(58,'Drivers & Assumptions'!C26)=0,ROUND('Drivers & Assumptions'!C27*(1+'Drivers & Assumptions'!C28)^4,0),0) -> 0 | BH7: =IF(MOD(59,'Drivers & Assumptions'!C26)=0,ROUND('Drivers & Assumptions'!C27*(1+'Drivers & Assumptions'!C28)^4,0),0) -> 0 | BI7: =IF(MOD(60,'Drivers & Assumptions'!C26)=0,ROUND('Drivers & Assumptions'!C27*(1+'Drivers & Assumptions'!C28)^4,0),0) -> 12
A8: New Zealand — Cases Ordered | B8: 0 | C8: 0 | D8: 0 | E8: 0 | F8: 0 | G8: 0 | H8: 0 | I8: 0 | J8: =IF(MOD(9,'Drivers & Assumptions'!C26)=0,ROUND('Drivers & Assumptions'!C27*(1+'Drivers & Assumptions'!C28)^0,0),0) -> 5 | K8: =IF(MOD(10,'Drivers & Assumptions'!C26)=0,ROUND('Drivers & Assumptions'!C27*(1+'Drivers & Assumptions'!C28)^0,0),0) -> 0 | L8: =IF(MOD(11,'Drivers & Assumptions'!C26)=0,ROUND('Drivers & Assumptions'!C27*(1+'Drivers & Assumptions'!C28)^0,0),0) -> 0 | M8: =IF(MOD(12,'Drivers & Assumptions'!C26)=0,ROUND('Drivers & Assumptions'!C27*(1+'Drivers & Assumptions'!C28)^0,0),0) -> 5 | N8: =IF(MOD(13,'Drivers & Assumptions'!C26)=0,ROUND('Drivers & Assumptions'!C27*(1+'Drivers & Assumptions'!C28)^1,0),0) -> 0 | O8: =IF(MOD(14,'Drivers & Assumptions'!C26)=0,ROUND('Drivers & Assumptions'!C27*(1+'Drivers & Assumptions'!C28)^1,0),0) -> 0 | P8: =IF(MOD(15,'Drivers & Assumptions'!C26)=0,ROUND('Drivers & Assumptions'!C27*(1+'Drivers & Assumptions'!C28)^1,0),0) -> 6 | Q8: =IF(MOD(16,'Drivers & Assumptions'!C26)=0,ROUND('Drivers & Assumptions'!C27*(1+'Drivers & Assumptions'!C28)^1,0),0) -> 0 | R8: =IF(MOD(17,'Drivers & Assumptions'!C26)=0,ROUND('Drivers & Assumptions'!C27*(1+'Drivers & Assumptions'!C28)^1,0),0) -> 0 | S8: =IF(MOD(18,'Drivers & Assumptions'!C26)=0,ROUND('Drivers & Assumptions'!C27*(1+'Drivers & Assumptions'!C28)^1,0),0) -> 6 | T8: =IF(MOD(19,'Drivers & Assumptions'!C26)=0,ROUND('Drivers & Assumptions'!C27*(1+'Drivers & Assumptions'!C28)^1,0),0) -> 0 | U8: =IF(MOD(20,'Drivers & Assumptions'!C26)=0,ROUND('Drivers & Assumptions'!C27*(1+'Drivers & Assumptions'!C28)^1,0),0) -> 0 | V8: =IF(MOD(21,'Drivers & Assumptions'!C26)=0,ROUND('Drivers & Assumptions'!C27*(1+'Drivers & Assumptions'!C28)^1,0),0) -> 6 | W8: =IF(MOD(22,'Drivers & Assumptions'!C26)=0,ROUND('Drivers & Assumptions'!C27*(1+'Drivers & Assumptions'!C28)^1,0),0) -> 0 | X8: =IF(MOD(23,'Drivers & Assumptions'!C26)=0,ROUND('Drivers & Assumptions'!C27*(1+'Drivers & Assumptions'!C28)^1,0),0) -> 0 | Y8: =IF(MOD(24,'Drivers & Assumptions'!C26)=0,ROUND('Drivers & Assumptions'!C27*(1+'Drivers & Assumptions'!C28)^1,0),0) -> 6 | Z8: =IF(MOD(25,'Drivers & Assumptions'!C26)=0,ROUND('Drivers & Assumptions'!C27*(1+'Drivers & Assumptions'!C28)^2,0),0) -> 0 | AA8: =IF(MOD(26,'Drivers & Assumptions'!C26)=0,ROUND('Drivers & Assumptions'!C27*(1+'Drivers & Assumptions'!C28)^2,0),0) -> 0 | AB8: =IF(MOD(27,'Drivers & Assumptions'!C26)=0,ROUND('Drivers & Assumptions'!C27*(1+'Drivers & Assumptions'!C28)^2,0),0) -> 8 | AC8: =IF(MOD(28,'Drivers & Assumptions'!C26)=0,ROUND('Drivers & Assumptions'!C27*(1+'Drivers & Assumptions'!C28)^2,0),0) -> 0 | AD8: =IF(MOD(29,'Drivers & Assumptions'!C26)=0,ROUND('Drivers & Assumptions'!C27*(1+'Drivers & Assumptions'!C28)^2,0),0) -> 0 | AE8: =IF(MOD(30,'Drivers & Assumptions'!C26)=0,ROUND('Drivers & Assumptions'!C27*(1+'Drivers & Assumptions'!C28)^2,0),0) -> 8 | AF8: =IF(MOD(31,'Drivers & Assumptions'!C26)=0,ROUND('Drivers & Assumptions'!C27*(1+'Drivers & Assumptions'!C28)^2,0),0) -> 0 | AG8: =IF(MOD(32,'Drivers & Assumptions'!C26)=0,ROUND('Drivers & Assumptions'!C27*(1+'Drivers & Assumptions'!C28)^2,0),0) -> 0 | AH8: =IF(MOD(33,'Drivers & Assumptions'!C26)=0,ROUND('Drivers & Assumptions'!C27*(1+'Drivers & Assumptions'!C28)^2,0),0) -> 8 | AI8: =IF(MOD(34,'Drivers & Assumptions'!C26)=0,ROUND('Drivers & Assumptions'!C27*(1+'Drivers & Assumptions'!C28)^2,0),0) -> 0 | AJ8: =IF(MOD(35,'Drivers & Assumptions'!C26)=0,ROUND('Drivers & Assumptions'!C27*(1+'Drivers & Assumptions'!C28)^2,0),0) -> 0 | AK8: =IF(MOD(36,'Drivers & Assumptions'!C26)=0,ROUND('Drivers & Assumptions'!C27*(1+'Drivers & Assumptions'!C28)^2,0),0) -> 8 | AL8: =IF(MOD(37,'Drivers & Assumptions'!C26)=0,ROUND('Drivers & Assumptions'!C27*(1+'Drivers & Assumptions'!C28)^3,0),0) -> 0 | AM8: =IF(MOD(38,'Drivers & Assumptions'!C26)=0,ROUND('Drivers & Assumptions'!C27*(1+'Drivers & Assumptions'!C28)^3,0),0) -> 0 | AN8: =IF(MOD(39,'Drivers & Assumptions'!C26)=0,ROUND('Drivers & Assumptions'!C27*(1+'Drivers & Assumptions'!C28)^3,0),0) -> 10 | AO8: =IF(MOD(40,'Drivers & Assumptions'!C26)=0,ROUND('Drivers & Assumptions'!C27*(1+'Drivers & Assumptions'!C28)^3,0),0) -> 0 | AP8: =IF(MOD(41,'Drivers & Assumptions'!C26)=0,ROUND('Drivers & Assumptions'!C27*(1+'Drivers & Assumptions'!C28)^3,0),0) -> 0 | AQ8: =IF(MOD(42,'Drivers & Assumptions'!C26)=0,ROUND('Drivers & Assumptions'!C27*(1+'Drivers & Assumptions'!C28)^3,0),0) -> 10 | AR8: =IF(MOD(43,'Drivers & Assumptions'!C26)=0,ROUND('Drivers & Assumptions'!C27*(1+'Drivers & Assumptions'!C28)^3,0),0) -> 0 | AS8: =IF(MOD(44,'Drivers & Assumptions'!C26)=0,ROUND('Drivers & Assumptions'!C27*(1+'Drivers & Assumptions'!C28)^3,0),0) -> 0 | AT8: =IF(MOD(45,'Drivers & Assumptions'!C26)=0,ROUND('Drivers & Assumptions'!C27*(1+'Drivers & Assumptions'!C28)^3,0),0) -> 10 | AU8: =IF(MOD(46,'Drivers & Assumptions'!C26)=0,ROUND('Drivers & Assumptions'!C27*(1+'Drivers & Assumptions'!C28)^3,0),0) -> 0 | AV8: =IF(MOD(47,'Drivers & Assumptions'!C26)=0,ROUND('Drivers & Assumptions'!C27*(1+'Drivers & Assumptions'!C28)^3,0),0) -> 0 | AW8: =IF(MOD(48,'Drivers & Assumptions'!C26)=0,ROUND('Drivers & Assumptions'!C27*(1+'Drivers & Assumptions'!C28)^3,0),0) -> 10 | AX8: =IF(MOD(49,'Drivers & Assumptions'!C26)=0,ROUND('Drivers & Assumptions'!C27*(1+'Drivers & Assumptions'!C28)^4,0),0) -> 0 | AY8: =IF(MOD(50,'Drivers & Assumptions'!C26)=0,ROUND('Drivers & Assumptions'!C27*(1+'Drivers & Assumptions'!C28)^4,0),0) -> 0 | AZ8: =IF(MOD(51,'Drivers & Assumptions'!C26)=0,ROUND('Drivers & Assumptions'!C27*(1+'Drivers & Assumptions'!C28)^4,0),0) -> 12 | BA8: =IF(MOD(52,'Drivers & Assumptions'!C26)=0,ROUND('Drivers & Assumptions'!C27*(1+'Drivers & Assumptions'!C28)^4,0),0) -> 0 | BB8: =IF(MOD(53,'Drivers & Assumptions'!C26)=0,ROUND('Drivers & Assumptions'!C27*(1+'Drivers & Assumptions'!C28)^4,0),0) -> 0 | BC8: =IF(MOD(54,'Drivers & Assumptions'!C26)=0,ROUND('Drivers & Assumptions'!C27*(1+'Drivers & Assumptions'!C28)^4,0),0) -> 12 | BD8: =IF(MOD(55,'Drivers & Assumptions'!C26)=0,ROUND('Drivers & Assumptions'!C27*(1+'Drivers & Assumptions'!C28)^4,0),0) -> 0 | BE8: =IF(MOD(56,'Drivers & Assumptions'!C26)=0,ROUND('Drivers & Assumptions'!C27*(1+'Drivers & Assumptions'!C28)^4,0),0) -> 0 | BF8: =IF(MOD(57,'Drivers & Assumptions'!C26)=0,ROUND('Drivers & Assumptions'!C27*(1+'Drivers & Assumptions'!C28)^4,0),0) -> 12 | BG8: =IF(MOD(58,'Drivers & Assumptions'!C26)=0,ROUND('Drivers & Assumptions'!C27*(1+'Drivers & Assumptions'!C28)^4,0),0) -> 0 | BH8: =IF(MOD(59,'Drivers & Assumptions'!C26)=0,ROUND('Drivers & Assumptions'!C27*(1+'Drivers & Assumptions'!C28)^4,0),0) -> 0 | BI8: =IF(MOD(60,'Drivers & Assumptions'!C26)=0,ROUND('Drivers & Assumptions'!C27*(1+'Drivers & Assumptions'!C28)^4,0),0) -> 12
A9: United Kingdom — Cases Ordered | B9: 0 | C9: 0 | D9: 0 | E9: 0 | F9: 0 | G9: 0 | H9: 0 | I9: 0 | J9: =IF(MOD(9,'Drivers & Assumptions'!C26)=0,ROUND('Drivers & Assumptions'!C27*(1+'Drivers & Assumptions'!C28)^0,0),0) -> 5 | K9: =IF(MOD(10,'Drivers & Assumptions'!C26)=0,ROUND('Drivers & Assumptions'!C27*(1+'Drivers & Assumptions'!C28)^0,0),0) -> 0 | L9: =IF(MOD(11,'Drivers & Assumptions'!C26)=0,ROUND('Drivers & Assumptions'!C27*(1+'Drivers & Assumptions'!C28)^0,0),0) -> 0 | M9: =IF(MOD(12,'Drivers & Assumptions'!C26)=0,ROUND('Drivers & Assumptions'!C27*(1+'Drivers & Assumptions'!C28)^0,0),0) -> 5 | N9: =IF(MOD(13,'Drivers & Assumptions'!C26)=0,ROUND('Drivers & Assumptions'!C27*(1+'Drivers & Assumptions'!C28)^1,0),0) -> 0 | O9: =IF(MOD(14,'Drivers & Assumptions'!C26)=0,ROUND('Drivers & Assumptions'!C27*(1+'Drivers & Assumptions'!C28)^1,0),0) -> 0 | P9: =IF(MOD(15,'Drivers & Assumptions'!C26)=0,ROUND('Drivers & Assumptions'!C27*(1+'Drivers & Assumptions'!C28)^1,0),0) -> 6 | Q9: =IF(MOD(16,'Drivers & Assumptions'!C26)=0,ROUND('Drivers & Assumptions'!C27*(1+'Drivers & Assumptions'!C28)^1,0),0) -> 0 | R9: =IF(MOD(17,'Drivers & Assumptions'!C26)=0,ROUND('Drivers & Assumptions'!C27*(1+'Drivers & Assumptions'!C28)^1,0),0) -> 0 | S9: =IF(MOD(18,'Drivers & Assumptions'!C26)=0,ROUND('Drivers & Assumptions'!C27*(1+'Drivers & Assumptions'!C28)^1,0),0) -> 6 | T9: =IF(MOD(19,'Drivers & Assumptions'!C26)=0,ROUND('Drivers & Assumptions'!C27*(1+'Drivers & Assumptions'!C28)^1,0),0) -> 0 | U9: =IF(MOD(20,'Drivers & Assumptions'!C26)=0,ROUND('Drivers & Assumptions'!C27*(1+'Drivers & Assumptions'!C28)^1,0),0) -> 0 | V9: =IF(MOD(21,'Drivers & Assumptions'!C26)=0,ROUND('Drivers & Assumptions'!C27*(1+'Drivers & Assumptions'!C28)^1,0),0) -> 6 | W9: =IF(MOD(22,'Drivers & Assumptions'!C26)=0,ROUND('Drivers & Assumptions'!C27*(1+'Drivers & Assumptions'!C28)^1,0),0) -> 0 | X9: =IF(MOD(23,'Drivers & Assumptions'!C26)=0,ROUND('Drivers & Assumptions'!C27*(1+'Drivers & Assumptions'!C28)^1,0),0) -> 0 | Y9: =IF(MOD(24,'Drivers & Assumptions'!C26)=0,ROUND('Drivers & Assumptions'!C27*(1+'Drivers & Assumptions'!C28)^1,0),0) -> 6 | Z9: =IF(MOD(25,'Drivers & Assumptions'!C26)=0,ROUND('Drivers & Assumptions'!C27*(1+'Drivers & Assumptions'!C28)^2,0),0) -> 0 | AA9: =IF(MOD(26,'Drivers & Assumptions'!C26)=0,ROUND('Drivers & Assumptions'!C27*(1+'Drivers & Assumptions'!C28)^2,0),0) -> 0 | AB9: =IF(MOD(27,'Drivers & Assumptions'!C26)=0,ROUND('Drivers & Assumptions'!C27*(1+'Drivers & Assumptions'!C28)^2,0),0) -> 8 | AC9: =IF(MOD(28,'Drivers & Assumptions'!C26)=0,ROUND('Drivers & Assumptions'!C27*(1+'Drivers & Assumptions'!C28)^2,0),0) -> 0 | AD9: =IF(MOD(29,'Drivers & Assumptions'!C26)=0,ROUND('Drivers & Assumptions'!C27*(1+'Drivers & Assumptions'!C28)^2,0),0) -> 0 | AE9: =IF(MOD(30,'Drivers & Assumptions'!C26)=0,ROUND('Drivers & Assumptions'!C27*(1+'Drivers & Assumptions'!C28)^2,0),0) -> 8 | AF9: =IF(MOD(31,'Drivers & Assumptions'!C26)=0,ROUND('Drivers & Assumptions'!C27*(1+'Drivers & Assumptions'!C28)^2,0),0) -> 0 | AG9: =IF(MOD(32,'Drivers & Assumptions'!C26)=0,ROUND('Drivers & Assumptions'!C27*(1+'Drivers & Assumptions'!C28)^2,0),0) -> 0 | AH9: =IF(MOD(33,'Drivers & Assumptions'!C26)=0,ROUND('Drivers & Assumptions'!C27*(1+'Drivers & Assumptions'!C28)^2,0),0) -> 8 | AI9: =IF(MOD(34,'Drivers & Assumptions'!C26)=0,ROUND('Drivers & Assumptions'!C27*(1+'Drivers & Assumptions'!C28)^2,0),0) -> 0 | AJ9: =IF(MOD(35,'Drivers & Assumptions'!C26)=0,ROUND('Drivers & Assumptions'!C27*(1+'Drivers & Assumptions'!C28)^2,0),0) -> 0 | AK9: =IF(MOD(36,'Drivers & Assumptions'!C26)=0,ROUND('Drivers & Assumptions'!C27*(1+'Drivers & Assumptions'!C28)^2,0),0) -> 8 | AL9: =IF(MOD(37,'Drivers & Assumptions'!C26)=0,ROUND('Drivers & Assumptions'!C27*(1+'Drivers & Assumptions'!C28)^3,0),0) -> 0 | AM9: =IF(MOD(38,'Drivers & Assumptions'!C26)=0,ROUND('Drivers & Assumptions'!C27*(1+'Drivers & Assumptions'!C28)^3,0),0) -> 0 | AN9: =IF(MOD(39,'Drivers & Assumptions'!C26)=0,ROUND('Drivers & Assumptions'!C27*(1+'Drivers & Assumptions'!C28)^3,0),0) -> 10 | AO9: =IF(MOD(40,'Drivers & Assumptions'!C26)=0,ROUND('Drivers & Assumptions'!C27*(1+'Drivers & Assumptions'!C28)^3,0),0) -> 0 | AP9: =IF(MOD(41,'Drivers & Assumptions'!C26)=0,ROUND('Drivers & Assumptions'!C27*(1+'Drivers & Assumptions'!C28)^3,0),0) -> 0 | AQ9: =IF(MOD(42,'Drivers & Assumptions'!C26)=0,ROUND('Drivers & Assumptions'!C27*(1+'Drivers & Assumptions'!C28)^3,0),0) -> 10 | AR9: =IF(MOD(43,'Drivers & Assumptions'!C26)=0,ROUND('Drivers & Assumptions'!C27*(1+'Drivers & Assumptions'!C28)^3,0),0) -> 0 | AS9: =IF(MOD(44,'Drivers & Assumptions'!C26)=0,ROUND('Drivers & Assumptions'!C27*(1+'Drivers & Assumptions'!C28)^3,0),0) -> 0 | AT9: =IF(MOD(45,'Drivers & Assumptions'!C26)=0,ROUND('Drivers & Assumptions'!C27*(1+'Drivers & Assumptions'!C28)^3,0),0) -> 10 | AU9: =IF(MOD(46,'Drivers & Assumptions'!C26)=0,ROUND('Drivers & Assumptions'!C27*(1+'Drivers & Assumptions'!C28)^3,0),0) -> 0 | AV9: =IF(MOD(47,'Drivers & Assumptions'!C26)=0,ROUND('Drivers & Assumptions'!C27*(1+'Drivers & Assumptions'!C28)^3,0),0) -> 0 | AW9: =IF(MOD(48,'Drivers & Assumptions'!C26)=0,ROUND('Drivers & Assumptions'!C27*(1+'Drivers & Assumptions'!C28)^3,0),0) -> 10 | AX9: =IF(MOD(49,'Drivers & Assumptions'!C26)=0,ROUND('Drivers & Assumptions'!C27*(1+'Drivers & Assumptions'!C28)^4,0),0) -> 0 | AY9: =IF(MOD(50,'Drivers & Assumptions'!C26)=0,ROUND('Drivers & Assumptions'!C27*(1+'Drivers & Assumptions'!C28)^4,0),0) -> 0 | AZ9: =IF(MOD(51,'Drivers & Assumptions'!C26)=0,ROUND('Drivers & Assumptions'!C27*(1+'Drivers & Assumptions'!C28)^4,0),0) -> 12 | BA9: =IF(MOD(52,'Drivers & Assumptions'!C26)=0,ROUND('Drivers & Assumptions'!C27*(1+'Drivers & Assumptions'!C28)^4,0),0) -> 0 | BB9: =IF(MOD(53,'Drivers & Assumptions'!C26)=0,ROUND('Drivers & Assumptions'!C27*(1+'Drivers & Assumptions'!C28)^4,0),0) -> 0 | BC9: =IF(MOD(54,'Drivers & Assumptions'!C26)=0,ROUND('Drivers & Assumptions'!C27*(1+'Drivers & Assumptions'!C28)^4,0),0) -> 12 | BD9: =IF(MOD(55,'Drivers & Assumptions'!C26)=0,ROUND('Drivers & Assumptions'!C27*(1+'Drivers & Assumptions'!C28)^4,0),0) -> 0 | BE9: =IF(MOD(56,'Drivers & Assumptions'!C26)=0,ROUND('Drivers & Assumptions'!C27*(1+'Drivers & Assumptions'!C28)^4,0),0) -> 0 | BF9: =IF(MOD(57,'Drivers & Assumptions'!C26)=0,ROUND('Drivers & Assumptions'!C27*(1+'Drivers & Assumptions'!C28)^4,0),0) -> 12 | BG9: =IF(MOD(58,'Drivers & Assumptions'!C26)=0,ROUND('Drivers & Assumptions'!C27*(1+'Drivers & Assumptions'!C28)^4,0),0) -> 0 | BH9: =IF(MOD(59,'Drivers & Assumptions'!C26)=0,ROUND('Drivers & Assumptions'!C27*(1+'Drivers & Assumptions'!C28)^4,0),0) -> 0 | BI9: =IF(MOD(60,'Drivers & Assumptions'!C26)=0,ROUND('Drivers & Assumptions'!C27*(1+'Drivers & Assumptions'!C28)^4,0),0) -> 12
A10: United States — Cases Ordered | B10: 0 | C10: 0 | D10: 0 | E10: 0 | F10: 0 | G10: 0 | H10: 0 | I10: 0 | J10: =IF(MOD(9,'Drivers & Assumptions'!C26)=0,ROUND('Drivers & Assumptions'!C27*(1+'Drivers & Assumptions'!C28)^0,0),0) -> 5 | K10: =IF(MOD(10,'Drivers & Assumptions'!C26)=0,ROUND('Drivers & Assumptions'!C27*(1+'Drivers & Assumptions'!C28)^0,0),0) -> 0 | L10: =IF(MOD(11,'Drivers & Assumptions'!C26)=0,ROUND('Drivers & Assumptions'!C27*(1+'Drivers & Assumptions'!C28)^0,0),0) -> 0 | M10: =IF(MOD(12,'Drivers & Assumptions'!C26)=0,ROUND('Drivers & Assumptions'!C27*(1+'Drivers & Assumptions'!C28)^0,0),0) -> 5 | N10: =IF(MOD(13,'Drivers & Assumptions'!C26)=0,ROUND('Drivers & Assumptions'!C27*(1+'Drivers & Assumptions'!C28)^1,0),0) -> 0 | O10: =IF(MOD(14,'Drivers & Assumptions'!C26)=0,ROUND('Drivers & Assumptions'!C27*(1+'Drivers & Assumptions'!C28)^1,0),0) -> 0 | P10: =IF(MOD(15,'Drivers & Assumptions'!C26)=0,ROUND('Drivers & Assumptions'!C27*(1+'Drivers & Assumptions'!C28)^1,0),0) -> 6 | Q10: =IF(MOD(16,'Drivers & Assumptions'!C26)=0,ROUND('Drivers & Assumptions'!C27*(1+'Drivers & Assumptions'!C28)^1,0),0) -> 0 | R10: =IF(MOD(17,'Drivers & Assumptions'!C26)=0,ROUND('Drivers & Assumptions'!C27*(1+'Drivers & Assumptions'!C28)^1,0),0) -> 0 | S10: =IF(MOD(18,'Drivers & Assumptions'!C26)=0,ROUND('Drivers & Assumptions'!C27*(1+'Drivers & Assumptions'!C28)^1,0),0) -> 6 | T10: =IF(MOD(19,'Drivers & Assumptions'!C26)=0,ROUND('Drivers & Assumptions'!C27*(1+'Drivers & Assumptions'!C28)^1,0),0) -> 0 | U10: =IF(MOD(20,'Drivers & Assumptions'!C26)=0,ROUND('Drivers & Assumptions'!C27*(1+'Drivers & Assumptions'!C28)^1,0),0) -> 0 | V10: =IF(MOD(21,'Drivers & Assumptions'!C26)=0,ROUND('Drivers & Assumptions'!C27*(1+'Drivers & Assumptions'!C28)^1,0),0) -> 6 | W10: =IF(MOD(22,'Drivers & Assumptions'!C26)=0,ROUND('Drivers & Assumptions'!C27*(1+'Drivers & Assumptions'!C28)^1,0),0) -> 0 | X10: =IF(MOD(23,'Drivers & Assumptions'!C26)=0,ROUND('Drivers & Assumptions'!C27*(1+'Drivers & Assumptions'!C28)^1,0),0) -> 0 | Y10: =IF(MOD(24,'Drivers & Assumptions'!C26)=0,ROUND('Drivers & Assumptions'!C27*(1+'Drivers & Assumptions'!C28)^1,0),0) -> 6 | Z10: =IF(MOD(25,'Drivers & Assumptions'!C26)=0,ROUND('Drivers & Assumptions'!C27*(1+'Drivers & Assumptions'!C28)^2,0),0) -> 0 | AA10: =IF(MOD(26,'Drivers & Assumptions'!C26)=0,ROUND('Drivers & Assumptions'!C27*(1+'Drivers & Assumptions'!C28)^2,0),0) -> 0 | AB10: =IF(MOD(27,'Drivers & Assumptions'!C26)=0,ROUND('Drivers & Assumptions'!C27*(1+'Drivers & Assumptions'!C28)^2,0),0) -> 8 | AC10: =IF(MOD(28,'Drivers & Assumptions'!C26)=0,ROUND('Drivers & Assumptions'!C27*(1+'Drivers & Assumptions'!C28)^2,0),0) -> 0 | AD10: =IF(MOD(29,'Drivers & Assumptions'!C26)=0,ROUND('Drivers & Assumptions'!C27*(1+'Drivers & Assumptions'!C28)^2,0),0) -> 0 | AE10: =IF(MOD(30,'Drivers & Assumptions'!C26)=0,ROUND('Drivers & Assumptions'!C27*(1+'Drivers & Assumptions'!C28)^2,0),0) -> 8 | AF10: =IF(MOD(31,'Drivers & Assumptions'!C26)=0,ROUND('Drivers & Assumptions'!C27*(1+'Drivers & Assumptions'!C28)^2,0),0) -> 0 | AG10: =IF(MOD(32,'Drivers & Assumptions'!C26)=0,ROUND('Drivers & Assumptions'!C27*(1+'Drivers & Assumptions'!C28)^2,0),0) -> 0 | AH10: =IF(MOD(33,'Drivers & Assumptions'!C26)=0,ROUND('Drivers & Assumptions'!C27*(1+'Drivers & Assumptions'!C28)^2,0),0) -> 8 | AI10: =IF(MOD(34,'Drivers & Assumptions'!C26)=0,ROUND('Drivers & Assumptions'!C27*(1+'Drivers & Assumptions'!C28)^2,0),0) -> 0 | AJ10: =IF(MOD(35,'Drivers & Assumptions'!C26)=0,ROUND('Drivers & Assumptions'!C27*(1+'Drivers & Assumptions'!C28)^2,0),0) -> 0 | AK10: =IF(MOD(36,'Drivers & Assumptions'!C26)=0,ROUND('Drivers & Assumptions'!C27*(1+'Drivers & Assumptions'!C28)^2,0),0) -> 8 | AL10: =IF(MOD(37,'Drivers & Assumptions'!C26)=0,ROUND('Drivers & Assumptions'!C27*(1+'Drivers & Assumptions'!C28)^3,0),0) -> 0 | AM10: =IF(MOD(38,'Drivers & Assumptions'!C26)=0,ROUND('Drivers & Assumptions'!C27*(1+'Drivers & Assumptions'!C28)^3,0),0) -> 0 | AN10: =IF(MOD(39,'Drivers & Assumptions'!C26)=0,ROUND('Drivers & Assumptions'!C27*(1+'Drivers & Assumptions'!C28)^3,0),0) -> 10 | AO10: =IF(MOD(40,'Drivers & Assumptions'!C26)=0,ROUND('Drivers & Assumptions'!C27*(1+'Drivers & Assumptions'!C28)^3,0),0) -> 0 | AP10: =IF(MOD(41,'Drivers & Assumptions'!C26)=0,ROUND('Drivers & Assumptions'!C27*(1+'Drivers & Assumptions'!C28)^3,0),0) -> 0 | AQ10: =IF(MOD(42,'Drivers & Assumptions'!C26)=0,ROUND('Drivers & Assumptions'!C27*(1+'Drivers & Assumptions'!C28)^3,0),0) -> 10 | AR10: =IF(MOD(43,'Drivers & Assumptions'!C26)=0,ROUND('Drivers & Assumptions'!C27*(1+'Drivers & Assumptions'!C28)^3,0),0) -> 0 | AS10: =IF(MOD(44,'Drivers & Assumptions'!C26)=0,ROUND('Drivers & Assumptions'!C27*(1+'Drivers & Assumptions'!C28)^3,0),0) -> 0 | AT10: =IF(MOD(45,'Drivers & Assumptions'!C26)=0,ROUND('Drivers & Assumptions'!C27*(1+'Drivers & Assumptions'!C28)^3,0),0) -> 10 | AU10: =IF(MOD(46,'Drivers & Assumptions'!C26)=0,ROUND('Drivers & Assumptions'!C27*(1+'Drivers & Assumptions'!C28)^3,0),0) -> 0 | AV10: =IF(MOD(47,'Drivers & Assumptions'!C26)=0,ROUND('Drivers & Assumptions'!C27*(1+'Drivers & Assumptions'!C28)^3,0),0) -> 0 | AW10: =IF(MOD(48,'Drivers & Assumptions'!C26)=0,ROUND('Drivers & Assumptions'!C27*(1+'Drivers & Assumptions'!C28)^3,0),0) -> 10 | AX10: =IF(MOD(49,'Drivers & Assumptions'!C26)=0,ROUND('Drivers & Assumptions'!C27*(1+'Drivers & Assumptions'!C28)^4,0),0) -> 0 | AY10: =IF(MOD(50,'Drivers & Assumptions'!C26)=0,ROUND('Drivers & Assumptions'!C27*(1+'Drivers & Assumptions'!C28)^4,0),0) -> 0 | AZ10: =IF(MOD(51,'Drivers & Assumptions'!C26)=0,ROUND('Drivers & Assumptions'!C27*(1+'Drivers & Assumptions'!C28)^4,0),0) -> 12 | BA10: =IF(MOD(52,'Drivers & Assumptions'!C26)=0,ROUND('Drivers & Assumptions'!C27*(1+'Drivers & Assumptions'!C28)^4,0),0) -> 0 | BB10: =IF(MOD(53,'Drivers & Assumptions'!C26)=0,ROUND('Drivers & Assumptions'!C27*(1+'Drivers & Assumptions'!C28)^4,0),0) -> 0 | BC10: =IF(MOD(54,'Drivers & Assumptions'!C26)=0,ROUND('Drivers & Assumptions'!C27*(1+'Drivers & Assumptions'!C28)^4,0),0) -> 12 | BD10: =IF(MOD(55,'Drivers & Assumptions'!C26)=0,ROUND('Drivers & Assumptions'!C27*(1+'Drivers & Assumptions'!C28)^4,0),0) -> 0 | BE10: =IF(MOD(56,'Drivers & Assumptions'!C26)=0,ROUND('Drivers & Assumptions'!C27*(1+'Drivers & Assumptions'!C28)^4,0),0) -> 0 | BF10: =IF(MOD(57,'Drivers & Assumptions'!C26)=0,ROUND('Drivers & Assumptions'!C27*(1+'Drivers & Assumptions'!C28)^4,0),0) -> 12 | BG10: =IF(MOD(58,'Drivers & Assumptions'!C26)=0,ROUND('Drivers & Assumptions'!C27*(1+'Drivers & Assumptions'!C28)^4,0),0) -> 0 | BH10: =IF(MOD(59,'Drivers & Assumptions'!C26)=0,ROUND('Drivers & Assumptions'!C27*(1+'Drivers & Assumptions'!C28)^4,0),0) -> 0 | BI10: =IF(MOD(60,'Drivers & Assumptions'!C26)=0,ROUND('Drivers & Assumptions'!C27*(1+'Drivers & Assumptions'!C28)^4,0),0) -> 12
A11: Canada — Cases Ordered | B11: 0 | C11: 0 | D11: 0 | E11: 0 | F11: 0 | G11: 0 | H11: 0 | I11: 0 | J11: =IF(MOD(9,'Drivers & Assumptions'!C26)=0,ROUND('Drivers & Assumptions'!C27*(1+'Drivers & Assumptions'!C28)^0,0),0) -> 5 | K11: =IF(MOD(10,'Drivers & Assumptions'!C26)=0,ROUND('Drivers & Assumptions'!C27*(1+'Drivers & Assumptions'!C28)^0,0),0) -> 0 | L11: =IF(MOD(11,'Drivers & Assumptions'!C26)=0,ROUND('Drivers & Assumptions'!C27*(1+'Drivers & Assumptions'!C28)^0,0),0) -> 0 | M11: =IF(MOD(12,'Drivers & Assumptions'!C26)=0,ROUND('Drivers & Assumptions'!C27*(1+'Drivers & Assumptions'!C28)^0,0),0) -> 5 | N11: =IF(MOD(13,'Drivers & Assumptions'!C26)=0,ROUND('Drivers & Assumptions'!C27*(1+'Drivers & Assumptions'!C28)^1,0),0) -> 0 | O11: =IF(MOD(14,'Drivers & Assumptions'!C26)=0,ROUND('Drivers & Assumptions'!C27*(1+'Drivers & Assumptions'!C28)^1,0),0) -> 0 | P11: =IF(MOD(15,'Drivers & Assumptions'!C26)=0,ROUND('Drivers & Assumptions'!C27*(1+'Drivers & Assumptions'!C28)^1,0),0) -> 6 | Q11: =IF(MOD(16,'Drivers & Assumptions'!C26)=0,ROUND('Drivers & Assumptions'!C27*(1+'Drivers & Assumptions'!C28)^1,0),0) -> 0 | R11: =IF(MOD(17,'Drivers & Assumptions'!C26)=0,ROUND('Drivers & Assumptions'!C27*(1+'Drivers & Assumptions'!C28)^1,0),0) -> 0 | S11: =IF(MOD(18,'Drivers & Assumptions'!C26)=0,ROUND('Drivers & Assumptions'!C27*(1+'Drivers & Assumptions'!C28)^1,0),0) -> 6 | T11: =IF(MOD(19,'Drivers & Assumptions'!C26)=0,ROUND('Drivers & Assumptions'!C27*(1+'Drivers & Assumptions'!C28)^1,0),0) -> 0 | U11: =IF(MOD(20,'Drivers & Assumptions'!C26)=0,ROUND('Drivers & Assumptions'!C27*(1+'Drivers & Assumptions'!C28)^1,0),0) -> 0 | V11: =IF(MOD(21,'Drivers & Assumptions'!C26)=0,ROUND('Drivers & Assumptions'!C27*(1+'Drivers & Assumptions'!C28)^1,0),0) -> 6 | W11: =IF(MOD(22,'Drivers & Assumptions'!C26)=0,ROUND('Drivers & Assumptions'!C27*(1+'Drivers & Assumptions'!C28)^1,0),0) -> 0 | X11: =IF(MOD(23,'Drivers & Assumptions'!C26)=0,ROUND('Drivers & Assumptions'!C27*(1+'Drivers & Assumptions'!C28)^1,0),0) -> 0 | Y11: =IF(MOD(24,'Drivers & Assumptions'!C26)=0,ROUND('Drivers & Assumptions'!C27*(1+'Drivers & Assumptions'!C28)^1,0),0) -> 6 | Z11: =IF(MOD(25,'Drivers & Assumptions'!C26)=0,ROUND('Drivers & Assumptions'!C27*(1+'Drivers & Assumptions'!C28)^2,0),0) -> 0 | AA11: =IF(MOD(26,'Drivers & Assumptions'!C26)=0,ROUND('Drivers & Assumptions'!C27*(1+'Drivers & Assumptions'!C28)^2,0),0) -> 0 | AB11: =IF(MOD(27,'Drivers & Assumptions'!C26)=0,ROUND('Drivers & Assumptions'!C27*(1+'Drivers & Assumptions'!C28)^2,0),0) -> 8 | AC11: =IF(MOD(28,'Drivers & Assumptions'!C26)=0,ROUND('Drivers & Assumptions'!C27*(1+'Drivers & Assumptions'!C28)^2,0),0) -> 0 | AD11: =IF(MOD(29,'Drivers & Assumptions'!C26)=0,ROUND('Drivers & Assumptions'!C27*(1+'Drivers & Assumptions'!C28)^2,0),0) -> 0 | AE11: =IF(MOD(30,'Drivers & Assumptions'!C26)=0,ROUND('Drivers & Assumptions'!C27*(1+'Drivers & Assumptions'!C28)^2,0),0) -> 8 | AF11: =IF(MOD(31,'Drivers & Assumptions'!C26)=0,ROUND('Drivers & Assumptions'!C27*(1+'Drivers & Assumptions'!C28)^2,0),0) -> 0 | AG11: =IF(MOD(32,'Drivers & Assumptions'!C26)=0,ROUND('Drivers & Assumptions'!C27*(1+'Drivers & Assumptions'!C28)^2,0),0) -> 0 | AH11: =IF(MOD(33,'Drivers & Assumptions'!C26)=0,ROUND('Drivers & Assumptions'!C27*(1+'Drivers & Assumptions'!C28)^2,0),0) -> 8 | AI11: =IF(MOD(34,'Drivers & Assumptions'!C26)=0,ROUND('Drivers & Assumptions'!C27*(1+'Drivers & Assumptions'!C28)^2,0),0) -> 0 | AJ11: =IF(MOD(35,'Drivers & Assumptions'!C26)=0,ROUND('Drivers & Assumptions'!C27*(1+'Drivers & Assumptions'!C28)^2,0),0) -> 0 | AK11: =IF(MOD(36,'Drivers & Assumptions'!C26)=0,ROUND('Drivers & Assumptions'!C27*(1+'Drivers & Assumptions'!C28)^2,0),0) -> 8 | AL11: =IF(MOD(37,'Drivers & Assumptions'!C26)=0,ROUND('Drivers & Assumptions'!C27*(1+'Drivers & Assumptions'!C28)^3,0),0) -> 0 | AM11: =IF(MOD(38,'Drivers & Assumptions'!C26)=0,ROUND('Drivers & Assumptions'!C27*(1+'Drivers & Assumptions'!C28)^3,0),0) -> 0 | AN11: =IF(MOD(39,'Drivers & Assumptions'!C26)=0,ROUND('Drivers & Assumptions'!C27*(1+'Drivers & Assumptions'!C28)^3,0),0) -> 10 | AO11: =IF(MOD(40,'Drivers & Assumptions'!C26)=0,ROUND('Drivers & Assumptions'!C27*(1+'Drivers & Assumptions'!C28)^3,0),0) -> 0 | AP11: =IF(MOD(41,'Drivers & Assumptions'!C26)=0,ROUND('Drivers & Assumptions'!C27*(1+'Drivers & Assumptions'!C28)^3,0),0) -> 0 | AQ11: =IF(MOD(42,'Drivers & Assumptions'!C26)=0,ROUND('Drivers & Assumptions'!C27*(1+'Drivers & Assumptions'!C28)^3,0),0) -> 10 | AR11: =IF(MOD(43,'Drivers & Assumptions'!C26)=0,ROUND('Drivers & Assumptions'!C27*(1+'Drivers & Assumptions'!C28)^3,0),0) -> 0 | AS11: =IF(MOD(44,'Drivers & Assumptions'!C26)=0,ROUND('Drivers & Assumptions'!C27*(1+'Drivers & Assumptions'!C28)^3,0),0) -> 0 | AT11: =IF(MOD(45,'Drivers & Assumptions'!C26)=0,ROUND('Drivers & Assumptions'!C27*(1+'Drivers & Assumptions'!C28)^3,0),0) -> 10 | AU11: =IF(MOD(46,'Drivers & Assumptions'!C26)=0,ROUND('Drivers & Assumptions'!C27*(1+'Drivers & Assumptions'!C28)^3,0),0) -> 0 | AV11: =IF(MOD(47,'Drivers & Assumptions'!C26)=0,ROUND('Drivers & Assumptions'!C27*(1+'Drivers & Assumptions'!C28)^3,0),0) -> 0 | AW11: =IF(MOD(48,'Drivers & Assumptions'!C26)=0,ROUND('Drivers & Assumptions'!C27*(1+'Drivers & Assumptions'!C28)^3,0),0) -> 10 | AX11: =IF(MOD(49,'Drivers & Assumptions'!C26)=0,ROUND('Drivers & Assumptions'!C27*(1+'Drivers & Assumptions'!C28)^4,0),0) -> 0 | AY11: =IF(MOD(50,'Drivers & Assumptions'!C26)=0,ROUND('Drivers & Assumptions'!C27*(1+'Drivers & Assumptions'!C28)^4,0),0) -> 0 | AZ11: =IF(MOD(51,'Drivers & Assumptions'!C26)=0,ROUND('Drivers & Assumptions'!C27*(1+'Drivers & Assumptions'!C28)^4,0),0) -> 12 | BA11: =IF(MOD(52,'Drivers & Assumptions'!C26)=0,ROUND('Drivers & Assumptions'!C27*(1+'Drivers & Assumptions'!C28)^4,0),0) -> 0 | BB11: =IF(MOD(53,'Drivers & Assumptions'!C26)=0,ROUND('Drivers & Assumptions'!C27*(1+'Drivers & Assumptions'!C28)^4,0),0) -> 0 | BC11: =IF(MOD(54,'Drivers & Assumptions'!C26)=0,ROUND('Drivers & Assumptions'!C27*(1+'Drivers & Assumptions'!C28)^4,0),0) -> 12 | BD11: =IF(MOD(55,'Drivers & Assumptions'!C26)=0,ROUND('Drivers & Assumptions'!C27*(1+'Drivers & Assumptions'!C28)^4,0),0) -> 0 | BE11: =IF(MOD(56,'Drivers & Assumptions'!C26)=0,ROUND('Drivers & Assumptions'!C27*(1+'Drivers & Assumptions'!C28)^4,0),0) -> 0 | BF11: =IF(MOD(57,'Drivers & Assumptions'!C26)=0,ROUND('Drivers & Assumptions'!C27*(1+'Drivers & Assumptions'!C28)^4,0),0) -> 12 | BG11: =IF(MOD(58,'Drivers & Assumptions'!C26)=0,ROUND('Drivers & Assumptions'!C27*(1+'Drivers & Assumptions'!C28)^4,0),0) -> 0 | BH11: =IF(MOD(59,'Drivers & Assumptions'!C26)=0,ROUND('Drivers & Assumptions'!C27*(1+'Drivers & Assumptions'!C28)^4,0),0) -> 0 | BI11: =IF(MOD(60,'Drivers & Assumptions'!C26)=0,ROUND('Drivers & Assumptions'!C27*(1+'Drivers & Assumptions'!C28)^4,0),0) -> 12
A12: Mexico — Cases Ordered | B12: 0 | C12: 0 | D12: 0 | E12: 0 | F12: 0 | G12: 0 | H12: 0 | I12: 0 | J12: =IF(MOD(9,'Drivers & Assumptions'!C26)=0,ROUND('Drivers & Assumptions'!C27*(1+'Drivers & Assumptions'!C28)^0,0),0) -> 5 | K12: =IF(MOD(10,'Drivers & Assumptions'!C26)=0,ROUND('Drivers & Assumptions'!C27*(1+'Drivers & Assumptions'!C28)^0,0),0) -> 0 | L12: =IF(MOD(11,'Drivers & Assumptions'!C26)=0,ROUND('Drivers & Assumptions'!C27*(1+'Drivers & Assumptions'!C28)^0,0),0) -> 0 | M12: =IF(MOD(12,'Drivers & Assumptions'!C26)=0,ROUND('Drivers & Assumptions'!C27*(1+'Drivers & Assumptions'!C28)^0,0),0) -> 5 | N12: =IF(MOD(13,'Drivers & Assumptions'!C26)=0,ROUND('Drivers & Assumptions'!C27*(1+'Drivers & Assumptions'!C28)^1,0),0) -> 0 | O12: =IF(MOD(14,'Drivers & Assumptions'!C26)=0,ROUND('Drivers & Assumptions'!C27*(1+'Drivers & Assumptions'!C28)^1,0),0) -> 0 | P12: =IF(MOD(15,'Drivers & Assumptions'!C26)=0,ROUND('Drivers & Assumptions'!C27*(1+'Drivers & Assumptions'!C28)^1,0),0) -> 6 | Q12: =IF(MOD(16,'Drivers & Assumptions'!C26)=0,ROUND('Drivers & Assumptions'!C27*(1+'Drivers & Assumptions'!C28)^1,0),0) -> 0 | R12: =IF(MOD(17,'Drivers & Assumptions'!C26)=0,ROUND('Drivers & Assumptions'!C27*(1+'Drivers & Assumptions'!C28)^1,0),0) -> 0 | S12: =IF(MOD(18,'Drivers & Assumptions'!C26)=0,ROUND('Drivers & Assumptions'!C27*(1+'Drivers & Assumptions'!C28)^1,0),0) -> 6 | T12: =IF(MOD(19,'Drivers & Assumptions'!C26)=0,ROUND('Drivers & Assumptions'!C27*(1+'Drivers & Assumptions'!C28)^1,0),0) -> 0 | U12: =IF(MOD(20,'Drivers & Assumptions'!C26)=0,ROUND('Drivers & Assumptions'!C27*(1+'Drivers & Assumptions'!C28)^1,0),0) -> 0 | V12: =IF(MOD(21,'Drivers & Assumptions'!C26)=0,ROUND('Drivers & Assumptions'!C27*(1+'Drivers & Assumptions'!C28)^1,0),0) -> 6 | W12: =IF(MOD(22,'Drivers & Assumptions'!C26)=0,ROUND('Drivers & Assumptions'!C27*(1+'Drivers & Assumptions'!C28)^1,0),0) -> 0 | X12: =IF(MOD(23,'Drivers & Assumptions'!C26)=0,ROUND('Drivers & Assumptions'!C27*(1+'Drivers & Assumptions'!C28)^1,0),0) -> 0 | Y12: =IF(MOD(24,'Drivers & Assumptions'!C26)=0,ROUND('Drivers & Assumptions'!C27*(1+'Drivers & Assumptions'!C28)^1,0),0) -> 6 | Z12: =IF(MOD(25,'Drivers & Assumptions'!C26)=0,ROUND('Drivers & Assumptions'!C27*(1+'Drivers & Assumptions'!C28)^2,0),0) -> 0 | AA12: =IF(MOD(26,'Drivers & Assumptions'!C26)=0,ROUND('Drivers & Assumptions'!C27*(1+'Drivers & Assumptions'!C28)^2,0),0) -> 0 | AB12: =IF(MOD(27,'Drivers & Assumptions'!C26)=0,ROUND('Drivers & Assumptions'!C27*(1+'Drivers & Assumptions'!C28)^2,0),0) -> 8 | AC12: =IF(MOD(28,'Drivers & Assumptions'!C26)=0,ROUND('Drivers & Assumptions'!C27*(1+'Drivers & Assumptions'!C28)^2,0),0) -> 0 | AD12: =IF(MOD(29,'Drivers & Assumptions'!C26)=0,ROUND('Drivers & Assumptions'!C27*(1+'Drivers & Assumptions'!C28)^2,0),0) -> 0 | AE12: =IF(MOD(30,'Drivers & Assumptions'!C26)=0,ROUND('Drivers & Assumptions'!C27*(1+'Drivers & Assumptions'!C28)^2,0),0) -> 8 | AF12: =IF(MOD(31,'Drivers & Assumptions'!C26)=0,ROUND('Drivers & Assumptions'!C27*(1+'Drivers & Assumptions'!C28)^2,0),0) -> 0 | AG12: =IF(MOD(32,'Drivers & Assumptions'!C26)=0,ROUND('Drivers & Assumptions'!C27*(1+'Drivers & Assumptions'!C28)^2,0),0) -> 0 | AH12: =IF(MOD(33,'Drivers & Assumptions'!C26)=0,ROUND('Drivers & Assumptions'!C27*(1+'Drivers & Assumptions'!C28)^2,0),0) -> 8 | AI12: =IF(MOD(34,'Drivers & Assumptions'!C26)=0,ROUND('Drivers & Assumptions'!C27*(1+'Drivers & Assumptions'!C28)^2,0),0) -> 0 | AJ12: =IF(MOD(35,'Drivers & Assumptions'!C26)=0,ROUND('Drivers & Assumptions'!C27*(1+'Drivers & Assumptions'!C28)^2,0),0) -> 0 | AK12: =IF(MOD(36,'Drivers & Assumptions'!C26)=0,ROUND('Drivers & Assumptions'!C27*(1+'Drivers & Assumptions'!C28)^2,0),0) -> 8 | AL12: =IF(MOD(37,'Drivers & Assumptions'!C26)=0,ROUND('Drivers & Assumptions'!C27*(1+'Drivers & Assumptions'!C28)^3,0),0) -> 0 | AM12: =IF(MOD(38,'Drivers & Assumptions'!C26)=0,ROUND('Drivers & Assumptions'!C27*(1+'Drivers & Assumptions'!C28)^3,0),0) -> 0 | AN12: =IF(MOD(39,'Drivers & Assumptions'!C26)=0,ROUND('Drivers & Assumptions'!C27*(1+'Drivers & Assumptions'!C28)^3,0),0) -> 10 | AO12: =IF(MOD(40,'Drivers & Assumptions'!C26)=0,ROUND('Drivers & Assumptions'!C27*(1+'Drivers & Assumptions'!C28)^3,0),0) -> 0 | AP12: =IF(MOD(41,'Drivers & Assumptions'!C26)=0,ROUND('Drivers & Assumptions'!C27*(1+'Drivers & Assumptions'!C28)^3,0),0) -> 0 | AQ12: =IF(MOD(42,'Drivers & Assumptions'!C26)=0,ROUND('Drivers & Assumptions'!C27*(1+'Drivers & Assumptions'!C28)^3,0),0) -> 10 | AR12: =IF(MOD(43,'Drivers & Assumptions'!C26)=0,ROUND('Drivers & Assumptions'!C27*(1+'Drivers & Assumptions'!C28)^3,0),0) -> 0 | AS12: =IF(MOD(44,'Drivers & Assumptions'!C26)=0,ROUND('Drivers & Assumptions'!C27*(1+'Drivers & Assumptions'!C28)^3,0),0) -> 0 | AT12: =IF(MOD(45,'Drivers & Assumptions'!C26)=0,ROUND('Drivers & Assumptions'!C27*(1+'Drivers & Assumptions'!C28)^3,0),0) -> 10 | AU12: =IF(MOD(46,'Drivers & Assumptions'!C26)=0,ROUND('Drivers & Assumptions'!C27*(1+'Drivers & Assumptions'!C28)^3,0),0) -> 0 | AV12: =IF(MOD(47,'Drivers & Assumptions'!C26)=0,ROUND('Drivers & Assumptions'!C27*(1+'Drivers & Assumptions'!C28)^3,0),0) -> 0 | AW12: =IF(MOD(48,'Drivers & Assumptions'!C26)=0,ROUND('Drivers & Assumptions'!C27*(1+'Drivers & Assumptions'!C28)^3,0),0) -> 10 | AX12: =IF(MOD(49,'Drivers & Assumptions'!C26)=0,ROUND('Drivers & Assumptions'!C27*(1+'Drivers & Assumptions'!C28)^4,0),0) -> 0 | AY12: =IF(MOD(50,'Drivers & Assumptions'!C26)=0,ROUND('Drivers & Assumptions'!C27*(1+'Drivers & Assumptions'!C28)^4,0),0) -> 0 | AZ12: =IF(MOD(51,'Drivers & Assumptions'!C26)=0,ROUND('Drivers & Assumptions'!C27*(1+'Drivers & Assumptions'!C28)^4,0),0) -> 12 | BA12: =IF(MOD(52,'Drivers & Assumptions'!C26)=0,ROUND('Drivers & Assumptions'!C27*(1+'Drivers & Assumptions'!C28)^4,0),0) -> 0 | BB12: =IF(MOD(53,'Drivers & Assumptions'!C26)=0,ROUND('Drivers & Assumptions'!C27*(1+'Drivers & Assumptions'!C28)^4,0),0) -> 0 | BC12: =IF(MOD(54,'Drivers & Assumptions'!C26)=0,ROUND('Drivers & Assumptions'!C27*(1+'Drivers & Assumptions'!C28)^4,0),0) -> 12 | BD12: =IF(MOD(55,'Drivers & Assumptions'!C26)=0,ROUND('Drivers & Assumptions'!C27*(1+'Drivers & Assumptions'!C28)^4,0),0) -> 0 | BE12: =IF(MOD(56,'Drivers & Assumptions'!C26)=0,ROUND('Drivers & Assumptions'!C27*(1+'Drivers & Assumptions'!C28)^4,0),0) -> 0 | BF12: =IF(MOD(57,'Drivers & Assumptions'!C26)=0,ROUND('Drivers & Assumptions'!C27*(1+'Drivers & Assumptions'!C28)^4,0),0) -> 12 | BG12: =IF(MOD(58,'Drivers & Assumptions'!C26)=0,ROUND('Drivers & Assumptions'!C27*(1+'Drivers & Assumptions'!C28)^4,0),0) -> 0 | BH12: =IF(MOD(59,'Drivers & Assumptions'!C26)=0,ROUND('Drivers & Assumptions'!C27*(1+'Drivers & Assumptions'!C28)^4,0),0) -> 0 | BI12: =IF(MOD(60,'Drivers & Assumptions'!C26)=0,ROUND('Drivers & Assumptions'!C27*(1+'Drivers & Assumptions'!C28)^4,0),0) -> 12
A13: European Union — Cases Ordered | B13: 0 | C13: 0 | D13: 0 | E13: 0 | F13: 0 | G13: 0 | H13: 0 | I13: 0 | J13: =IF(MOD(9,'Drivers & Assumptions'!C26)=0,ROUND('Drivers & Assumptions'!C27*(1+'Drivers & Assumptions'!C28)^0,0),0) -> 5 | K13: =IF(MOD(10,'Drivers & Assumptions'!C26)=0,ROUND('Drivers & Assumptions'!C27*(1+'Drivers & Assumptions'!C28)^0,0),0) -> 0 | L13: =IF(MOD(11,'Drivers & Assumptions'!C26)=0,ROUND('Drivers & Assumptions'!C27*(1+'Drivers & Assumptions'!C28)^0,0),0) -> 0 | M13: =IF(MOD(12,'Drivers & Assumptions'!C26)=0,ROUND('Drivers & Assumptions'!C27*(1+'Drivers & Assumptions'!C28)^0,0),0) -> 5 | N13: =IF(MOD(13,'Drivers & Assumptions'!C26)=0,ROUND('Drivers & Assumptions'!C27*(1+'Drivers & Assumptions'!C28)^1,0),0) -> 0 | O13: =IF(MOD(14,'Drivers & Assumptions'!C26)=0,ROUND('Drivers & Assumptions'!C27*(1+'Drivers & Assumptions'!C28)^1,0),0) -> 0 | P13: =IF(MOD(15,'Drivers & Assumptions'!C26)=0,ROUND('Drivers & Assumptions'!C27*(1+'Drivers & Assumptions'!C28)^1,0),0) -> 6 | Q13: =IF(MOD(16,'Drivers & Assumptions'!C26)=0,ROUND('Drivers & Assumptions'!C27*(1+'Drivers & Assumptions'!C28)^1,0),0) -> 0 | R13: =IF(MOD(17,'Drivers & Assumptions'!C26)=0,ROUND('Drivers & Assumptions'!C27*(1+'Drivers & Assumptions'!C28)^1,0),0) -> 0 | S13: =IF(MOD(18,'Drivers & Assumptions'!C26)=0,ROUND('Drivers & Assumptions'!C27*(1+'Drivers & Assumptions'!C28)^1,0),0) -> 6 | T13: =IF(MOD(19,'Drivers & Assumptions'!C26)=0,ROUND('Drivers & Assumptions'!C27*(1+'Drivers & Assumptions'!C28)^1,0),0) -> 0 | U13: =IF(MOD(20,'Drivers & Assumptions'!C26)=0,ROUND('Drivers & Assumptions'!C27*(1+'Drivers & Assumptions'!C28)^1,0),0) -> 0 | V13: =IF(MOD(21,'Drivers & Assumptions'!C26)=0,ROUND('Drivers & Assumptions'!C27*(1+'Drivers & Assumptions'!C28)^1,0),0) -> 6 | W13: =IF(MOD(22,'Drivers & Assumptions'!C26)=0,ROUND('Drivers & Assumptions'!C27*(1+'Drivers & Assumptions'!C28)^1,0),0) -> 0 | X13: =IF(MOD(23,'Drivers & Assumptions'!C26)=0,ROUND('Drivers & Assumptions'!C27*(1+'Drivers & Assumptions'!C28)^1,0),0) -> 0 | Y13: =IF(MOD(24,'Drivers & Assumptions'!C26)=0,ROUND('Drivers & Assumptions'!C27*(1+'Drivers & Assumptions'!C28)^1,0),0) -> 6 | Z13: =IF(MOD(25,'Drivers & Assumptions'!C26)=0,ROUND('Drivers & Assumptions'!C27*(1+'Drivers & Assumptions'!C28)^2,0),0) -> 0 | AA13: =IF(MOD(26,'Drivers & Assumptions'!C26)=0,ROUND('Drivers & Assumptions'!C27*(1+'Drivers & Assumptions'!C28)^2,0),0) -> 0 | AB13: =IF(MOD(27,'Drivers & Assumptions'!C26)=0,ROUND('Drivers & Assumptions'!C27*(1+'Drivers & Assumptions'!C28)^2,0),0) -> 8 | AC13: =IF(MOD(28,'Drivers & Assumptions'!C26)=0,ROUND('Drivers & Assumptions'!C27*(1+'Drivers & Assumptions'!C28)^2,0),0) -> 0 | AD13: =IF(MOD(29,'Drivers & Assumptions'!C26)=0,ROUND('Drivers & Assumptions'!C27*(1+'Drivers & Assumptions'!C28)^2,0),0) -> 0 | AE13: =IF(MOD(30,'Drivers & Assumptions'!C26)=0,ROUND('Drivers & Assumptions'!C27*(1+'Drivers & Assumptions'!C28)^2,0),0) -> 8 | AF13: =IF(MOD(31,'Drivers & Assumptions'!C26)=0,ROUND('Drivers & Assumptions'!C27*(1+'Drivers & Assumptions'!C28)^2,0),0) -> 0 | AG13: =IF(MOD(32,'Drivers & Assumptions'!C26)=0,ROUND('Drivers & Assumptions'!C27*(1+'Drivers & Assumptions'!C28)^2,0),0) -> 0 | AH13: =IF(MOD(33,'Drivers & Assumptions'!C26)=0,ROUND('Drivers & Assumptions'!C27*(1+'Drivers & Assumptions'!C28)^2,0),0) -> 8 | AI13: =IF(MOD(34,'Drivers & Assumptions'!C26)=0,ROUND('Drivers & Assumptions'!C27*(1+'Drivers & Assumptions'!C28)^2,0),0) -> 0 | AJ13: =IF(MOD(35,'Drivers & Assumptions'!C26)=0,ROUND('Drivers & Assumptions'!C27*(1+'Drivers & Assumptions'!C28)^2,0),0) -> 0 | AK13: =IF(MOD(36,'Drivers & Assumptions'!C26)=0,ROUND('Drivers & Assumptions'!C27*(1+'Drivers & Assumptions'!C28)^2,0),0) -> 8 | AL13: =IF(MOD(37,'Drivers & Assumptions'!C26)=0,ROUND('Drivers & Assumptions'!C27*(1+'Drivers & Assumptions'!C28)^3,0),0) -> 0 | AM13: =IF(MOD(38,'Drivers & Assumptions'!C26)=0,ROUND('Drivers & Assumptions'!C27*(1+'Drivers & Assumptions'!C28)^3,0),0) -> 0 | AN13: =IF(MOD(39,'Drivers & Assumptions'!C26)=0,ROUND('Drivers & Assumptions'!C27*(1+'Drivers & Assumptions'!C28)^3,0),0) -> 10 | AO13: =IF(MOD(40,'Drivers & Assumptions'!C26)=0,ROUND('Drivers & Assumptions'!C27*(1+'Drivers & Assumptions'!C28)^3,0),0) -> 0 | AP13: =IF(MOD(41,'Drivers & Assumptions'!C26)=0,ROUND('Drivers & Assumptions'!C27*(1+'Drivers & Assumptions'!C28)^3,0),0) -> 0 | AQ13: =IF(MOD(42,'Drivers & Assumptions'!C26)=0,ROUND('Drivers & Assumptions'!C27*(1+'Drivers & Assumptions'!C28)^3,0),0) -> 10 | AR13: =IF(MOD(43,'Drivers & Assumptions'!C26)=0,ROUND('Drivers & Assumptions'!C27*(1+'Drivers & Assumptions'!C28)^3,0),0) -> 0 | AS13: =IF(MOD(44,'Drivers & Assumptions'!C26)=0,ROUND('Drivers & Assumptions'!C27*(1+'Drivers & Assumptions'!C28)^3,0),0) -> 0 | AT13: =IF(MOD(45,'Drivers & Assumptions'!C26)=0,ROUND('Drivers & Assumptions'!C27*(1+'Drivers & Assumptions'!C28)^3,0),0) -> 10 | AU13: =IF(MOD(46,'Drivers & Assumptions'!C26)=0,ROUND('Drivers & Assumptions'!C27*(1+'Drivers & Assumptions'!C28)^3,0),0) -> 0 | AV13: =IF(MOD(47,'Drivers & Assumptions'!C26)=0,ROUND('Drivers & Assumptions'!C27*(1+'Drivers & Assumptions'!C28)^3,0),0) -> 0 | AW13: =IF(MOD(48,'Drivers & Assumptions'!C26)=0,ROUND('Drivers & Assumptions'!C27*(1+'Drivers & Assumptions'!C28)^3,0),0) -> 10 | AX13: =IF(MOD(49,'Drivers & Assumptions'!C26)=0,ROUND('Drivers & Assumptions'!C27*(1+'Drivers & Assumptions'!C28)^4,0),0) -> 0 | AY13: =IF(MOD(50,'Drivers & Assumptions'!C26)=0,ROUND('Drivers & Assumptions'!C27*(1+'Drivers & Assumptions'!C28)^4,0),0) -> 0 | AZ13: =IF(MOD(51,'Drivers & Assumptions'!C26)=0,ROUND('Drivers & Assumptions'!C27*(1+'Drivers & Assumptions'!C28)^4,0),0) -> 12 | BA13: =IF(MOD(52,'Drivers & Assumptions'!C26)=0,ROUND('Drivers & Assumptions'!C27*(1+'Drivers & Assumptions'!C28)^4,0),0) -> 0 | BB13: =IF(MOD(53,'Drivers & Assumptions'!C26)=0,ROUND('Drivers & Assumptions'!C27*(1+'Drivers & Assumptions'!C28)^4,0),0) -> 0 | BC13: =IF(MOD(54,'Drivers & Assumptions'!C26)=0,ROUND('Drivers & Assumptions'!C27*(1+'Drivers & Assumptions'!C28)^4,0),0) -> 12 | BD13: =IF(MOD(55,'Drivers & Assumptions'!C26)=0,ROUND('Drivers & Assumptions'!C27*(1+'Drivers & Assumptions'!C28)^4,0),0) -> 0 | BE13: =IF(MOD(56,'Drivers & Assumptions'!C26)=0,ROUND('Drivers & Assumptions'!C27*(1+'Drivers & Assumptions'!C28)^4,0),0) -> 0 | BF13: =IF(MOD(57,'Drivers & Assumptions'!C26)=0,ROUND('Drivers & Assumptions'!C27*(1+'Drivers & Assumptions'!C28)^4,0),0) -> 12 | BG13: =IF(MOD(58,'Drivers & Assumptions'!C26)=0,ROUND('Drivers & Assumptions'!C27*(1+'Drivers & Assumptions'!C28)^4,0),0) -> 0 | BH13: =IF(MOD(59,'Drivers & Assumptions'!C26)=0,ROUND('Drivers & Assumptions'!C27*(1+'Drivers & Assumptions'!C28)^4,0),0) -> 0 | BI13: =IF(MOD(60,'Drivers & Assumptions'!C26)=0,ROUND('Drivers & Assumptions'!C27*(1+'Drivers & Assumptions'!C28)^4,0),0) -> 12
A14: UAE — Cases Ordered | B14: 0 | C14: 0 | D14: 0 | E14: 0 | F14: 0 | G14: 0 | H14: 0 | I14: 0 | J14: =IF(MOD(9,'Drivers & Assumptions'!C26)=0,ROUND('Drivers & Assumptions'!C27*(1+'Drivers & Assumptions'!C28)^0,0),0) -> 5 | K14: =IF(MOD(10,'Drivers & Assumptions'!C26)=0,ROUND('Drivers & Assumptions'!C27*(1+'Drivers & Assumptions'!C28)^0,0),0) -> 0 | L14: =IF(MOD(11,'Drivers & Assumptions'!C26)=0,ROUND('Drivers & Assumptions'!C27*(1+'Drivers & Assumptions'!C28)^0,0),0) -> 0 | M14: =IF(MOD(12,'Drivers & Assumptions'!C26)=0,ROUND('Drivers & Assumptions'!C27*(1+'Drivers & Assumptions'!C28)^0,0),0) -> 5 | N14: =IF(MOD(13,'Drivers & Assumptions'!C26)=0,ROUND('Drivers & Assumptions'!C27*(1+'Drivers & Assumptions'!C28)^1,0),0) -> 0 | O14: =IF(MOD(14,'Drivers & Assumptions'!C26)=0,ROUND('Drivers & Assumptions'!C27*(1+'Drivers & Assumptions'!C28)^1,0),0) -> 0 | P14: =IF(MOD(15,'Drivers & Assumptions'!C26)=0,ROUND('Drivers & Assumptions'!C27*(1+'Drivers & Assumptions'!C28)^1,0),0) -> 6 | Q14: =IF(MOD(16,'Drivers & Assumptions'!C26)=0,ROUND('Drivers & Assumptions'!C27*(1+'Drivers & Assumptions'!C28)^1,0),0) -> 0 | R14: =IF(MOD(17,'Drivers & Assumptions'!C26)=0,ROUND('Drivers & Assumptions'!C27*(1+'Drivers & Assumptions'!C28)^1,0),0) -> 0 | S14: =IF(MOD(18,'Drivers & Assumptions'!C26)=0,ROUND('Drivers & Assumptions'!C27*(1+'Drivers & Assumptions'!C28)^1,0),0) -> 6 | T14: =IF(MOD(19,'Drivers & Assumptions'!C26)=0,ROUND('Drivers & Assumptions'!C27*(1+'Drivers & Assumptions'!C28)^1,0),0) -> 0 | U14: =IF(MOD(20,'Drivers & Assumptions'!C26)=0,ROUND('Drivers & Assumptions'!C27*(1+'Drivers & Assumptions'!C28)^1,0),0) -> 0 | V14: =IF(MOD(21,'Drivers & Assumptions'!C26)=0,ROUND('Drivers & Assumptions'!C27*(1+'Drivers & Assumptions'!C28)^1,0),0) -> 6 | W14: =IF(MOD(22,'Drivers & Assumptions'!C26)=0,ROUND('Drivers & Assumptions'!C27*(1+'Drivers & Assumptions'!C28)^1,0),0) -> 0 | X14: =IF(MOD(23,'Drivers & Assumptions'!C26)=0,ROUND('Drivers & Assumptions'!C27*(1+'Drivers & Assumptions'!C28)^1,0),0) -> 0 | Y14: =IF(MOD(24,'Drivers & Assumptions'!C26)=0,ROUND('Drivers & Assumptions'!C27*(1+'Drivers & Assumptions'!C28)^1,0),0) -> 6 | Z14: =IF(MOD(25,'Drivers & Assumptions'!C26)=0,ROUND('Drivers & Assumptions'!C27*(1+'Drivers & Assumptions'!C28)^2,0),0) -> 0 | AA14: =IF(MOD(26,'Drivers & Assumptions'!C26)=0,ROUND('Drivers & Assumptions'!C27*(1+'Drivers & Assumptions'!C28)^2,0),0) -> 0 | AB14: =IF(MOD(27,'Drivers & Assumptions'!C26)=0,ROUND('Drivers & Assumptions'!C27*(1+'Drivers & Assumptions'!C28)^2,0),0) -> 8 | AC14: =IF(MOD(28,'Drivers & Assumptions'!C26)=0,ROUND('Drivers & Assumptions'!C27*(1+'Drivers & Assumptions'!C28)^2,0),0) -> 0 | AD14: =IF(MOD(29,'Drivers & Assumptions'!C26)=0,ROUND('Drivers & Assumptions'!C27*(1+'Drivers & Assumptions'!C28)^2,0),0) -> 0 | AE14: =IF(MOD(30,'Drivers & Assumptions'!C26)=0,ROUND('Drivers & Assumptions'!C27*(1+'Drivers & Assumptions'!C28)^2,0),0) -> 8 | AF14: =IF(MOD(31,'Drivers & Assumptions'!C26)=0,ROUND('Drivers & Assumptions'!C27*(1+'Drivers & Assumptions'!C28)^2,0),0) -> 0 | AG14: =IF(MOD(32,'Drivers & Assumptions'!C26)=0,ROUND('Drivers & Assumptions'!C27*(1+'Drivers & Assumptions'!C28)^2,0),0) -> 0 | AH14: =IF(MOD(33,'Drivers & Assumptions'!C26)=0,ROUND('Drivers & Assumptions'!C27*(1+'Drivers & Assumptions'!C28)^2,0),0) -> 8 | AI14: =IF(MOD(34,'Drivers & Assumptions'!C26)=0,ROUND('Drivers & Assumptions'!C27*(1+'Drivers & Assumptions'!C28)^2,0),0) -> 0 | AJ14: =IF(MOD(35,'Drivers & Assumptions'!C26)=0,ROUND('Drivers & Assumptions'!C27*(1+'Drivers & Assumptions'!C28)^2,0),0) -> 0 | AK14: =IF(MOD(36,'Drivers & Assumptions'!C26)=0,ROUND('Drivers & Assumptions'!C27*(1+'Drivers & Assumptions'!C28)^2,0),0) -> 8 | AL14: =IF(MOD(37,'Drivers & Assumptions'!C26)=0,ROUND('Drivers & Assumptions'!C27*(1+'Drivers & Assumptions'!C28)^3,0),0) -> 0 | AM14: =IF(MOD(38,'Drivers & Assumptions'!C26)=0,ROUND('Drivers & Assumptions'!C27*(1+'Drivers & Assumptions'!C28)^3,0),0) -> 0 | AN14: =IF(MOD(39,'Drivers & Assumptions'!C26)=0,ROUND('Drivers & Assumptions'!C27*(1+'Drivers & Assumptions'!C28)^3,0),0) -> 10 | AO14: =IF(MOD(40,'Drivers & Assumptions'!C26)=0,ROUND('Drivers & Assumptions'!C27*(1+'Drivers & Assumptions'!C28)^3,0),0) -> 0 | AP14: =IF(MOD(41,'Drivers & Assumptions'!C26)=0,ROUND('Drivers & Assumptions'!C27*(1+'Drivers & Assumptions'!C28)^3,0),0) -> 0 | AQ14: =IF(MOD(42,'Drivers & Assumptions'!C26)=0,ROUND('Drivers & Assumptions'!C27*(1+'Drivers & Assumptions'!C28)^3,0),0) -> 10 | AR14: =IF(MOD(43,'Drivers & Assumptions'!C26)=0,ROUND('Drivers & Assumptions'!C27*(1+'Drivers & Assumptions'!C28)^3,0),0) -> 0 | AS14: =IF(MOD(44,'Drivers & Assumptions'!C26)=0,ROUND('Drivers & Assumptions'!C27*(1+'Drivers & Assumptions'!C28)^3,0),0) -> 0 | AT14: =IF(MOD(45,'Drivers & Assumptions'!C26)=0,ROUND('Drivers & Assumptions'!C27*(1+'Drivers & Assumptions'!C28)^3,0),0) -> 10 | AU14: =IF(MOD(46,'Drivers & Assumptions'!C26)=0,ROUND('Drivers & Assumptions'!C27*(1+'Drivers & Assumptions'!C28)^3,0),0) -> 0 | AV14: =IF(MOD(47,'Drivers & Assumptions'!C26)=0,ROUND('Drivers & Assumptions'!C27*(1+'Drivers & Assumptions'!C28)^3,0),0) -> 0 | AW14: =IF(MOD(48,'Drivers & Assumptions'!C26)=0,ROUND('Drivers & Assumptions'!C27*(1+'Drivers & Assumptions'!C28)^3,0),0) -> 10 | AX14: =IF(MOD(49,'Drivers & Assumptions'!C26)=0,ROUND('Drivers & Assumptions'!C27*(1+'Drivers & Assumptions'!C28)^4,0),0) -> 0 | AY14: =IF(MOD(50,'Drivers & Assumptions'!C26)=0,ROUND('Drivers & Assumptions'!C27*(1+'Drivers & Assumptions'!C28)^4,0),0) -> 0 | AZ14: =IF(MOD(51,'Drivers & Assumptions'!C26)=0,ROUND('Drivers & Assumptions'!C27*(1+'Drivers & Assumptions'!C28)^4,0),0) -> 12 | BA14: =IF(MOD(52,'Drivers & Assumptions'!C26)=0,ROUND('Drivers & Assumptions'!C27*(1+'Drivers & Assumptions'!C28)^4,0),0) -> 0 | BB14: =IF(MOD(53,'Drivers & Assumptions'!C26)=0,ROUND('Drivers & Assumptions'!C27*(1+'Drivers & Assumptions'!C28)^4,0),0) -> 0 | BC14: =IF(MOD(54,'Drivers & Assumptions'!C26)=0,ROUND('Drivers & Assumptions'!C27*(1+'Drivers & Assumptions'!C28)^4,0),0) -> 12 | BD14: =IF(MOD(55,'Drivers & Assumptions'!C26)=0,ROUND('Drivers & Assumptions'!C27*(1+'Drivers & Assumptions'!C28)^4,0),0) -> 0 | BE14: =IF(MOD(56,'Drivers & Assumptions'!C26)=0,ROUND('Drivers & Assumptions'!C27*(1+'Drivers & Assumptions'!C28)^4,0),0) -> 0 | BF14: =IF(MOD(57,'Drivers & Assumptions'!C26)=0,ROUND('Drivers & Assumptions'!C27*(1+'Drivers & Assumptions'!C28)^4,0),0) -> 12 | BG14: =IF(MOD(58,'Drivers & Assumptions'!C26)=0,ROUND('Drivers & Assumptions'!C27*(1+'Drivers & Assumptions'!C28)^4,0),0) -> 0 | BH14: =IF(MOD(59,'Drivers & Assumptions'!C26)=0,ROUND('Drivers & Assumptions'!C27*(1+'Drivers & Assumptions'!C28)^4,0),0) -> 0 | BI14: =IF(MOD(60,'Drivers & Assumptions'!C26)=0,ROUND('Drivers & Assumptions'!C27*(1+'Drivers & Assumptions'!C28)^4,0),0) -> 12
A15: Malaysia — Cases Ordered | B15: 0 | C15: 0 | D15: 0 | E15: 0 | F15: 0 | G15: 0 | H15: 0 | I15: 0 | J15: =IF(MOD(9,'Drivers & Assumptions'!C26)=0,ROUND('Drivers & Assumptions'!C27*(1+'Drivers & Assumptions'!C28)^0,0),0) -> 5 | K15: =IF(MOD(10,'Drivers & Assumptions'!C26)=0,ROUND('Drivers & Assumptions'!C27*(1+'Drivers & Assumptions'!C28)^0,0),0) -> 0 | L15: =IF(MOD(11,'Drivers & Assumptions'!C26)=0,ROUND('Drivers & Assumptions'!C27*(1+'Drivers & Assumptions'!C28)^0,0),0) -> 0 | M15: =IF(MOD(12,'Drivers & Assumptions'!C26)=0,ROUND('Drivers & Assumptions'!C27*(1+'Drivers & Assumptions'!C28)^0,0),0) -> 5 | N15: =IF(MOD(13,'Drivers & Assumptions'!C26)=0,ROUND('Drivers & Assumptions'!C27*(1+'Drivers & Assumptions'!C28)^1,0),0) -> 0 | O15: =IF(MOD(14,'Drivers & Assumptions'!C26)=0,ROUND('Drivers & Assumptions'!C27*(1+'Drivers & Assumptions'!C28)^1,0),0) -> 0 | P15: =IF(MOD(15,'Drivers & Assumptions'!C26)=0,ROUND('Drivers & Assumptions'!C27*(1+'Drivers & Assumptions'!C28)^1,0),0) -> 6 | Q15: =IF(MOD(16,'Drivers & Assumptions'!C26)=0,ROUND('Drivers & Assumptions'!C27*(1+'Drivers & Assumptions'!C28)^1,0),0) -> 0 | R15: =IF(MOD(17,'Drivers & Assumptions'!C26)=0,ROUND('Drivers & Assumptions'!C27*(1+'Drivers & Assumptions'!C28)^1,0),0) -> 0 | S15: =IF(MOD(18,'Drivers & Assumptions'!C26)=0,ROUND('Drivers & Assumptions'!C27*(1+'Drivers & Assumptions'!C28)^1,0),0) -> 6 | T15: =IF(MOD(19,'Drivers & Assumptions'!C26)=0,ROUND('Drivers & Assumptions'!C27*(1+'Drivers & Assumptions'!C28)^1,0),0) -> 0 | U15: =IF(MOD(20,'Drivers & Assumptions'!C26)=0,ROUND('Drivers & Assumptions'!C27*(1+'Drivers & Assumptions'!C28)^1,0),0) -> 0 | V15: =IF(MOD(21,'Drivers & Assumptions'!C26)=0,ROUND('Drivers & Assumptions'!C27*(1+'Drivers & Assumptions'!C28)^1,0),0) -> 6 | W15: =IF(MOD(22,'Drivers & Assumptions'!C26)=0,ROUND('Drivers & Assumptions'!C27*(1+'Drivers & Assumptions'!C28)^1,0),0) -> 0 | X15: =IF(MOD(23,'Drivers & Assumptions'!C26)=0,ROUND('Drivers & Assumptions'!C27*(1+'Drivers & Assumptions'!C28)^1,0),0) -> 0 | Y15: =IF(MOD(24,'Drivers & Assumptions'!C26)=0,ROUND('Drivers & Assumptions'!C27*(1+'Drivers & Assumptions'!C28)^1,0),0) -> 6 | Z15: =IF(MOD(25,'Drivers & Assumptions'!C26)=0,ROUND('Drivers & Assumptions'!C27*(1+'Drivers & Assumptions'!C28)^2,0),0) -> 0 | AA15: =IF(MOD(26,'Drivers & Assumptions'!C26)=0,ROUND('Drivers & Assumptions'!C27*(1+'Drivers & Assumptions'!C28)^2,0),0) -> 0 | AB15: =IF(MOD(27,'Drivers & Assumptions'!C26)=0,ROUND('Drivers & Assumptions'!C27*(1+'Drivers & Assumptions'!C28)^2,0),0) -> 8 | AC15: =IF(MOD(28,'Drivers & Assumptions'!C26)=0,ROUND('Drivers & Assumptions'!C27*(1+'Drivers & Assumptions'!C28)^2,0),0) -> 0 | AD15: =IF(MOD(29,'Drivers & Assumptions'!C26)=0,ROUND('Drivers & Assumptions'!C27*(1+'Drivers & Assumptions'!C28)^2,0),0) -> 0 | AE15: =IF(MOD(30,'Drivers & Assumptions'!C26)=0,ROUND('Drivers & Assumptions'!C27*(1+'Drivers & Assumptions'!C28)^2,0),0) -> 8 | AF15: =IF(MOD(31,'Drivers & Assumptions'!C26)=0,ROUND('Drivers & Assumptions'!C27*(1+'Drivers & Assumptions'!C28)^2,0),0) -> 0 | AG15: =IF(MOD(32,'Drivers & Assumptions'!C26)=0,ROUND('Drivers & Assumptions'!C27*(1+'Drivers & Assumptions'!C28)^2,0),0) -> 0 | AH15: =IF(MOD(33,'Drivers & Assumptions'!C26)=0,ROUND('Drivers & Assumptions'!C27*(1+'Drivers & Assumptions'!C28)^2,0),0) -> 8 | AI15: =IF(MOD(34,'Drivers & Assumptions'!C26)=0,ROUND('Drivers & Assumptions'!C27*(1+'Drivers & Assumptions'!C28)^2,0),0) -> 0 | AJ15: =IF(MOD(35,'Drivers & Assumptions'!C26)=0,ROUND('Drivers & Assumptions'!C27*(1+'Drivers & Assumptions'!C28)^2,0),0) -> 0 | AK15: =IF(MOD(36,'Drivers & Assumptions'!C26)=0,ROUND('Drivers & Assumptions'!C27*(1+'Drivers & Assumptions'!C28)^2,0),0) -> 8 | AL15: =IF(MOD(37,'Drivers & Assumptions'!C26)=0,ROUND('Drivers & Assumptions'!C27*(1+'Drivers & Assumptions'!C28)^3,0),0) -> 0 | AM15: =IF(MOD(38,'Drivers & Assumptions'!C26)=0,ROUND('Drivers & Assumptions'!C27*(1+'Drivers & Assumptions'!C28)^3,0),0) -> 0 | AN15: =IF(MOD(39,'Drivers & Assumptions'!C26)=0,ROUND('Drivers & Assumptions'!C27*(1+'Drivers & Assumptions'!C28)^3,0),0) -> 10 | AO15: =IF(MOD(40,'Drivers & Assumptions'!C26)=0,ROUND('Drivers & Assumptions'!C27*(1+'Drivers & Assumptions'!C28)^3,0),0) -> 0 | AP15: =IF(MOD(41,'Drivers & Assumptions'!C26)=0,ROUND('Drivers & Assumptions'!C27*(1+'Drivers & Assumptions'!C28)^3,0),0) -> 0 | AQ15: =IF(MOD(42,'Drivers & Assumptions'!C26)=0,ROUND('Drivers & Assumptions'!C27*(1+'Drivers & Assumptions'!C28)^3,0),0) -> 10 | AR15: =IF(MOD(43,'Drivers & Assumptions'!C26)=0,ROUND('Drivers & Assumptions'!C27*(1+'Drivers & Assumptions'!C28)^3,0),0) -> 0 | AS15: =IF(MOD(44,'Drivers & Assumptions'!C26)=0,ROUND('Drivers & Assumptions'!C27*(1+'Drivers & Assumptions'!C28)^3,0),0) -> 0 | AT15: =IF(MOD(45,'Drivers & Assumptions'!C26)=0,ROUND('Drivers & Assumptions'!C27*(1+'Drivers & Assumptions'!C28)^3,0),0) -> 10 | AU15: =IF(MOD(46,'Drivers & Assumptions'!C26)=0,ROUND('Drivers & Assumptions'!C27*(1+'Drivers & Assumptions'!C28)^3,0),0) -> 0 | AV15: =IF(MOD(47,'Drivers & Assumptions'!C26)=0,ROUND('Drivers & Assumptions'!C27*(1+'Drivers & Assumptions'!C28)^3,0),0) -> 0 | AW15: =IF(MOD(48,'Drivers & Assumptions'!C26)=0,ROUND('Drivers & Assumptions'!C27*(1+'Drivers & Assumptions'!C28)^3,0),0) -> 10 | AX15: =IF(MOD(49,'Drivers & Assumptions'!C26)=0,ROUND('Drivers & Assumptions'!C27*(1+'Drivers & Assumptions'!C28)^4,0),0) -> 0 | AY15: =IF(MOD(50,'Drivers & Assumptions'!C26)=0,ROUND('Drivers & Assumptions'!C27*(1+'Drivers & Assumptions'!C28)^4,0),0) -> 0 | AZ15: =IF(MOD(51,'Drivers & Assumptions'!C26)=0,ROUND('Drivers & Assumptions'!C27*(1+'Drivers & Assumptions'!C28)^4,0),0) -> 12 | BA15: =IF(MOD(52,'Drivers & Assumptions'!C26)=0,ROUND('Drivers & Assumptions'!C27*(1+'Drivers & Assumptions'!C28)^4,0),0) -> 0 | BB15: =IF(MOD(53,'Drivers & Assumptions'!C26)=0,ROUND('Drivers & Assumptions'!C27*(1+'Drivers & Assumptions'!C28)^4,0),0) -> 0 | BC15: =IF(MOD(54,'Drivers & Assumptions'!C26)=0,ROUND('Drivers & Assumptions'!C27*(1+'Drivers & Assumptions'!C28)^4,0),0) -> 12 | BD15: =IF(MOD(55,'Drivers & Assumptions'!C26)=0,ROUND('Drivers & Assumptions'!C27*(1+'Drivers & Assumptions'!C28)^4,0),0) -> 0 | BE15: =IF(MOD(56,'Drivers & Assumptions'!C26)=0,ROUND('Drivers & Assumptions'!C27*(1+'Drivers & Assumptions'!C28)^4,0),0) -> 0 | BF15: =IF(MOD(57,'Drivers & Assumptions'!C26)=0,ROUND('Drivers & Assumptions'!C27*(1+'Drivers & Assumptions'!C28)^4,0),0) -> 12 | BG15: =IF(MOD(58,'Drivers & Assumptions'!C26)=0,ROUND('Drivers & Assumptions'!C27*(1+'Drivers & Assumptions'!C28)^4,0),0) -> 0 | BH15: =IF(MOD(59,'Drivers & Assumptions'!C26)=0,ROUND('Drivers & Assumptions'!C27*(1+'Drivers & Assumptions'!C28)^4,0),0) -> 0 | BI15: =IF(MOD(60,'Drivers & Assumptions'!C26)=0,ROUND('Drivers & Assumptions'!C27*(1+'Drivers & Assumptions'!C28)^4,0),0) -> 12
A16: Japan — Cases Ordered | B16: 0 | C16: 0 | D16: 0 | E16: 0 | F16: 0 | G16: 0 | H16: 0 | I16: 0 | J16: =IF(MOD(9,'Drivers & Assumptions'!C26)=0,ROUND('Drivers & Assumptions'!C27*(1+'Drivers & Assumptions'!C28)^0,0),0) -> 5 | K16: =IF(MOD(10,'Drivers & Assumptions'!C26)=0,ROUND('Drivers & Assumptions'!C27*(1+'Drivers & Assumptions'!C28)^0,0),0) -> 0 | L16: =IF(MOD(11,'Drivers & Assumptions'!C26)=0,ROUND('Drivers & Assumptions'!C27*(1+'Drivers & Assumptions'!C28)^0,0),0) -> 0 | M16: =IF(MOD(12,'Drivers & Assumptions'!C26)=0,ROUND('Drivers & Assumptions'!C27*(1+'Drivers & Assumptions'!C28)^0,0),0) -> 5 | N16: =IF(MOD(13,'Drivers & Assumptions'!C26)=0,ROUND('Drivers & Assumptions'!C27*(1+'Drivers & Assumptions'!C28)^1,0),0) -> 0 | O16: =IF(MOD(14,'Drivers & Assumptions'!C26)=0,ROUND('Drivers & Assumptions'!C27*(1+'Drivers & Assumptions'!C28)^1,0),0) -> 0 | P16: =IF(MOD(15,'Drivers & Assumptions'!C26)=0,ROUND('Drivers & Assumptions'!C27*(1+'Drivers & Assumptions'!C28)^1,0),0) -> 6 | Q16: =IF(MOD(16,'Drivers & Assumptions'!C26)=0,ROUND('Drivers & Assumptions'!C27*(1+'Drivers & Assumptions'!C28)^1,0),0) -> 0 | R16: =IF(MOD(17,'Drivers & Assumptions'!C26)=0,ROUND('Drivers & Assumptions'!C27*(1+'Drivers & Assumptions'!C28)^1,0),0) -> 0 | S16: =IF(MOD(18,'Drivers & Assumptions'!C26)=0,ROUND('Drivers & Assumptions'!C27*(1+'Drivers & Assumptions'!C28)^1,0),0) -> 6 | T16: =IF(MOD(19,'Drivers & Assumptions'!C26)=0,ROUND('Drivers & Assumptions'!C27*(1+'Drivers & Assumptions'!C28)^1,0),0) -> 0 | U16: =IF(MOD(20,'Drivers & Assumptions'!C26)=0,ROUND('Drivers & Assumptions'!C27*(1+'Drivers & Assumptions'!C28)^1,0),0) -> 0 | V16: =IF(MOD(21,'Drivers & Assumptions'!C26)=0,ROUND('Drivers & Assumptions'!C27*(1+'Drivers & Assumptions'!C28)^1,0),0) -> 6 | W16: =IF(MOD(22,'Drivers & Assumptions'!C26)=0,ROUND('Drivers & Assumptions'!C27*(1+'Drivers & Assumptions'!C28)^1,0),0) -> 0 | X16: =IF(MOD(23,'Drivers & Assumptions'!C26)=0,ROUND('Drivers & Assumptions'!C27*(1+'Drivers & Assumptions'!C28)^1,0),0) -> 0 | Y16: =IF(MOD(24,'Drivers & Assumptions'!C26)=0,ROUND('Drivers & Assumptions'!C27*(1+'Drivers & Assumptions'!C28)^1,0),0) -> 6 | Z16: =IF(MOD(25,'Drivers & Assumptions'!C26)=0,ROUND('Drivers & Assumptions'!C27*(1+'Drivers & Assumptions'!C28)^2,0),0) -> 0 | AA16: =IF(MOD(26,'Drivers & Assumptions'!C26)=0,ROUND('Drivers & Assumptions'!C27*(1+'Drivers & Assumptions'!C28)^2,0),0) -> 0 | AB16: =IF(MOD(27,'Drivers & Assumptions'!C26)=0,ROUND('Drivers & Assumptions'!C27*(1+'Drivers & Assumptions'!C28)^2,0),0) -> 8 | AC16: =IF(MOD(28,'Drivers & Assumptions'!C26)=0,ROUND('Drivers & Assumptions'!C27*(1+'Drivers & Assumptions'!C28)^2,0),0) -> 0 | AD16: =IF(MOD(29,'Drivers & Assumptions'!C26)=0,ROUND('Drivers & Assumptions'!C27*(1+'Drivers & Assumptions'!C28)^2,0),0) -> 0 | AE16: =IF(MOD(30,'Drivers & Assumptions'!C26)=0,ROUND('Drivers & Assumptions'!C27*(1+'Drivers & Assumptions'!C28)^2,0),0) -> 8 | AF16: =IF(MOD(31,'Drivers & Assumptions'!C26)=0,ROUND('Drivers & Assumptions'!C27*(1+'Drivers & Assumptions'!C28)^2,0),0) -> 0 | AG16: =IF(MOD(32,'Drivers & Assumptions'!C26)=0,ROUND('Drivers & Assumptions'!C27*(1+'Drivers & Assumptions'!C28)^2,0),0) -> 0 | AH16: =IF(MOD(33,'Drivers & Assumptions'!C26)=0,ROUND('Drivers & Assumptions'!C27*(1+'Drivers & Assumptions'!C28)^2,0),0) -> 8 | AI16: =IF(MOD(34,'Drivers & Assumptions'!C26)=0,ROUND('Drivers & Assumptions'!C27*(1+'Drivers & Assumptions'!C28)^2,0),0) -> 0 | AJ16: =IF(MOD(35,'Drivers & Assumptions'!C26)=0,ROUND('Drivers & Assumptions'!C27*(1+'Drivers & Assumptions'!C28)^2,0),0) -> 0 | AK16: =IF(MOD(36,'Drivers & Assumptions'!C26)=0,ROUND('Drivers & Assumptions'!C27*(1+'Drivers & Assumptions'!C28)^2,0),0) -> 8 | AL16: =IF(MOD(37,'Drivers & Assumptions'!C26)=0,ROUND('Drivers & Assumptions'!C27*(1+'Drivers & Assumptions'!C28)^3,0),0) -> 0 | AM16: =IF(MOD(38,'Drivers & Assumptions'!C26)=0,ROUND('Drivers & Assumptions'!C27*(1+'Drivers & Assumptions'!C28)^3,0),0) -> 0 | AN16: =IF(MOD(39,'Drivers & Assumptions'!C26)=0,ROUND('Drivers & Assumptions'!C27*(1+'Drivers & Assumptions'!C28)^3,0),0) -> 10 | AO16: =IF(MOD(40,'Drivers & Assumptions'!C26)=0,ROUND('Drivers & Assumptions'!C27*(1+'Drivers & Assumptions'!C28)^3,0),0) -> 0 | AP16: =IF(MOD(41,'Drivers & Assumptions'!C26)=0,ROUND('Drivers & Assumptions'!C27*(1+'Drivers & Assumptions'!C28)^3,0),0) -> 0 | AQ16: =IF(MOD(42,'Drivers & Assumptions'!C26)=0,ROUND('Drivers & Assumptions'!C27*(1+'Drivers & Assumptions'!C28)^3,0),0) -> 10 | AR16: =IF(MOD(43,'Drivers & Assumptions'!C26)=0,ROUND('Drivers & Assumptions'!C27*(1+'Drivers & Assumptions'!C28)^3,0),0) -> 0 | AS16: =IF(MOD(44,'Drivers & Assumptions'!C26)=0,ROUND('Drivers & Assumptions'!C27*(1+'Drivers & Assumptions'!C28)^3,0),0) -> 0 | AT16: =IF(MOD(45,'Drivers & Assumptions'!C26)=0,ROUND('Drivers & Assumptions'!C27*(1+'Drivers & Assumptions'!C28)^3,0),0) -> 10 | AU16: =IF(MOD(46,'Drivers & Assumptions'!C26)=0,ROUND('Drivers & Assumptions'!C27*(1+'Drivers & Assumptions'!C28)^3,0),0) -> 0 | AV16: =IF(MOD(47,'Drivers & Assumptions'!C26)=0,ROUND('Drivers & Assumptions'!C27*(1+'Drivers & Assumptions'!C28)^3,0),0) -> 0 | AW16: =IF(MOD(48,'Drivers & Assumptions'!C26)=0,ROUND('Drivers & Assumptions'!C27*(1+'Drivers & Assumptions'!C28)^3,0),0) -> 10 | AX16: =IF(MOD(49,'Drivers & Assumptions'!C26)=0,ROUND('Drivers & Assumptions'!C27*(1+'Drivers & Assumptions'!C28)^4,0),0) -> 0 | AY16: =IF(MOD(50,'Drivers & Assumptions'!C26)=0,ROUND('Drivers & Assumptions'!C27*(1+'Drivers & Assumptions'!C28)^4,0),0) -> 0 | AZ16: =IF(MOD(51,'Drivers & Assumptions'!C26)=0,ROUND('Drivers & Assumptions'!C27*(1+'Drivers & Assumptions'!C28)^4,0),0) -> 12 | BA16: =IF(MOD(52,'Drivers & Assumptions'!C26)=0,ROUND('Drivers & Assumptions'!C27*(1+'Drivers & Assumptions'!C28)^4,0),0) -> 0 | BB16: =IF(MOD(53,'Drivers & Assumptions'!C26)=0,ROUND('Drivers & Assumptions'!C27*(1+'Drivers & Assumptions'!C28)^4,0),0) -> 0 | BC16: =IF(MOD(54,'Drivers & Assumptions'!C26)=0,ROUND('Drivers & Assumptions'!C27*(1+'Drivers & Assumptions'!C28)^4,0),0) -> 12 | BD16: =IF(MOD(55,'Drivers & Assumptions'!C26)=0,ROUND('Drivers & Assumptions'!C27*(1+'Drivers & Assumptions'!C28)^4,0),0) -> 0 | BE16: =IF(MOD(56,'Drivers & Assumptions'!C26)=0,ROUND('Drivers & Assumptions'!C27*(1+'Drivers & Assumptions'!C28)^4,0),0) -> 0 | BF16: =IF(MOD(57,'Drivers & Assumptions'!C26)=0,ROUND('Drivers & Assumptions'!C27*(1+'Drivers & Assumptions'!C28)^4,0),0) -> 12 | BG16: =IF(MOD(58,'Drivers & Assumptions'!C26)=0,ROUND('Drivers & Assumptions'!C27*(1+'Drivers & Assumptions'!C28)^4,0),0) -> 0 | BH16: =IF(MOD(59,'Drivers & Assumptions'!C26)=0,ROUND('Drivers & Assumptions'!C27*(1+'Drivers & Assumptions'!C28)^4,0),0) -> 0 | BI16: =IF(MOD(60,'Drivers & Assumptions'!C26)=0,ROUND('Drivers & Assumptions'!C27*(1+'Drivers & Assumptions'!C28)^4,0),0) -> 12
A17: Country 11 — Cases Ordered | B17: 0 | C17: 0 | D17: 0 | E17: 0 | F17: 0 | G17: 0 | H17: 0 | I17: 0 | J17: =IF(MOD(9,'Drivers & Assumptions'!C26)=0,ROUND('Drivers & Assumptions'!C27*(1+'Drivers & Assumptions'!C28)^0,0),0) -> 5 | K17: =IF(MOD(10,'Drivers & Assumptions'!C26)=0,ROUND('Drivers & Assumptions'!C27*(1+'Drivers & Assumptions'!C28)^0,0),0) -> 0 | L17: =IF(MOD(11,'Drivers & Assumptions'!C26)=0,ROUND('Drivers & Assumptions'!C27*(1+'Drivers & Assumptions'!C28)^0,0),0) -> 0 | M17: =IF(MOD(12,'Drivers & Assumptions'!C26)=0,ROUND('Drivers & Assumptions'!C27*(1+'Drivers & Assumptions'!C28)^0,0),0) -> 5 | N17: =IF(MOD(13,'Drivers & Assumptions'!C26)=0,ROUND('Drivers & Assumptions'!C27*(1+'Drivers & Assumptions'!C28)^1,0),0) -> 0 | O17: =IF(MOD(14,'Drivers & Assumptions'!C26)=0,ROUND('Drivers & Assumptions'!C27*(1+'Drivers & Assumptions'!C28)^1,0),0) -> 0 | P17: =IF(MOD(15,'Drivers & Assumptions'!C26)=0,ROUND('Drivers & Assumptions'!C27*(1+'Drivers & Assumptions'!C28)^1,0),0) -> 6 | Q17: =IF(MOD(16,'Drivers & Assumptions'!C26)=0,ROUND('Drivers & Assumptions'!C27*(1+'Drivers & Assumptions'!C28)^1,0),0) -> 0 | R17: =IF(MOD(17,'Drivers & Assumptions'!C26)=0,ROUND('Drivers & Assumptions'!C27*(1+'Drivers & Assumptions'!C28)^1,0),0) -> 0 | S17: =IF(MOD(18,'Drivers & Assumptions'!C26)=0,ROUND('Drivers & Assumptions'!C27*(1+'Drivers & Assumptions'!C28)^1,0),0) -> 6 | T17: =IF(MOD(19,'Drivers & Assumptions'!C26)=0,ROUND('Drivers & Assumptions'!C27*(1+'Drivers & Assumptions'!C28)^1,0),0) -> 0 | U17: =IF(MOD(20,'Drivers & Assumptions'!C26)=0,ROUND('Drivers & Assumptions'!C27*(1+'Drivers & Assumptions'!C28)^1,0),0) -> 0 | V17: =IF(MOD(21,'Drivers & Assumptions'!C26)=0,ROUND('Drivers & Assumptions'!C27*(1+'Drivers & Assumptions'!C28)^1,0),0) -> 6 | W17: =IF(MOD(22,'Drivers & Assumptions'!C26)=0,ROUND('Drivers & Assumptions'!C27*(1+'Drivers & Assumptions'!C28)^1,0),0) -> 0 | X17: =IF(MOD(23,'Drivers & Assumptions'!C26)=0,ROUND('Drivers & Assumptions'!C27*(1+'Drivers & Assumptions'!C28)^1,0),0) -> 0 | Y17: =IF(MOD(24,'Drivers & Assumptions'!C26)=0,ROUND('Drivers & Assumptions'!C27*(1+'Drivers & Assumptions'!C28)^1,0),0) -> 6 | Z17: =IF(MOD(25,'Drivers & Assumptions'!C26)=0,ROUND('Drivers & Assumptions'!C27*(1+'Drivers & Assumptions'!C28)^2,0),0) -> 0 | AA17: =IF(MOD(26,'Drivers & Assumptions'!C26)=0,ROUND('Drivers & Assumptions'!C27*(1+'Drivers & Assumptions'!C28)^2,0),0) -> 0 | AB17: =IF(MOD(27,'Drivers & Assumptions'!C26)=0,ROUND('Drivers & Assumptions'!C27*(1+'Drivers & Assumptions'!C28)^2,0),0) -> 8 | AC17: =IF(MOD(28,'Drivers & Assumptions'!C26)=0,ROUND('Drivers & Assumptions'!C27*(1+'Drivers & Assumptions'!C28)^2,0),0) -> 0 | AD17: =IF(MOD(29,'Drivers & Assumptions'!C26)=0,ROUND('Drivers & Assumptions'!C27*(1+'Drivers & Assumptions'!C28)^2,0),0) -> 0 | AE17: =IF(MOD(30,'Drivers & Assumptions'!C26)=0,ROUND('Drivers & Assumptions'!C27*(1+'Drivers & Assumptions'!C28)^2,0),0) -> 8 | AF17: =IF(MOD(31,'Drivers & Assumptions'!C26)=0,ROUND('Drivers & Assumptions'!C27*(1+'Drivers & Assumptions'!C28)^2,0),0) -> 0 | AG17: =IF(MOD(32,'Drivers & Assumptions'!C26)=0,ROUND('Drivers & Assumptions'!C27*(1+'Drivers & Assumptions'!C28)^2,0),0) -> 0 | AH17: =IF(MOD(33,'Drivers & Assumptions'!C26)=0,ROUND('Drivers & Assumptions'!C27*(1+'Drivers & Assumptions'!C28)^2,0),0) -> 8 | AI17: =IF(MOD(34,'Drivers & Assumptions'!C26)=0,ROUND('Drivers & Assumptions'!C27*(1+'Drivers & Assumptions'!C28)^2,0),0) -> 0 | AJ17: =IF(MOD(35,'Drivers & Assumptions'!C26)=0,ROUND('Drivers & Assumptions'!C27*(1+'Drivers & Assumptions'!C28)^2,0),0) -> 0 | AK17: =IF(MOD(36,'Drivers & Assumptions'!C26)=0,ROUND('Drivers & Assumptions'!C27*(1+'Drivers & Assumptions'!C28)^2,0),0) -> 8 | AL17: =IF(MOD(37,'Drivers & Assumptions'!C26)=0,ROUND('Drivers & Assumptions'!C27*(1+'Drivers & Assumptions'!C28)^3,0),0) -> 0 | AM17: =IF(MOD(38,'Drivers & Assumptions'!C26)=0,ROUND('Drivers & Assumptions'!C27*(1+'Drivers & Assumptions'!C28)^3,0),0) -> 0 | AN17: =IF(MOD(39,'Drivers & Assumptions'!C26)=0,ROUND('Drivers & Assumptions'!C27*(1+'Drivers & Assumptions'!C28)^3,0),0) -> 10 | AO17: =IF(MOD(40,'Drivers & Assumptions'!C26)=0,ROUND('Drivers & Assumptions'!C27*(1+'Drivers & Assumptions'!C28)^3,0),0) -> 0 | AP17: =IF(MOD(41,'Drivers & Assumptions'!C26)=0,ROUND('Drivers & Assumptions'!C27*(1+'Drivers & Assumptions'!C28)^3,0),0) -> 0 | AQ17: =IF(MOD(42,'Drivers & Assumptions'!C26)=0,ROUND('Drivers & Assumptions'!C27*(1+'Drivers & Assumptions'!C28)^3,0),0) -> 10 | AR17: =IF(MOD(43,'Drivers & Assumptions'!C26)=0,ROUND('Drivers & Assumptions'!C27*(1+'Drivers & Assumptions'!C28)^3,0),0) -> 0 | AS17: =IF(MOD(44,'Drivers & Assumptions'!C26)=0,ROUND('Drivers & Assumptions'!C27*(1+'Drivers & Assumptions'!C28)^3,0),0) -> 0 | AT17: =IF(MOD(45,'Drivers & Assumptions'!C26)=0,ROUND('Drivers & Assumptions'!C27*(1+'Drivers & Assumptions'!C28)^3,0),0) -> 10 | AU17: =IF(MOD(46,'Drivers & Assumptions'!C26)=0,ROUND('Drivers & Assumptions'!C27*(1+'Drivers & Assumptions'!C28)^3,0),0) -> 0 | AV17: =IF(MOD(47,'Drivers & Assumptions'!C26)=0,ROUND('Drivers & Assumptions'!C27*(1+'Drivers & Assumptions'!C28)^3,0),0) -> 0 | AW17: =IF(MOD(48,'Drivers & Assumptions'!C26)=0,ROUND('Drivers & Assumptions'!C27*(1+'Drivers & Assumptions'!C28)^3,0),0) -> 10 | AX17: =IF(MOD(49,'Drivers & Assumptions'!C26)=0,ROUND('Drivers & Assumptions'!C27*(1+'Drivers & Assumptions'!C28)^4,0),0) -> 0 | AY17: =IF(MOD(50,'Drivers & Assumptions'!C26)=0,ROUND('Drivers & Assumptions'!C27*(1+'Drivers & Assumptions'!C28)^4,0),0) -> 0 | AZ17: =IF(MOD(51,'Drivers & Assumptions'!C26)=0,ROUND('Drivers & Assumptions'!C27*(1+'Drivers & Assumptions'!C28)^4,0),0) -> 12 | BA17: =IF(MOD(52,'Drivers & Assumptions'!C26)=0,ROUND('Drivers & Assumptions'!C27*(1+'Drivers & Assumptions'!C28)^4,0),0) -> 0 | BB17: =IF(MOD(53,'Drivers & Assumptions'!C26)=0,ROUND('Drivers & Assumptions'!C27*(1+'Drivers & Assumptions'!C28)^4,0),0) -> 0 | BC17: =IF(MOD(54,'Drivers & Assumptions'!C26)=0,ROUND('Drivers & Assumptions'!C27*(1+'Drivers & Assumptions'!C28)^4,0),0) -> 12 | BD17: =IF(MOD(55,'Drivers & Assumptions'!C26)=0,ROUND('Drivers & Assumptions'!C27*(1+'Drivers & Assumptions'!C28)^4,0),0) -> 0 | BE17: =IF(MOD(56,'Drivers & Assumptions'!C26)=0,ROUND('Drivers & Assumptions'!C27*(1+'Drivers & Assumptions'!C28)^4,0),0) -> 0 | BF17: =IF(MOD(57,'Drivers & Assumptions'!C26)=0,ROUND('Drivers & Assumptions'!C27*(1+'Drivers & Assumptions'!C28)^4,0),0) -> 12 | BG17: =IF(MOD(58,'Drivers & Assumptions'!C26)=0,ROUND('Drivers & Assumptions'!C27*(1+'Drivers & Assumptions'!C28)^4,0),0) -> 0 | BH17: =IF(MOD(59,'Drivers & Assumptions'!C26)=0,ROUND('Drivers & Assumptions'!C27*(1+'Drivers & Assumptions'!C28)^4,0),0) -> 0 | BI17: =IF(MOD(60,'Drivers & Assumptions'!C26)=0,ROUND('Drivers & Assumptions'!C27*(1+'Drivers & Assumptions'!C28)^4,0),0) -> 12
A18: Country 12 — Cases Ordered | B18: 0 | C18: 0 | D18: 0 | E18: 0 | F18: 0 | G18: 0 | H18: 0 | I18: 0 | J18: =IF(MOD(9,'Drivers & Assumptions'!C26)=0,ROUND('Drivers & Assumptions'!C27*(1+'Drivers & Assumptions'!C28)^0,0),0) -> 5 | K18: =IF(MOD(10,'Drivers & Assumptions'!C26)=0,ROUND('Drivers & Assumptions'!C27*(1+'Drivers & Assumptions'!C28)^0,0),0) -> 0 | L18: =IF(MOD(11,'Drivers & Assumptions'!C26)=0,ROUND('Drivers & Assumptions'!C27*(1+'Drivers & Assumptions'!C28)^0,0),0) -> 0 | M18: =IF(MOD(12,'Drivers & Assumptions'!C26)=0,ROUND('Drivers & Assumptions'!C27*(1+'Drivers & Assumptions'!C28)^0,0),0) -> 5 | N18: =IF(MOD(13,'Drivers & Assumptions'!C26)=0,ROUND('Drivers & Assumptions'!C27*(1+'Drivers & Assumptions'!C28)^1,0),0) -> 0 | O18: =IF(MOD(14,'Drivers & Assumptions'!C26)=0,ROUND('Drivers & Assumptions'!C27*(1+'Drivers & Assumptions'!C28)^1,0),0) -> 0 | P18: =IF(MOD(15,'Drivers & Assumptions'!C26)=0,ROUND('Drivers & Assumptions'!C27*(1+'Drivers & Assumptions'!C28)^1,0),0) -> 6 | Q18: =IF(MOD(16,'Drivers & Assumptions'!C26)=0,ROUND('Drivers & Assumptions'!C27*(1+'Drivers & Assumptions'!C28)^1,0),0) -> 0 | R18: =IF(MOD(17,'Drivers & Assumptions'!C26)=0,ROUND('Drivers & Assumptions'!C27*(1+'Drivers & Assumptions'!C28)^1,0),0) -> 0 | S18: =IF(MOD(18,'Drivers & Assumptions'!C26)=0,ROUND('Drivers & Assumptions'!C27*(1+'Drivers & Assumptions'!C28)^1,0),0) -> 6 | T18: =IF(MOD(19,'Drivers & Assumptions'!C26)=0,ROUND('Drivers & Assumptions'!C27*(1+'Drivers & Assumptions'!C28)^1,0),0) -> 0 | U18: =IF(MOD(20,'Drivers & Assumptions'!C26)=0,ROUND('Drivers & Assumptions'!C27*(1+'Drivers & Assumptions'!C28)^1,0),0) -> 0 | V18: =IF(MOD(21,'Drivers & Assumptions'!C26)=0,ROUND('Drivers & Assumptions'!C27*(1+'Drivers & Assumptions'!C28)^1,0),0) -> 6 | W18: =IF(MOD(22,'Drivers & Assumptions'!C26)=0,ROUND('Drivers & Assumptions'!C27*(1+'Drivers & Assumptions'!C28)^1,0),0) -> 0 | X18: =IF(MOD(23,'Drivers & Assumptions'!C26)=0,ROUND('Drivers & Assumptions'!C27*(1+'Drivers & Assumptions'!C28)^1,0),0) -> 0 | Y18: =IF(MOD(24,'Drivers & Assumptions'!C26)=0,ROUND('Drivers & Assumptions'!C27*(1+'Drivers & Assumptions'!C28)^1,0),0) -> 6 | Z18: =IF(MOD(25,'Drivers & Assumptions'!C26)=0,ROUND('Drivers & Assumptions'!C27*(1+'Drivers & Assumptions'!C28)^2,0),0) -> 0 | AA18: =IF(MOD(26,'Drivers & Assumptions'!C26)=0,ROUND('Drivers & Assumptions'!C27*(1+'Drivers & Assumptions'!C28)^2,0),0) -> 0 | AB18: =IF(MOD(27,'Drivers & Assumptions'!C26)=0,ROUND('Drivers & Assumptions'!C27*(1+'Drivers & Assumptions'!C28)^2,0),0) -> 8 | AC18: =IF(MOD(28,'Drivers & Assumptions'!C26)=0,ROUND('Drivers & Assumptions'!C27*(1+'Drivers & Assumptions'!C28)^2,0),0) -> 0 | AD18: =IF(MOD(29,'Drivers & Assumptions'!C26)=0,ROUND('Drivers & Assumptions'!C27*(1+'Drivers & Assumptions'!C28)^2,0),0) -> 0 | AE18: =IF(MOD(30,'Drivers & Assumptions'!C26)=0,ROUND('Drivers & Assumptions'!C27*(1+'Drivers & Assumptions'!C28)^2,0),0) -> 8 | AF18: =IF(MOD(31,'Drivers & Assumptions'!C26)=0,ROUND('Drivers & Assumptions'!C27*(1+'Drivers & Assumptions'!C28)^2,0),0) -> 0 | AG18: =IF(MOD(32,'Drivers & Assumptions'!C26)=0,ROUND('Drivers & Assumptions'!C27*(1+'Drivers & Assumptions'!C28)^2,0),0) -> 0 | AH18: =IF(MOD(33,'Drivers & Assumptions'!C26)=0,ROUND('Drivers & Assumptions'!C27*(1+'Drivers & Assumptions'!C28)^2,0),0) -> 8 | AI18: =IF(MOD(34,'Drivers & Assumptions'!C26)=0,ROUND('Drivers & Assumptions'!C27*(1+'Drivers & Assumptions'!C28)^2,0),0) -> 0 | AJ18: =IF(MOD(35,'Drivers & Assumptions'!C26)=0,ROUND('Drivers & Assumptions'!C27*(1+'Drivers & Assumptions'!C28)^2,0),0) -> 0 | AK18: =IF(MOD(36,'Drivers & Assumptions'!C26)=0,ROUND('Drivers & Assumptions'!C27*(1+'Drivers & Assumptions'!C28)^2,0),0) -> 8 | AL18: =IF(MOD(37,'Drivers & Assumptions'!C26)=0,ROUND('Drivers & Assumptions'!C27*(1+'Drivers & Assumptions'!C28)^3,0),0) -> 0 | AM18: =IF(MOD(38,'Drivers & Assumptions'!C26)=0,ROUND('Drivers & Assumptions'!C27*(1+'Drivers & Assumptions'!C28)^3,0),0) -> 0 | AN18: =IF(MOD(39,'Drivers & Assumptions'!C26)=0,ROUND('Drivers & Assumptions'!C27*(1+'Drivers & Assumptions'!C28)^3,0),0) -> 10 | AO18: =IF(MOD(40,'Drivers & Assumptions'!C26)=0,ROUND('Drivers & Assumptions'!C27*(1+'Drivers & Assumptions'!C28)^3,0),0) -> 0 | AP18: =IF(MOD(41,'Drivers & Assumptions'!C26)=0,ROUND('Drivers & Assumptions'!C27*(1+'Drivers & Assumptions'!C28)^3,0),0) -> 0 | AQ18: =IF(MOD(42,'Drivers & Assumptions'!C26)=0,ROUND('Drivers & Assumptions'!C27*(1+'Drivers & Assumptions'!C28)^3,0),0) -> 10 | AR18: =IF(MOD(43,'Drivers & Assumptions'!C26)=0,ROUND('Drivers & Assumptions'!C27*(1+'Drivers & Assumptions'!C28)^3,0),0) -> 0 | AS18: =IF(MOD(44,'Drivers & Assumptions'!C26)=0,ROUND('Drivers & Assumptions'!C27*(1+'Drivers & Assumptions'!C28)^3,0),0) -> 0 | AT18: =IF(MOD(45,'Drivers & Assumptions'!C26)=0,ROUND('Drivers & Assumptions'!C27*(1+'Drivers & Assumptions'!C28)^3,0),0) -> 10 | AU18: =IF(MOD(46,'Drivers & Assumptions'!C26)=0,ROUND('Drivers & Assumptions'!C27*(1+'Drivers & Assumptions'!C28)^3,0),0) -> 0 | AV18: =IF(MOD(47,'Drivers & Assumptions'!C26)=0,ROUND('Drivers & Assumptions'!C27*(1+'Drivers & Assumptions'!C28)^3,0),0) -> 0 | AW18: =IF(MOD(48,'Drivers & Assumptions'!C26)=0,ROUND('Drivers & Assumptions'!C27*(1+'Drivers & Assumptions'!C28)^3,0),0) -> 10 | AX18: =IF(MOD(49,'Drivers & Assumptions'!C26)=0,ROUND('Drivers & Assumptions'!C27*(1+'Drivers & Assumptions'!C28)^4,0),0) -> 0 | AY18: =IF(MOD(50,'Drivers & Assumptions'!C26)=0,ROUND('Drivers & Assumptions'!C27*(1+'Drivers & Assumptions'!C28)^4,0),0) -> 0 | AZ18: =IF(MOD(51,'Drivers & Assumptions'!C26)=0,ROUND('Drivers & Assumptions'!C27*(1+'Drivers & Assumptions'!C28)^4,0),0) -> 12 | BA18: =IF(MOD(52,'Drivers & Assumptions'!C26)=0,ROUND('Drivers & Assumptions'!C27*(1+'Drivers & Assumptions'!C28)^4,0),0) -> 0 | BB18: =IF(MOD(53,'Drivers & Assumptions'!C26)=0,ROUND('Drivers & Assumptions'!C27*(1+'Drivers & Assumptions'!C28)^4,0),0) -> 0 | BC18: =IF(MOD(54,'Drivers & Assumptions'!C26)=0,ROUND('Drivers & Assumptions'!C27*(1+'Drivers & Assumptions'!C28)^4,0),0) -> 12 | BD18: =IF(MOD(55,'Drivers & Assumptions'!C26)=0,ROUND('Drivers & Assumptions'!C27*(1+'Drivers & Assumptions'!C28)^4,0),0) -> 0 | BE18: =IF(MOD(56,'Drivers & Assumptions'!C26)=0,ROUND('Drivers & Assumptions'!C27*(1+'Drivers & Assumptions'!C28)^4,0),0) -> 0 | BF18: =IF(MOD(57,'Drivers & Assumptions'!C26)=0,ROUND('Drivers & Assumptions'!C27*(1+'Drivers & Assumptions'!C28)^4,0),0) -> 12 | BG18: =IF(MOD(58,'Drivers & Assumptions'!C26)=0,ROUND('Drivers & Assumptions'!C27*(1+'Drivers & Assumptions'!C28)^4,0),0) -> 0 | BH18: =IF(MOD(59,'Drivers & Assumptions'!C26)=0,ROUND('Drivers & Assumptions'!C27*(1+'Drivers & Assumptions'!C28)^4,0),0) -> 0 | BI18: =IF(MOD(60,'Drivers & Assumptions'!C26)=0,ROUND('Drivers & Assumptions'!C27*(1+'Drivers & Assumptions'!C28)^4,0),0) -> 12
A19: Country 13 — Cases Ordered | B19: 0 | C19: 0 | D19: 0 | E19: 0 | F19: 0 | G19: 0 | H19: 0 | I19: 0 | J19: =IF(MOD(9,'Drivers & Assumptions'!C26)=0,ROUND('Drivers & Assumptions'!C27*(1+'Drivers & Assumptions'!C28)^0,0),0) -> 5 | K19: =IF(MOD(10,'Drivers & Assumptions'!C26)=0,ROUND('Drivers & Assumptions'!C27*(1+'Drivers & Assumptions'!C28)^0,0),0) -> 0 | L19: =IF(MOD(11,'Drivers & Assumptions'!C26)=0,ROUND('Drivers & Assumptions'!C27*(1+'Drivers & Assumptions'!C28)^0,0),0) -> 0 | M19: =IF(MOD(12,'Drivers & Assumptions'!C26)=0,ROUND('Drivers & Assumptions'!C27*(1+'Drivers & Assumptions'!C28)^0,0),0) -> 5 | N19: =IF(MOD(13,'Drivers & Assumptions'!C26)=0,ROUND('Drivers & Assumptions'!C27*(1+'Drivers & Assumptions'!C28)^1,0),0) -> 0 | O19: =IF(MOD(14,'Drivers & Assumptions'!C26)=0,ROUND('Drivers & Assumptions'!C27*(1+'Drivers & Assumptions'!C28)^1,0),0) -> 0 | P19: =IF(MOD(15,'Drivers & Assumptions'!C26)=0,ROUND('Drivers & Assumptions'!C27*(1+'Drivers & Assumptions'!C28)^1,0),0) -> 6 | Q19: =IF(MOD(16,'Drivers & Assumptions'!C26)=0,ROUND('Drivers & Assumptions'!C27*(1+'Drivers & Assumptions'!C28)^1,0),0) -> 0 | R19: =IF(MOD(17,'Drivers & Assumptions'!C26)=0,ROUND('Drivers & Assumptions'!C27*(1+'Drivers & Assumptions'!C28)^1,0),0) -> 0 | S19: =IF(MOD(18,'Drivers & Assumptions'!C26)=0,ROUND('Drivers & Assumptions'!C27*(1+'Drivers & Assumptions'!C28)^1,0),0) -> 6 | T19: =IF(MOD(19,'Drivers & Assumptions'!C26)=0,ROUND('Drivers & Assumptions'!C27*(1+'Drivers & Assumptions'!C28)^1,0),0) -> 0 | U19: =IF(MOD(20,'Drivers & Assumptions'!C26)=0,ROUND('Drivers & Assumptions'!C27*(1+'Drivers & Assumptions'!C28)^1,0),0) -> 0 | V19: =IF(MOD(21,'Drivers & Assumptions'!C26)=0,ROUND('Drivers & Assumptions'!C27*(1+'Drivers & Assumptions'!C28)^1,0),0) -> 6 | W19: =IF(MOD(22,'Drivers & Assumptions'!C26)=0,ROUND('Drivers & Assumptions'!C27*(1+'Drivers & Assumptions'!C28)^1,0),0) -> 0 | X19: =IF(MOD(23,'Drivers & Assumptions'!C26)=0,ROUND('Drivers & Assumptions'!C27*(1+'Drivers & Assumptions'!C28)^1,0),0) -> 0 | Y19: =IF(MOD(24,'Drivers & Assumptions'!C26)=0,ROUND('Drivers & Assumptions'!C27*(1+'Drivers & Assumptions'!C28)^1,0),0) -> 6 | Z19: =IF(MOD(25,'Drivers & Assumptions'!C26)=0,ROUND('Drivers & Assumptions'!C27*(1+'Drivers & Assumptions'!C28)^2,0),0) -> 0 | AA19: =IF(MOD(26,'Drivers & Assumptions'!C26)=0,ROUND('Drivers & Assumptions'!C27*(1+'Drivers & Assumptions'!C28)^2,0),0) -> 0 | AB19: =IF(MOD(27,'Drivers & Assumptions'!C26)=0,ROUND('Drivers & Assumptions'!C27*(1+'Drivers & Assumptions'!C28)^2,0),0) -> 8 | AC19: =IF(MOD(28,'Drivers & Assumptions'!C26)=0,ROUND('Drivers & Assumptions'!C27*(1+'Drivers & Assumptions'!C28)^2,0),0) -> 0 | AD19: =IF(MOD(29,'Drivers & Assumptions'!C26)=0,ROUND('Drivers & Assumptions'!C27*(1+'Drivers & Assumptions'!C28)^2,0),0) -> 0 | AE19: =IF(MOD(30,'Drivers & Assumptions'!C26)=0,ROUND('Drivers & Assumptions'!C27*(1+'Drivers & Assumptions'!C28)^2,0),0) -> 8 | AF19: =IF(MOD(31,'Drivers & Assumptions'!C26)=0,ROUND('Drivers & Assumptions'!C27*(1+'Drivers & Assumptions'!C28)^2,0),0) -> 0 | AG19: =IF(MOD(32,'Drivers & Assumptions'!C26)=0,ROUND('Drivers & Assumptions'!C27*(1+'Drivers & Assumptions'!C28)^2,0),0) -> 0 | AH19: =IF(MOD(33,'Drivers & Assumptions'!C26)=0,ROUND('Drivers & Assumptions'!C27*(1+'Drivers & Assumptions'!C28)^2,0),0) -> 8 | AI19: =IF(MOD(34,'Drivers & Assumptions'!C26)=0,ROUND('Drivers & Assumptions'!C27*(1+'Drivers & Assumptions'!C28)^2,0),0) -> 0 | AJ19: =IF(MOD(35,'Drivers & Assumptions'!C26)=0,ROUND('Drivers & Assumptions'!C27*(1+'Drivers & Assumptions'!C28)^2,0),0) -> 0 | AK19: =IF(MOD(36,'Drivers & Assumptions'!C26)=0,ROUND('Drivers & Assumptions'!C27*(1+'Drivers & Assumptions'!C28)^2,0),0) -> 8 | AL19: =IF(MOD(37,'Drivers & Assumptions'!C26)=0,ROUND('Drivers & Assumptions'!C27*(1+'Drivers & Assumptions'!C28)^3,0),0) -> 0 | AM19: =IF(MOD(38,'Drivers & Assumptions'!C26)=0,ROUND('Drivers & Assumptions'!C27*(1+'Drivers & Assumptions'!C28)^3,0),0) -> 0 | AN19: =IF(MOD(39,'Drivers & Assumptions'!C26)=0,ROUND('Drivers & Assumptions'!C27*(1+'Drivers & Assumptions'!C28)^3,0),0) -> 10 | AO19: =IF(MOD(40,'Drivers & Assumptions'!C26)=0,ROUND('Drivers & Assumptions'!C27*(1+'Drivers & Assumptions'!C28)^3,0),0) -> 0 | AP19: =IF(MOD(41,'Drivers & Assumptions'!C26)=0,ROUND('Drivers & Assumptions'!C27*(1+'Drivers & Assumptions'!C28)^3,0),0) -> 0 | AQ19: =IF(MOD(42,'Drivers & Assumptions'!C26)=0,ROUND('Drivers & Assumptions'!C27*(1+'Drivers & Assumptions'!C28)^3,0),0) -> 10 | AR19: =IF(MOD(43,'Drivers & Assumptions'!C26)=0,ROUND('Drivers & Assumptions'!C27*(1+'Drivers & Assumptions'!C28)^3,0),0) -> 0 | AS19: =IF(MOD(44,'Drivers & Assumptions'!C26)=0,ROUND('Drivers & Assumptions'!C27*(1+'Drivers & Assumptions'!C28)^3,0),0) -> 0 | AT19: =IF(MOD(45,'Drivers & Assumptions'!C26)=0,ROUND('Drivers & Assumptions'!C27*(1+'Drivers & Assumptions'!C28)^3,0),0) -> 10 | AU19: =IF(MOD(46,'Drivers & Assumptions'!C26)=0,ROUND('Drivers & Assumptions'!C27*(1+'Drivers & Assumptions'!C28)^3,0),0) -> 0 | AV19: =IF(MOD(47,'Drivers & Assumptions'!C26)=0,ROUND('Drivers & Assumptions'!C27*(1+'Drivers & Assumptions'!C28)^3,0),0) -> 0 | AW19: =IF(MOD(48,'Drivers & Assumptions'!C26)=0,ROUND('Drivers & Assumptions'!C27*(1+'Drivers & Assumptions'!C28)^3,0),0) -> 10 | AX19: =IF(MOD(49,'Drivers & Assumptions'!C26)=0,ROUND('Drivers & Assumptions'!C27*(1+'Drivers & Assumptions'!C28)^4,0),0) -> 0 | AY19: =IF(MOD(50,'Drivers & Assumptions'!C26)=0,ROUND('Drivers & Assumptions'!C27*(1+'Drivers & Assumptions'!C28)^4,0),0) -> 0 | AZ19: =IF(MOD(51,'Drivers & Assumptions'!C26)=0,ROUND('Drivers & Assumptions'!C27*(1+'Drivers & Assumptions'!C28)^4,0),0) -> 12 | BA19: =IF(MOD(52,'Drivers & Assumptions'!C26)=0,ROUND('Drivers & Assumptions'!C27*(1+'Drivers & Assumptions'!C28)^4,0),0) -> 0 | BB19: =IF(MOD(53,'Drivers & Assumptions'!C26)=0,ROUND('Drivers & Assumptions'!C27*(1+'Drivers & Assumptions'!C28)^4,0),0) -> 0 | BC19: =IF(MOD(54,'Drivers & Assumptions'!C26)=0,ROUND('Drivers & Assumptions'!C27*(1+'Drivers & Assumptions'!C28)^4,0),0) -> 12 | BD19: =IF(MOD(55,'Drivers & Assumptions'!C26)=0,ROUND('Drivers & Assumptions'!C27*(1+'Drivers & Assumptions'!C28)^4,0),0) -> 0 | BE19: =IF(MOD(56,'Drivers & Assumptions'!C26)=0,ROUND('Drivers & Assumptions'!C27*(1+'Drivers & Assumptions'!C28)^4,0),0) -> 0 | BF19: =IF(MOD(57,'Drivers & Assumptions'!C26)=0,ROUND('Drivers & Assumptions'!C27*(1+'Drivers & Assumptions'!C28)^4,0),0) -> 12 | BG19: =IF(MOD(58,'Drivers & Assumptions'!C26)=0,ROUND('Drivers & Assumptions'!C27*(1+'Drivers & Assumptions'!C28)^4,0),0) -> 0 | BH19: =IF(MOD(59,'Drivers & Assumptions'!C26)=0,ROUND('Drivers & Assumptions'!C27*(1+'Drivers & Assumptions'!C28)^4,0),0) -> 0 | BI19: =IF(MOD(60,'Drivers & Assumptions'!C26)=0,ROUND('Drivers & Assumptions'!C27*(1+'Drivers & Assumptions'!C28)^4,0),0) -> 12
A20: Country 14 — Cases Ordered | B20: 0 | C20: 0 | D20: 0 | E20: 0 | F20: 0 | G20: 0 | H20: 0 | I20: 0 | J20: =IF(MOD(9,'Drivers & Assumptions'!C26)=0,ROUND('Drivers & Assumptions'!C27*(1+'Drivers & Assumptions'!C28)^0,0),0) -> 5 | K20: =IF(MOD(10,'Drivers & Assumptions'!C26)=0,ROUND('Drivers & Assumptions'!C27*(1+'Drivers & Assumptions'!C28)^0,0),0) -> 0 | L20: =IF(MOD(11,'Drivers & Assumptions'!C26)=0,ROUND('Drivers & Assumptions'!C27*(1+'Drivers & Assumptions'!C28)^0,0),0) -> 0 | M20: =IF(MOD(12,'Drivers & Assumptions'!C26)=0,ROUND('Drivers & Assumptions'!C27*(1+'Drivers & Assumptions'!C28)^0,0),0) -> 5 | N20: =IF(MOD(13,'Drivers & Assumptions'!C26)=0,ROUND('Drivers & Assumptions'!C27*(1+'Drivers & Assumptions'!C28)^1,0),0) -> 0 | O20: =IF(MOD(14,'Drivers & Assumptions'!C26)=0,ROUND('Drivers & Assumptions'!C27*(1+'Drivers & Assumptions'!C28)^1,0),0) -> 0 | P20: =IF(MOD(15,'Drivers & Assumptions'!C26)=0,ROUND('Drivers & Assumptions'!C27*(1+'Drivers & Assumptions'!C28)^1,0),0) -> 6 | Q20: =IF(MOD(16,'Drivers & Assumptions'!C26)=0,ROUND('Drivers & Assumptions'!C27*(1+'Drivers & Assumptions'!C28)^1,0),0) -> 0 | R20: =IF(MOD(17,'Drivers & Assumptions'!C26)=0,ROUND('Drivers & Assumptions'!C27*(1+'Drivers & Assumptions'!C28)^1,0),0) -> 0 | S20: =IF(MOD(18,'Drivers & Assumptions'!C26)=0,ROUND('Drivers & Assumptions'!C27*(1+'Drivers & Assumptions'!C28)^1,0),0) -> 6 | T20: =IF(MOD(19,'Drivers & Assumptions'!C26)=0,ROUND('Drivers & Assumptions'!C27*(1+'Drivers & Assumptions'!C28)^1,0),0) -> 0 | U20: =IF(MOD(20,'Drivers & Assumptions'!C26)=0,ROUND('Drivers & Assumptions'!C27*(1+'Drivers & Assumptions'!C28)^1,0),0) -> 0 | V20: =IF(MOD(21,'Drivers & Assumptions'!C26)=0,ROUND('Drivers & Assumptions'!C27*(1+'Drivers & Assumptions'!C28)^1,0),0) -> 6 | W20: =IF(MOD(22,'Drivers & Assumptions'!C26)=0,ROUND('Drivers & Assumptions'!C27*(1+'Drivers & Assumptions'!C28)^1,0),0) -> 0 | X20: =IF(MOD(23,'Drivers & Assumptions'!C26)=0,ROUND('Drivers & Assumptions'!C27*(1+'Drivers & Assumptions'!C28)^1,0),0) -> 0 | Y20: =IF(MOD(24,'Drivers & Assumptions'!C26)=0,ROUND('Drivers & Assumptions'!C27*(1+'Drivers & Assumptions'!C28)^1,0),0) -> 6 | Z20: =IF(MOD(25,'Drivers & Assumptions'!C26)=0,ROUND('Drivers & Assumptions'!C27*(1+'Drivers & Assumptions'!C28)^2,0),0) -> 0 | AA20: =IF(MOD(26,'Drivers & Assumptions'!C26)=0,ROUND('Drivers & Assumptions'!C27*(1+'Drivers & Assumptions'!C28)^2,0),0) -> 0 | AB20: =IF(MOD(27,'Drivers & Assumptions'!C26)=0,ROUND('Drivers & Assumptions'!C27*(1+'Drivers & Assumptions'!C28)^2,0),0) -> 8 | AC20: =IF(MOD(28,'Drivers & Assumptions'!C26)=0,ROUND('Drivers & Assumptions'!C27*(1+'Drivers & Assumptions'!C28)^2,0),0) -> 0 | AD20: =IF(MOD(29,'Drivers & Assumptions'!C26)=0,ROUND('Drivers & Assumptions'!C27*(1+'Drivers & Assumptions'!C28)^2,0),0) -> 0 | AE20: =IF(MOD(30,'Drivers & Assumptions'!C26)=0,ROUND('Drivers & Assumptions'!C27*(1+'Drivers & Assumptions'!C28)^2,0),0) -> 8 | AF20: =IF(MOD(31,'Drivers & Assumptions'!C26)=0,ROUND('Drivers & Assumptions'!C27*(1+'Drivers & Assumptions'!C28)^2,0),0) -> 0 | AG20: =IF(MOD(32,'Drivers & Assumptions'!C26)=0,ROUND('Drivers & Assumptions'!C27*(1+'Drivers & Assumptions'!C28)^2,0),0) -> 0 | AH20: =IF(MOD(33,'Drivers & Assumptions'!C26)=0,ROUND('Drivers & Assumptions'!C27*(1+'Drivers & Assumptions'!C28)^2,0),0) -> 8 | AI20: =IF(MOD(34,'Drivers & Assumptions'!C26)=0,ROUND('Drivers & Assumptions'!C27*(1+'Drivers & Assumptions'!C28)^2,0),0) -> 0 | AJ20: =IF(MOD(35,'Drivers & Assumptions'!C26)=0,ROUND('Drivers & Assumptions'!C27*(1+'Drivers & Assumptions'!C28)^2,0),0) -> 0 | AK20: =IF(MOD(36,'Drivers & Assumptions'!C26)=0,ROUND('Drivers & Assumptions'!C27*(1+'Drivers & Assumptions'!C28)^2,0),0) -> 8 | AL20: =IF(MOD(37,'Drivers & Assumptions'!C26)=0,ROUND('Drivers & Assumptions'!C27*(1+'Drivers & Assumptions'!C28)^3,0),0) -> 0 | AM20: =IF(MOD(38,'Drivers & Assumptions'!C26)=0,ROUND('Drivers & Assumptions'!C27*(1+'Drivers & Assumptions'!C28)^3,0),0) -> 0 | AN20: =IF(MOD(39,'Drivers & Assumptions'!C26)=0,ROUND('Drivers & Assumptions'!C27*(1+'Drivers & Assumptions'!C28)^3,0),0) -> 10 | AO20: =IF(MOD(40,'Drivers & Assumptions'!C26)=0,ROUND('Drivers & Assumptions'!C27*(1+'Drivers & Assumptions'!C28)^3,0),0) -> 0 | AP20: =IF(MOD(41,'Drivers & Assumptions'!C26)=0,ROUND('Drivers & Assumptions'!C27*(1+'Drivers & Assumptions'!C28)^3,0),0) -> 0 | AQ20: =IF(MOD(42,'Drivers & Assumptions'!C26)=0,ROUND('Drivers & Assumptions'!C27*(1+'Drivers & Assumptions'!C28)^3,0),0) -> 10 | AR20: =IF(MOD(43,'Drivers & Assumptions'!C26)=0,ROUND('Drivers & Assumptions'!C27*(1+'Drivers & Assumptions'!C28)^3,0),0) -> 0 | AS20: =IF(MOD(44,'Drivers & Assumptions'!C26)=0,ROUND('Drivers & Assumptions'!C27*(1+'Drivers & Assumptions'!C28)^3,0),0) -> 0 | AT20: =IF(MOD(45,'Drivers & Assumptions'!C26)=0,ROUND('Drivers & Assumptions'!C27*(1+'Drivers & Assumptions'!C28)^3,0),0) -> 10 | AU20: =IF(MOD(46,'Drivers & Assumptions'!C26)=0,ROUND('Drivers & Assumptions'!C27*(1+'Drivers & Assumptions'!C28)^3,0),0) -> 0 | AV20: =IF(MOD(47,'Drivers & Assumptions'!C26)=0,ROUND('Drivers & Assumptions'!C27*(1+'Drivers & Assumptions'!C28)^3,0),0) -> 0 | AW20: =IF(MOD(48,'Drivers & Assumptions'!C26)=0,ROUND('Drivers & Assumptions'!C27*(1+'Drivers & Assumptions'!C28)^3,0),0) -> 10 | AX20: =IF(MOD(49,'Drivers & Assumptions'!C26)=0,ROUND('Drivers & Assumptions'!C27*(1+'Drivers & Assumptions'!C28)^4,0),0) -> 0 | AY20: =IF(MOD(50,'Drivers & Assumptions'!C26)=0,ROUND('Drivers & Assumptions'!C27*(1+'Drivers & Assumptions'!C28)^4,0),0) -> 0 | AZ20: =IF(MOD(51,'Drivers & Assumptions'!C26)=0,ROUND('Drivers & Assumptions'!C27*(1+'Drivers & Assumptions'!C28)^4,0),0) -> 12 | BA20: =IF(MOD(52,'Drivers & Assumptions'!C26)=0,ROUND('Drivers & Assumptions'!C27*(1+'Drivers & Assumptions'!C28)^4,0),0) -> 0 | BB20: =IF(MOD(53,'Drivers & Assumptions'!C26)=0,ROUND('Drivers & Assumptions'!C27*(1+'Drivers & Assumptions'!C28)^4,0),0) -> 0 | BC20: =IF(MOD(54,'Drivers & Assumptions'!C26)=0,ROUND('Drivers & Assumptions'!C27*(1+'Drivers & Assumptions'!C28)^4,0),0) -> 12 | BD20: =IF(MOD(55,'Drivers & Assumptions'!C26)=0,ROUND('Drivers & Assumptions'!C27*(1+'Drivers & Assumptions'!C28)^4,0),0) -> 0 | BE20: =IF(MOD(56,'Drivers & Assumptions'!C26)=0,ROUND('Drivers & Assumptions'!C27*(1+'Drivers & Assumptions'!C28)^4,0),0) -> 0 | BF20: =IF(MOD(57,'Drivers & Assumptions'!C26)=0,ROUND('Drivers & Assumptions'!C27*(1+'Drivers & Assumptions'!C28)^4,0),0) -> 12 | BG20: =IF(MOD(58,'Drivers & Assumptions'!C26)=0,ROUND('Drivers & Assumptions'!C27*(1+'Drivers & Assumptions'!C28)^4,0),0) -> 0 | BH20: =IF(MOD(59,'Drivers & Assumptions'!C26)=0,ROUND('Drivers & Assumptions'!C27*(1+'Drivers & Assumptions'!C28)^4,0),0) -> 0 | BI20: =IF(MOD(60,'Drivers & Assumptions'!C26)=0,ROUND('Drivers & Assumptions'!C27*(1+'Drivers & Assumptions'!C28)^4,0),0) -> 12
A21: Country 15 — Cases Ordered | B21: 0 | C21: 0 | D21: 0 | E21: 0 | F21: 0 | G21: 0 | H21: 0 | I21: 0 | J21: =IF(MOD(9,'Drivers & Assumptions'!C26)=0,ROUND('Drivers & Assumptions'!C27*(1+'Drivers & Assumptions'!C28)^0,0),0) -> 5 | K21: =IF(MOD(10,'Drivers & Assumptions'!C26)=0,ROUND('Drivers & Assumptions'!C27*(1+'Drivers & Assumptions'!C28)^0,0),0) -> 0 | L21: =IF(MOD(11,'Drivers & Assumptions'!C26)=0,ROUND('Drivers & Assumptions'!C27*(1+'Drivers & Assumptions'!C28)^0,0),0) -> 0 | M21: =IF(MOD(12,'Drivers & Assumptions'!C26)=0,ROUND('Drivers & Assumptions'!C27*(1+'Drivers & Assumptions'!C28)^0,0),0) -> 5 | N21: =IF(MOD(13,'Drivers & Assumptions'!C26)=0,ROUND('Drivers & Assumptions'!C27*(1+'Drivers & Assumptions'!C28)^1,0),0) -> 0 | O21: =IF(MOD(14,'Drivers & Assumptions'!C26)=0,ROUND('Drivers & Assumptions'!C27*(1+'Drivers & Assumptions'!C28)^1,0),0) -> 0 | P21: =IF(MOD(15,'Drivers & Assumptions'!C26)=0,ROUND('Drivers & Assumptions'!C27*(1+'Drivers & Assumptions'!C28)^1,0),0) -> 6 | Q21: =IF(MOD(16,'Drivers & Assumptions'!C26)=0,ROUND('Drivers & Assumptions'!C27*(1+'Drivers & Assumptions'!C28)^1,0),0) -> 0 | R21: =IF(MOD(17,'Drivers & Assumptions'!C26)=0,ROUND('Drivers & Assumptions'!C27*(1+'Drivers & Assumptions'!C28)^1,0),0) -> 0 | S21: =IF(MOD(18,'Drivers & Assumptions'!C26)=0,ROUND('Drivers & Assumptions'!C27*(1+'Drivers & Assumptions'!C28)^1,0),0) -> 6 | T21: =IF(MOD(19,'Drivers & Assumptions'!C26)=0,ROUND('Drivers & Assumptions'!C27*(1+'Drivers & Assumptions'!C28)^1,0),0) -> 0 | U21: =IF(MOD(20,'Drivers & Assumptions'!C26)=0,ROUND('Drivers & Assumptions'!C27*(1+'Drivers & Assumptions'!C28)^1,0),0) -> 0 | V21: =IF(MOD(21,'Drivers & Assumptions'!C26)=0,ROUND('Drivers & Assumptions'!C27*(1+'Drivers & Assumptions'!C28)^1,0),0) -> 6 | W21: =IF(MOD(22,'Drivers & Assumptions'!C26)=0,ROUND('Drivers & Assumptions'!C27*(1+'Drivers & Assumptions'!C28)^1,0),0) -> 0 | X21: =IF(MOD(23,'Drivers & Assumptions'!C26)=0,ROUND('Drivers & Assumptions'!C27*(1+'Drivers & Assumptions'!C28)^1,0),0) -> 0 | Y21: =IF(MOD(24,'Drivers & Assumptions'!C26)=0,ROUND('Drivers & Assumptions'!C27*(1+'Drivers & Assumptions'!C28)^1,0),0) -> 6 | Z21: =IF(MOD(25,'Drivers & Assumptions'!C26)=0,ROUND('Drivers & Assumptions'!C27*(1+'Drivers & Assumptions'!C28)^2,0),0) -> 0 | AA21: =IF(MOD(26,'Drivers & Assumptions'!C26)=0,ROUND('Drivers & Assumptions'!C27*(1+'Drivers & Assumptions'!C28)^2,0),0) -> 0 | AB21: =IF(MOD(27,'Drivers & Assumptions'!C26)=0,ROUND('Drivers & Assumptions'!C27*(1+'Drivers & Assumptions'!C28)^2,0),0) -> 8 | AC21: =IF(MOD(28,'Drivers & Assumptions'!C26)=0,ROUND('Drivers & Assumptions'!C27*(1+'Drivers & Assumptions'!C28)^2,0),0) -> 0 | AD21: =IF(MOD(29,'Drivers & Assumptions'!C26)=0,ROUND('Drivers & Assumptions'!C27*(1+'Drivers & Assumptions'!C28)^2,0),0) -> 0 | AE21: =IF(MOD(30,'Drivers & Assumptions'!C26)=0,ROUND('Drivers & Assumptions'!C27*(1+'Drivers & Assumptions'!C28)^2,0),0) -> 8 | AF21: =IF(MOD(31,'Drivers & Assumptions'!C26)=0,ROUND('Drivers & Assumptions'!C27*(1+'Drivers & Assumptions'!C28)^2,0),0) -> 0 | AG21: =IF(MOD(32,'Drivers & Assumptions'!C26)=0,ROUND('Drivers & Assumptions'!C27*(1+'Drivers & Assumptions'!C28)^2,0),0) -> 0 | AH21: =IF(MOD(33,'Drivers & Assumptions'!C26)=0,ROUND('Drivers & Assumptions'!C27*(1+'Drivers & Assumptions'!C28)^2,0),0) -> 8 | AI21: =IF(MOD(34,'Drivers & Assumptions'!C26)=0,ROUND('Drivers & Assumptions'!C27*(1+'Drivers & Assumptions'!C28)^2,0),0) -> 0 | AJ21: =IF(MOD(35,'Drivers & Assumptions'!C26)=0,ROUND('Drivers & Assumptions'!C27*(1+'Drivers & Assumptions'!C28)^2,0),0) -> 0 | AK21: =IF(MOD(36,'Drivers & Assumptions'!C26)=0,ROUND('Drivers & Assumptions'!C27*(1+'Drivers & Assumptions'!C28)^2,0),0) -> 8 | AL21: =IF(MOD(37,'Drivers & Assumptions'!C26)=0,ROUND('Drivers & Assumptions'!C27*(1+'Drivers & Assumptions'!C28)^3,0),0) -> 0 | AM21: =IF(MOD(38,'Drivers & Assumptions'!C26)=0,ROUND('Drivers & Assumptions'!C27*(1+'Drivers & Assumptions'!C28)^3,0),0) -> 0 | AN21: =IF(MOD(39,'Drivers & Assumptions'!C26)=0,ROUND('Drivers & Assumptions'!C27*(1+'Drivers & Assumptions'!C28)^3,0),0) -> 10 | AO21: =IF(MOD(40,'Drivers & Assumptions'!C26)=0,ROUND('Drivers & Assumptions'!C27*(1+'Drivers & Assumptions'!C28)^3,0),0) -> 0 | AP21: =IF(MOD(41,'Drivers & Assumptions'!C26)=0,ROUND('Drivers & Assumptions'!C27*(1+'Drivers & Assumptions'!C28)^3,0),0) -> 0 | AQ21: =IF(MOD(42,'Drivers & Assumptions'!C26)=0,ROUND('Drivers & Assumptions'!C27*(1+'Drivers & Assumptions'!C28)^3,0),0) -> 10 | AR21: =IF(MOD(43,'Drivers & Assumptions'!C26)=0,ROUND('Drivers & Assumptions'!C27*(1+'Drivers & Assumptions'!C28)^3,0),0) -> 0 | AS21: =IF(MOD(44,'Drivers & Assumptions'!C26)=0,ROUND('Drivers & Assumptions'!C27*(1+'Drivers & Assumptions'!C28)^3,0),0) -> 0 | AT21: =IF(MOD(45,'Drivers & Assumptions'!C26)=0,ROUND('Drivers & Assumptions'!C27*(1+'Drivers & Assumptions'!C28)^3,0),0) -> 10 | AU21: =IF(MOD(46,'Drivers & Assumptions'!C26)=0,ROUND('Drivers & Assumptions'!C27*(1+'Drivers & Assumptions'!C28)^3,0),0) -> 0 | AV21: =IF(MOD(47,'Drivers & Assumptions'!C26)=0,ROUND('Drivers & Assumptions'!C27*(1+'Drivers & Assumptions'!C28)^3,0),0) -> 0 | AW21: =IF(MOD(48,'Drivers & Assumptions'!C26)=0,ROUND('Drivers & Assumptions'!C27*(1+'Drivers & Assumptions'!C28)^3,0),0) -> 10 | AX21: =IF(MOD(49,'Drivers & Assumptions'!C26)=0,ROUND('Drivers & Assumptions'!C27*(1+'Drivers & Assumptions'!C28)^4,0),0) -> 0 | AY21: =IF(MOD(50,'Drivers & Assumptions'!C26)=0,ROUND('Drivers & Assumptions'!C27*(1+'Drivers & Assumptions'!C28)^4,0),0) -> 0 | AZ21: =IF(MOD(51,'Drivers & Assumptions'!C26)=0,ROUND('Drivers & Assumptions'!C27*(1+'Drivers & Assumptions'!C28)^4,0),0) -> 12 | BA21: =IF(MOD(52,'Drivers & Assumptions'!C26)=0,ROUND('Drivers & Assumptions'!C27*(1+'Drivers & Assumptions'!C28)^4,0),0) -> 0 | BB21: =IF(MOD(53,'Drivers & Assumptions'!C26)=0,ROUND('Drivers & Assumptions'!C27*(1+'Drivers & Assumptions'!C28)^4,0),0) -> 0 | BC21: =IF(MOD(54,'Drivers & Assumptions'!C26)=0,ROUND('Drivers & Assumptions'!C27*(1+'Drivers & Assumptions'!C28)^4,0),0) -> 12 | BD21: =IF(MOD(55,'Drivers & Assumptions'!C26)=0,ROUND('Drivers & Assumptions'!C27*(1+'Drivers & Assumptions'!C28)^4,0),0) -> 0 | BE21: =IF(MOD(56,'Drivers & Assumptions'!C26)=0,ROUND('Drivers & Assumptions'!C27*(1+'Drivers & Assumptions'!C28)^4,0),0) -> 0 | BF21: =IF(MOD(57,'Drivers & Assumptions'!C26)=0,ROUND('Drivers & Assumptions'!C27*(1+'Drivers & Assumptions'!C28)^4,0),0) -> 12 | BG21: =IF(MOD(58,'Drivers & Assumptions'!C26)=0,ROUND('Drivers & Assumptions'!C27*(1+'Drivers & Assumptions'!C28)^4,0),0) -> 0 | BH21: =IF(MOD(59,'Drivers & Assumptions'!C26)=0,ROUND('Drivers & Assumptions'!C27*(1+'Drivers & Assumptions'!C28)^4,0),0) -> 0 | BI21: =IF(MOD(60,'Drivers & Assumptions'!C26)=0,ROUND('Drivers & Assumptions'!C27*(1+'Drivers & Assumptions'!C28)^4,0),0) -> 12
A22: Country 16 — Cases Ordered | B22: 0 | C22: 0 | D22: 0 | E22: 0 | F22: 0 | G22: 0 | H22: 0 | I22: 0 | J22: =IF(MOD(9,'Drivers & Assumptions'!C26)=0,ROUND('Drivers & Assumptions'!C27*(1+'Drivers & Assumptions'!C28)^0,0),0) -> 5 | K22: =IF(MOD(10,'Drivers & Assumptions'!C26)=0,ROUND('Drivers & Assumptions'!C27*(1+'Drivers & Assumptions'!C28)^0,0),0) -> 0 | L22: =IF(MOD(11,'Drivers & Assumptions'!C26)=0,ROUND('Drivers & Assumptions'!C27*(1+'Drivers & Assumptions'!C28)^0,0),0) -> 0 | M22: =IF(MOD(12,'Drivers & Assumptions'!C26)=0,ROUND('Drivers & Assumptions'!C27*(1+'Drivers & Assumptions'!C28)^0,0),0) -> 5 | N22: =IF(MOD(13,'Drivers & Assumptions'!C26)=0,ROUND('Drivers & Assumptions'!C27*(1+'Drivers & Assumptions'!C28)^1,0),0) -> 0 | O22: =IF(MOD(14,'Drivers & Assumptions'!C26)=0,ROUND('Drivers & Assumptions'!C27*(1+'Drivers & Assumptions'!C28)^1,0),0) -> 0 | P22: =IF(MOD(15,'Drivers & Assumptions'!C26)=0,ROUND('Drivers & Assumptions'!C27*(1+'Drivers & Assumptions'!C28)^1,0),0) -> 6 | Q22: =IF(MOD(16,'Drivers & Assumptions'!C26)=0,ROUND('Drivers & Assumptions'!C27*(1+'Drivers & Assumptions'!C28)^1,0),0) -> 0 | R22: =IF(MOD(17,'Drivers & Assumptions'!C26)=0,ROUND('Drivers & Assumptions'!C27*(1+'Drivers & Assumptions'!C28)^1,0),0) -> 0 | S22: =IF(MOD(18,'Drivers & Assumptions'!C26)=0,ROUND('Drivers & Assumptions'!C27*(1+'Drivers & Assumptions'!C28)^1,0),0) -> 6 | T22: =IF(MOD(19,'Drivers & Assumptions'!C26)=0,ROUND('Drivers & Assumptions'!C27*(1+'Drivers & Assumptions'!C28)^1,0),0) -> 0 | U22: =IF(MOD(20,'Drivers & Assumptions'!C26)=0,ROUND('Drivers & Assumptions'!C27*(1+'Drivers & Assumptions'!C28)^1,0),0) -> 0 | V22: =IF(MOD(21,'Drivers & Assumptions'!C26)=0,ROUND('Drivers & Assumptions'!C27*(1+'Drivers & Assumptions'!C28)^1,0),0) -> 6 | W22: =IF(MOD(22,'Drivers & Assumptions'!C26)=0,ROUND('Drivers & Assumptions'!C27*(1+'Drivers & Assumptions'!C28)^1,0),0) -> 0 | X22: =IF(MOD(23,'Drivers & Assumptions'!C26)=0,ROUND('Drivers & Assumptions'!C27*(1+'Drivers & Assumptions'!C28)^1,0),0) -> 0 | Y22: =IF(MOD(24,'Drivers & Assumptions'!C26)=0,ROUND('Drivers & Assumptions'!C27*(1+'Drivers & Assumptions'!C28)^1,0),0) -> 6 | Z22: =IF(MOD(25,'Drivers & Assumptions'!C26)=0,ROUND('Drivers & Assumptions'!C27*(1+'Drivers & Assumptions'!C28)^2,0),0) -> 0 | AA22: =IF(MOD(26,'Drivers & Assumptions'!C26)=0,ROUND('Drivers & Assumptions'!C27*(1+'Drivers & Assumptions'!C28)^2,0),0) -> 0 | AB22: =IF(MOD(27,'Drivers & Assumptions'!C26)=0,ROUND('Drivers & Assumptions'!C27*(1+'Drivers & Assumptions'!C28)^2,0),0) -> 8 | AC22: =IF(MOD(28,'Drivers & Assumptions'!C26)=0,ROUND('Drivers & Assumptions'!C27*(1+'Drivers & Assumptions'!C28)^2,0),0) -> 0 | AD22: =IF(MOD(29,'Drivers & Assumptions'!C26)=0,ROUND('Drivers & Assumptions'!C27*(1+'Drivers & Assumptions'!C28)^2,0),0) -> 0 | AE22: =IF(MOD(30,'Drivers & Assumptions'!C26)=0,ROUND('Drivers & Assumptions'!C27*(1+'Drivers & Assumptions'!C28)^2,0),0) -> 8 | AF22: =IF(MOD(31,'Drivers & Assumptions'!C26)=0,ROUND('Drivers & Assumptions'!C27*(1+'Drivers & Assumptions'!C28)^2,0),0) -> 0 | AG22: =IF(MOD(32,'Drivers & Assumptions'!C26)=0,ROUND('Drivers & Assumptions'!C27*(1+'Drivers & Assumptions'!C28)^2,0),0) -> 0 | AH22: =IF(MOD(33,'Drivers & Assumptions'!C26)=0,ROUND('Drivers & Assumptions'!C27*(1+'Drivers & Assumptions'!C28)^2,0),0) -> 8 | AI22: =IF(MOD(34,'Drivers & Assumptions'!C26)=0,ROUND('Drivers & Assumptions'!C27*(1+'Drivers & Assumptions'!C28)^2,0),0) -> 0 | AJ22: =IF(MOD(35,'Drivers & Assumptions'!C26)=0,ROUND('Drivers & Assumptions'!C27*(1+'Drivers & Assumptions'!C28)^2,0),0) -> 0 | AK22: =IF(MOD(36,'Drivers & Assumptions'!C26)=0,ROUND('Drivers & Assumptions'!C27*(1+'Drivers & Assumptions'!C28)^2,0),0) -> 8 | AL22: =IF(MOD(37,'Drivers & Assumptions'!C26)=0,ROUND('Drivers & Assumptions'!C27*(1+'Drivers & Assumptions'!C28)^3,0),0) -> 0 | AM22: =IF(MOD(38,'Drivers & Assumptions'!C26)=0,ROUND('Drivers & Assumptions'!C27*(1+'Drivers & Assumptions'!C28)^3,0),0) -> 0 | AN22: =IF(MOD(39,'Drivers & Assumptions'!C26)=0,ROUND('Drivers & Assumptions'!C27*(1+'Drivers & Assumptions'!C28)^3,0),0) -> 10 | AO22: =IF(MOD(40,'Drivers & Assumptions'!C26)=0,ROUND('Drivers & Assumptions'!C27*(1+'Drivers & Assumptions'!C28)^3,0),0) -> 0 | AP22: =IF(MOD(41,'Drivers & Assumptions'!C26)=0,ROUND('Drivers & Assumptions'!C27*(1+'Drivers & Assumptions'!C28)^3,0),0) -> 0 | AQ22: =IF(MOD(42,'Drivers & Assumptions'!C26)=0,ROUND('Drivers & Assumptions'!C27*(1+'Drivers & Assumptions'!C28)^3,0),0) -> 10 | AR22: =IF(MOD(43,'Drivers & Assumptions'!C26)=0,ROUND('Drivers & Assumptions'!C27*(1+'Drivers & Assumptions'!C28)^3,0),0) -> 0 | AS22: =IF(MOD(44,'Drivers & Assumptions'!C26)=0,ROUND('Drivers & Assumptions'!C27*(1+'Drivers & Assumptions'!C28)^3,0),0) -> 0 | AT22: =IF(MOD(45,'Drivers & Assumptions'!C26)=0,ROUND('Drivers & Assumptions'!C27*(1+'Drivers & Assumptions'!C28)^3,0),0) -> 10 | AU22: =IF(MOD(46,'Drivers & Assumptions'!C26)=0,ROUND('Drivers & Assumptions'!C27*(1+'Drivers & Assumptions'!C28)^3,0),0) -> 0 | AV22: =IF(MOD(47,'Drivers & Assumptions'!C26)=0,ROUND('Drivers & Assumptions'!C27*(1+'Drivers & Assumptions'!C28)^3,0),0) -> 0 | AW22: =IF(MOD(48,'Drivers & Assumptions'!C26)=0,ROUND('Drivers & Assumptions'!C27*(1+'Drivers & Assumptions'!C28)^3,0),0) -> 10 | AX22: =IF(MOD(49,'Drivers & Assumptions'!C26)=0,ROUND('Drivers & Assumptions'!C27*(1+'Drivers & Assumptions'!C28)^4,0),0) -> 0 | AY22: =IF(MOD(50,'Drivers & Assumptions'!C26)=0,ROUND('Drivers & Assumptions'!C27*(1+'Drivers & Assumptions'!C28)^4,0),0) -> 0 | AZ22: =IF(MOD(51,'Drivers & Assumptions'!C26)=0,ROUND('Drivers & Assumptions'!C27*(1+'Drivers & Assumptions'!C28)^4,0),0) -> 12 | BA22: =IF(MOD(52,'Drivers & Assumptions'!C26)=0,ROUND('Drivers & Assumptions'!C27*(1+'Drivers & Assumptions'!C28)^4,0),0) -> 0 | BB22: =IF(MOD(53,'Drivers & Assumptions'!C26)=0,ROUND('Drivers & Assumptions'!C27*(1+'Drivers & Assumptions'!C28)^4,0),0) -> 0 | BC22: =IF(MOD(54,'Drivers & Assumptions'!C26)=0,ROUND('Drivers & Assumptions'!C27*(1+'Drivers & Assumptions'!C28)^4,0),0) -> 12 | BD22: =IF(MOD(55,'Drivers & Assumptions'!C26)=0,ROUND('Drivers & Assumptions'!C27*(1+'Drivers & Assumptions'!C28)^4,0),0) -> 0 | BE22: =IF(MOD(56,'Drivers & Assumptions'!C26)=0,ROUND('Drivers & Assumptions'!C27*(1+'Drivers & Assumptions'!C28)^4,0),0) -> 0 | BF22: =IF(MOD(57,'Drivers & Assumptions'!C26)=0,ROUND('Drivers & Assumptions'!C27*(1+'Drivers & Assumptions'!C28)^4,0),0) -> 12 | BG22: =IF(MOD(58,'Drivers & Assumptions'!C26)=0,ROUND('Drivers & Assumptions'!C27*(1+'Drivers & Assumptions'!C28)^4,0),0) -> 0 | BH22: =IF(MOD(59,'Drivers & Assumptions'!C26)=0,ROUND('Drivers & Assumptions'!C27*(1+'Drivers & Assumptions'!C28)^4,0),0) -> 0 | BI22: =IF(MOD(60,'Drivers & Assumptions'!C26)=0,ROUND('Drivers & Assumptions'!C27*(1+'Drivers & Assumptions'!C28)^4,0),0) -> 12
A23: Country 17 — Cases Ordered | B23: 0 | C23: 0 | D23: 0 | E23: 0 | F23: 0 | G23: 0 | H23: 0 | I23: 0 | J23: =IF(MOD(9,'Drivers & Assumptions'!C26)=0,ROUND('Drivers & Assumptions'!C27*(1+'Drivers & Assumptions'!C28)^0,0),0) -> 5 | K23: =IF(MOD(10,'Drivers & Assumptions'!C26)=0,ROUND('Drivers & Assumptions'!C27*(1+'Drivers & Assumptions'!C28)^0,0),0) -> 0 | L23: =IF(MOD(11,'Drivers & Assumptions'!C26)=0,ROUND('Drivers & Assumptions'!C27*(1+'Drivers & Assumptions'!C28)^0,0),0) -> 0 | M23: =IF(MOD(12,'Drivers & Assumptions'!C26)=0,ROUND('Drivers & Assumptions'!C27*(1+'Drivers & Assumptions'!C28)^0,0),0) -> 5 | N23: =IF(MOD(13,'Drivers & Assumptions'!C26)=0,ROUND('Drivers & Assumptions'!C27*(1+'Drivers & Assumptions'!C28)^1,0),0) -> 0 | O23: =IF(MOD(14,'Drivers & Assumptions'!C26)=0,ROUND('Drivers & Assumptions'!C27*(1+'Drivers & Assumptions'!C28)^1,0),0) -> 0 | P23: =IF(MOD(15,'Drivers & Assumptions'!C26)=0,ROUND('Drivers & Assumptions'!C27*(1+'Drivers & Assumptions'!C28)^1,0),0) -> 6 | Q23: =IF(MOD(16,'Drivers & Assumptions'!C26)=0,ROUND('Drivers & Assumptions'!C27*(1+'Drivers & Assumptions'!C28)^1,0),0) -> 0 | R23: =IF(MOD(17,'Drivers & Assumptions'!C26)=0,ROUND('Drivers & Assumptions'!C27*(1+'Drivers & Assumptions'!C28)^1,0),0) -> 0 | S23: =IF(MOD(18,'Drivers & Assumptions'!C26)=0,ROUND('Drivers & Assumptions'!C27*(1+'Drivers & Assumptions'!C28)^1,0),0) -> 6 | T23: =IF(MOD(19,'Drivers & Assumptions'!C26)=0,ROUND('Drivers & Assumptions'!C27*(1+'Drivers & Assumptions'!C28)^1,0),0) -> 0 | U23: =IF(MOD(20,'Drivers & Assumptions'!C26)=0,ROUND('Drivers & Assumptions'!C27*(1+'Drivers & Assumptions'!C28)^1,0),0) -> 0 | V23: =IF(MOD(21,'Drivers & Assumptions'!C26)=0,ROUND('Drivers & Assumptions'!C27*(1+'Drivers & Assumptions'!C28)^1,0),0) -> 6 | W23: =IF(MOD(22,'Drivers & Assumptions'!C26)=0,ROUND('Drivers & Assumptions'!C27*(1+'Drivers & Assumptions'!C28)^1,0),0) -> 0 | X23: =IF(MOD(23,'Drivers & Assumptions'!C26)=0,ROUND('Drivers & Assumptions'!C27*(1+'Drivers & Assumptions'!C28)^1,0),0) -> 0 | Y23: =IF(MOD(24,'Drivers & Assumptions'!C26)=0,ROUND('Drivers & Assumptions'!C27*(1+'Drivers & Assumptions'!C28)^1,0),0) -> 6 | Z23: =IF(MOD(25,'Drivers & Assumptions'!C26)=0,ROUND('Drivers & Assumptions'!C27*(1+'Drivers & Assumptions'!C28)^2,0),0) -> 0 | AA23: =IF(MOD(26,'Drivers & Assumptions'!C26)=0,ROUND('Drivers & Assumptions'!C27*(1+'Drivers & Assumptions'!C28)^2,0),0) -> 0 | AB23: =IF(MOD(27,'Drivers & Assumptions'!C26)=0,ROUND('Drivers & Assumptions'!C27*(1+'Drivers & Assumptions'!C28)^2,0),0) -> 8 | AC23: =IF(MOD(28,'Drivers & Assumptions'!C26)=0,ROUND('Drivers & Assumptions'!C27*(1+'Drivers & Assumptions'!C28)^2,0),0) -> 0 | AD23: =IF(MOD(29,'Drivers & Assumptions'!C26)=0,ROUND('Drivers & Assumptions'!C27*(1+'Drivers & Assumptions'!C28)^2,0),0) -> 0 | AE23: =IF(MOD(30,'Drivers & Assumptions'!C26)=0,ROUND('Drivers & Assumptions'!C27*(1+'Drivers & Assumptions'!C28)^2,0),0) -> 8 | AF23: =IF(MOD(31,'Drivers & Assumptions'!C26)=0,ROUND('Drivers & Assumptions'!C27*(1+'Drivers & Assumptions'!C28)^2,0),0) -> 0 | AG23: =IF(MOD(32,'Drivers & Assumptions'!C26)=0,ROUND('Drivers & Assumptions'!C27*(1+'Drivers & Assumptions'!C28)^2,0),0) -> 0 | AH23: =IF(MOD(33,'Drivers & Assumptions'!C26)=0,ROUND('Drivers & Assumptions'!C27*(1+'Drivers & Assumptions'!C28)^2,0),0) -> 8 | AI23: =IF(MOD(34,'Drivers & Assumptions'!C26)=0,ROUND('Drivers & Assumptions'!C27*(1+'Drivers & Assumptions'!C28)^2,0),0) -> 0 | AJ23: =IF(MOD(35,'Drivers & Assumptions'!C26)=0,ROUND('Drivers & Assumptions'!C27*(1+'Drivers & Assumptions'!C28)^2,0),0) -> 0 | AK23: =IF(MOD(36,'Drivers & Assumptions'!C26)=0,ROUND('Drivers & Assumptions'!C27*(1+'Drivers & Assumptions'!C28)^2,0),0) -> 8 | AL23: =IF(MOD(37,'Drivers & Assumptions'!C26)=0,ROUND('Drivers & Assumptions'!C27*(1+'Drivers & Assumptions'!C28)^3,0),0) -> 0 | AM23: =IF(MOD(38,'Drivers & Assumptions'!C26)=0,ROUND('Drivers & Assumptions'!C27*(1+'Drivers & Assumptions'!C28)^3,0),0) -> 0 | AN23: =IF(MOD(39,'Drivers & Assumptions'!C26)=0,ROUND('Drivers & Assumptions'!C27*(1+'Drivers & Assumptions'!C28)^3,0),0) -> 10 | AO23: =IF(MOD(40,'Drivers & Assumptions'!C26)=0,ROUND('Drivers & Assumptions'!C27*(1+'Drivers & Assumptions'!C28)^3,0),0) -> 0 | AP23: =IF(MOD(41,'Drivers & Assumptions'!C26)=0,ROUND('Drivers & Assumptions'!C27*(1+'Drivers & Assumptions'!C28)^3,0),0) -> 0 | AQ23: =IF(MOD(42,'Drivers & Assumptions'!C26)=0,ROUND('Drivers & Assumptions'!C27*(1+'Drivers & Assumptions'!C28)^3,0),0) -> 10 | AR23: =IF(MOD(43,'Drivers & Assumptions'!C26)=0,ROUND('Drivers & Assumptions'!C27*(1+'Drivers & Assumptions'!C28)^3,0),0) -> 0 | AS23: =IF(MOD(44,'Drivers & Assumptions'!C26)=0,ROUND('Drivers & Assumptions'!C27*(1+'Drivers & Assumptions'!C28)^3,0),0) -> 0 | AT23: =IF(MOD(45,'Drivers & Assumptions'!C26)=0,ROUND('Drivers & Assumptions'!C27*(1+'Drivers & Assumptions'!C28)^3,0),0) -> 10 | AU23: =IF(MOD(46,'Drivers & Assumptions'!C26)=0,ROUND('Drivers & Assumptions'!C27*(1+'Drivers & Assumptions'!C28)^3,0),0) -> 0 | AV23: =IF(MOD(47,'Drivers & Assumptions'!C26)=0,ROUND('Drivers & Assumptions'!C27*(1+'Drivers & Assumptions'!C28)^3,0),0) -> 0 | AW23: =IF(MOD(48,'Drivers & Assumptions'!C26)=0,ROUND('Drivers & Assumptions'!C27*(1+'Drivers & Assumptions'!C28)^3,0),0) -> 10 | AX23: =IF(MOD(49,'Drivers & Assumptions'!C26)=0,ROUND('Drivers & Assumptions'!C27*(1+'Drivers & Assumptions'!C28)^4,0),0) -> 0 | AY23: =IF(MOD(50,'Drivers & Assumptions'!C26)=0,ROUND('Drivers & Assumptions'!C27*(1+'Drivers & Assumptions'!C28)^4,0),0) -> 0 | AZ23: =IF(MOD(51,'Drivers & Assumptions'!C26)=0,ROUND('Drivers & Assumptions'!C27*(1+'Drivers & Assumptions'!C28)^4,0),0) -> 12 | BA23: =IF(MOD(52,'Drivers & Assumptions'!C26)=0,ROUND('Drivers & Assumptions'!C27*(1+'Drivers & Assumptions'!C28)^4,0),0) -> 0 | BB23: =IF(MOD(53,'Drivers & Assumptions'!C26)=0,ROUND('Drivers & Assumptions'!C27*(1+'Drivers & Assumptions'!C28)^4,0),0) -> 0 | BC23: =IF(MOD(54,'Drivers & Assumptions'!C26)=0,ROUND('Drivers & Assumptions'!C27*(1+'Drivers & Assumptions'!C28)^4,0),0) -> 12 | BD23: =IF(MOD(55,'Drivers & Assumptions'!C26)=0,ROUND('Drivers & Assumptions'!C27*(1+'Drivers & Assumptions'!C28)^4,0),0) -> 0 | BE23: =IF(MOD(56,'Drivers & Assumptions'!C26)=0,ROUND('Drivers & Assumptions'!C27*(1+'Drivers & Assumptions'!C28)^4,0),0) -> 0 | BF23: =IF(MOD(57,'Drivers & Assumptions'!C26)=0,ROUND('Drivers & Assumptions'!C27*(1+'Drivers & Assumptions'!C28)^4,0),0) -> 12 | BG23: =IF(MOD(58,'Drivers & Assumptions'!C26)=0,ROUND('Drivers & Assumptions'!C27*(1+'Drivers & Assumptions'!C28)^4,0),0) -> 0 | BH23: =IF(MOD(59,'Drivers & Assumptions'!C26)=0,ROUND('Drivers & Assumptions'!C27*(1+'Drivers & Assumptions'!C28)^4,0),0) -> 0 | BI23: =IF(MOD(60,'Drivers & Assumptions'!C26)=0,ROUND('Drivers & Assumptions'!C27*(1+'Drivers & Assumptions'!C28)^4,0),0) -> 12
A24: Country 18 — Cases Ordered | B24: 0 | C24: 0 | D24: 0 | E24: 0 | F24: 0 | G24: 0 | H24: 0 | I24: 0 | J24: =IF(MOD(9,'Drivers & Assumptions'!C26)=0,ROUND('Drivers & Assumptions'!C27*(1+'Drivers & Assumptions'!C28)^0,0),0) -> 5 | K24: =IF(MOD(10,'Drivers & Assumptions'!C26)=0,ROUND('Drivers & Assumptions'!C27*(1+'Drivers & Assumptions'!C28)^0,0),0) -> 0 | L24: =IF(MOD(11,'Drivers & Assumptions'!C26)=0,ROUND('Drivers & Assumptions'!C27*(1+'Drivers & Assumptions'!C28)^0,0),0) -> 0 | M24: =IF(MOD(12,'Drivers & Assumptions'!C26)=0,ROUND('Drivers & Assumptions'!C27*(1+'Drivers & Assumptions'!C28)^0,0),0) -> 5 | N24: =IF(MOD(13,'Drivers & Assumptions'!C26)=0,ROUND('Drivers & Assumptions'!C27*(1+'Drivers & Assumptions'!C28)^1,0),0) -> 0 | O24: =IF(MOD(14,'Drivers & Assumptions'!C26)=0,ROUND('Drivers & Assumptions'!C27*(1+'Drivers & Assumptions'!C28)^1,0),0) -> 0 | P24: =IF(MOD(15,'Drivers & Assumptions'!C26)=0,ROUND('Drivers & Assumptions'!C27*(1+'Drivers & Assumptions'!C28)^1,0),0) -> 6 | Q24: =IF(MOD(16,'Drivers & Assumptions'!C26)=0,ROUND('Drivers & Assumptions'!C27*(1+'Drivers & Assumptions'!C28)^1,0),0) -> 0 | R24: =IF(MOD(17,'Drivers & Assumptions'!C26)=0,ROUND('Drivers & Assumptions'!C27*(1+'Drivers & Assumptions'!C28)^1,0),0) -> 0 | S24: =IF(MOD(18,'Drivers & Assumptions'!C26)=0,ROUND('Drivers & Assumptions'!C27*(1+'Drivers & Assumptions'!C28)^1,0),0) -> 6 | T24: =IF(MOD(19,'Drivers & Assumptions'!C26)=0,ROUND('Drivers & Assumptions'!C27*(1+'Drivers & Assumptions'!C28)^1,0),0) -> 0 | U24: =IF(MOD(20,'Drivers & Assumptions'!C26)=0,ROUND('Drivers & Assumptions'!C27*(1+'Drivers & Assumptions'!C28)^1,0),0) -> 0 | V24: =IF(MOD(21,'Drivers & Assumptions'!C26)=0,ROUND('Drivers & Assumptions'!C27*(1+'Drivers & Assumptions'!C28)^1,0),0) -> 6 | W24: =IF(MOD(22,'Drivers & Assumptions'!C26)=0,ROUND('Drivers & Assumptions'!C27*(1+'Drivers & Assumptions'!C28)^1,0),0) -> 0 | X24: =IF(MOD(23,'Drivers & Assumptions'!C26)=0,ROUND('Drivers & Assumptions'!C27*(1+'Drivers & Assumptions'!C28)^1,0),0) -> 0 | Y24: =IF(MOD(24,'Drivers & Assumptions'!C26)=0,ROUND('Drivers & Assumptions'!C27*(1+'Drivers & Assumptions'!C28)^1,0),0) -> 6 | Z24: =IF(MOD(25,'Drivers & Assumptions'!C26)=0,ROUND('Drivers & Assumptions'!C27*(1+'Drivers & Assumptions'!C28)^2,0),0) -> 0 | AA24: =IF(MOD(26,'Drivers & Assumptions'!C26)=0,ROUND('Drivers & Assumptions'!C27*(1+'Drivers & Assumptions'!C28)^2,0),0) -> 0 | AB24: =IF(MOD(27,'Drivers & Assumptions'!C26)=0,ROUND('Drivers & Assumptions'!C27*(1+'Drivers & Assumptions'!C28)^2,0),0) -> 8 | AC24: =IF(MOD(28,'Drivers & Assumptions'!C26)=0,ROUND('Drivers & Assumptions'!C27*(1+'Drivers & Assumptions'!C28)^2,0),0) -> 0 | AD24: =IF(MOD(29,'Drivers & Assumptions'!C26)=0,ROUND('Drivers & Assumptions'!C27*(1+'Drivers & Assumptions'!C28)^2,0),0) -> 0 | AE24: =IF(MOD(30,'Drivers & Assumptions'!C26)=0,ROUND('Drivers & Assumptions'!C27*(1+'Drivers & Assumptions'!C28)^2,0),0) -> 8 | AF24: =IF(MOD(31,'Drivers & Assumptions'!C26)=0,ROUND('Drivers & Assumptions'!C27*(1+'Drivers & Assumptions'!C28)^2,0),0) -> 0 | AG24: =IF(MOD(32,'Drivers & Assumptions'!C26)=0,ROUND('Drivers & Assumptions'!C27*(1+'Drivers & Assumptions'!C28)^2,0),0) -> 0 | AH24: =IF(MOD(33,'Drivers & Assumptions'!C26)=0,ROUND('Drivers & Assumptions'!C27*(1+'Drivers & Assumptions'!C28)^2,0),0) -> 8 | AI24: =IF(MOD(34,'Drivers & Assumptions'!C26)=0,ROUND('Drivers & Assumptions'!C27*(1+'Drivers & Assumptions'!C28)^2,0),0) -> 0 | AJ24: =IF(MOD(35,'Drivers & Assumptions'!C26)=0,ROUND('Drivers & Assumptions'!C27*(1+'Drivers & Assumptions'!C28)^2,0),0) -> 0 | AK24: =IF(MOD(36,'Drivers & Assumptions'!C26)=0,ROUND('Drivers & Assumptions'!C27*(1+'Drivers & Assumptions'!C28)^2,0),0) -> 8 | AL24: =IF(MOD(37,'Drivers & Assumptions'!C26)=0,ROUND('Drivers & Assumptions'!C27*(1+'Drivers & Assumptions'!C28)^3,0),0) -> 0 | AM24: =IF(MOD(38,'Drivers & Assumptions'!C26)=0,ROUND('Drivers & Assumptions'!C27*(1+'Drivers & Assumptions'!C28)^3,0),0) -> 0 | AN24: =IF(MOD(39,'Drivers & Assumptions'!C26)=0,ROUND('Drivers & Assumptions'!C27*(1+'Drivers & Assumptions'!C28)^3,0),0) -> 10 | AO24: =IF(MOD(40,'Drivers & Assumptions'!C26)=0,ROUND('Drivers & Assumptions'!C27*(1+'Drivers & Assumptions'!C28)^3,0),0) -> 0 | AP24: =IF(MOD(41,'Drivers & Assumptions'!C26)=0,ROUND('Drivers & Assumptions'!C27*(1+'Drivers & Assumptions'!C28)^3,0),0) -> 0 | AQ24: =IF(MOD(42,'Drivers & Assumptions'!C26)=0,ROUND('Drivers & Assumptions'!C27*(1+'Drivers & Assumptions'!C28)^3,0),0) -> 10 | AR24: =IF(MOD(43,'Drivers & Assumptions'!C26)=0,ROUND('Drivers & Assumptions'!C27*(1+'Drivers & Assumptions'!C28)^3,0),0) -> 0 | AS24: =IF(MOD(44,'Drivers & Assumptions'!C26)=0,ROUND('Drivers & Assumptions'!C27*(1+'Drivers & Assumptions'!C28)^3,0),0) -> 0 | AT24: =IF(MOD(45,'Drivers & Assumptions'!C26)=0,ROUND('Drivers & Assumptions'!C27*(1+'Drivers & Assumptions'!C28)^3,0),0) -> 10 | AU24: =IF(MOD(46,'Drivers & Assumptions'!C26)=0,ROUND('Drivers & Assumptions'!C27*(1+'Drivers & Assumptions'!C28)^3,0),0) -> 0 | AV24: =IF(MOD(47,'Drivers & Assumptions'!C26)=0,ROUND('Drivers & Assumptions'!C27*(1+'Drivers & Assumptions'!C28)^3,0),0) -> 0 | AW24: =IF(MOD(48,'Drivers & Assumptions'!C26)=0,ROUND('Drivers & Assumptions'!C27*(1+'Drivers & Assumptions'!C28)^3,0),0) -> 10 | AX24: =IF(MOD(49,'Drivers & Assumptions'!C26)=0,ROUND('Drivers & Assumptions'!C27*(1+'Drivers & Assumptions'!C28)^4,0),0) -> 0 | AY24: =IF(MOD(50,'Drivers & Assumptions'!C26)=0,ROUND('Drivers & Assumptions'!C27*(1+'Drivers & Assumptions'!C28)^4,0),0) -> 0 | AZ24: =IF(MOD(51,'Drivers & Assumptions'!C26)=0,ROUND('Drivers & Assumptions'!C27*(1+'Drivers & Assumptions'!C28)^4,0),0) -> 12 | BA24: =IF(MOD(52,'Drivers & Assumptions'!C26)=0,ROUND('Drivers & Assumptions'!C27*(1+'Drivers & Assumptions'!C28)^4,0),0) -> 0 | BB24: =IF(MOD(53,'Drivers & Assumptions'!C26)=0,ROUND('Drivers & Assumptions'!C27*(1+'Drivers & Assumptions'!C28)^4,0),0) -> 0 | BC24: =IF(MOD(54,'Drivers & Assumptions'!C26)=0,ROUND('Drivers & Assumptions'!C27*(1+'Drivers & Assumptions'!C28)^4,0),0) -> 12 | BD24: =IF(MOD(55,'Drivers & Assumptions'!C26)=0,ROUND('Drivers & Assumptions'!C27*(1+'Drivers & Assumptions'!C28)^4,0),0) -> 0 | BE24: =IF(MOD(56,'Drivers & Assumptions'!C26)=0,ROUND('Drivers & Assumptions'!C27*(1+'Drivers & Assumptions'!C28)^4,0),0) -> 0 | BF24: =IF(MOD(57,'Drivers & Assumptions'!C26)=0,ROUND('Drivers & Assumptions'!C27*(1+'Drivers & Assumptions'!C28)^4,0),0) -> 12 | BG24: =IF(MOD(58,'Drivers & Assumptions'!C26)=0,ROUND('Drivers & Assumptions'!C27*(1+'Drivers & Assumptions'!C28)^4,0),0) -> 0 | BH24: =IF(MOD(59,'Drivers & Assumptions'!C26)=0,ROUND('Drivers & Assumptions'!C27*(1+'Drivers & Assumptions'!C28)^4,0),0) -> 0 | BI24: =IF(MOD(60,'Drivers & Assumptions'!C26)=0,ROUND('Drivers & Assumptions'!C27*(1+'Drivers & Assumptions'!C28)^4,0),0) -> 12
A25: Country 19 — Cases Ordered | B25: 0 | C25: 0 | D25: 0 | E25: 0 | F25: 0 | G25: 0 | H25: 0 | I25: 0 | J25: =IF(MOD(9,'Drivers & Assumptions'!C26)=0,ROUND('Drivers & Assumptions'!C27*(1+'Drivers & Assumptions'!C28)^0,0),0) -> 5 | K25: =IF(MOD(10,'Drivers & Assumptions'!C26)=0,ROUND('Drivers & Assumptions'!C27*(1+'Drivers & Assumptions'!C28)^0,0),0) -> 0 | L25: =IF(MOD(11,'Drivers & Assumptions'!C26)=0,ROUND('Drivers & Assumptions'!C27*(1+'Drivers & Assumptions'!C28)^0,0),0) -> 0 | M25: =IF(MOD(12,'Drivers & Assumptions'!C26)=0,ROUND('Drivers & Assumptions'!C27*(1+'Drivers & Assumptions'!C28)^0,0),0) -> 5 | N25: =IF(MOD(13,'Drivers & Assumptions'!C26)=0,ROUND('Drivers & Assumptions'!C27*(1+'Drivers & Assumptions'!C28)^1,0),0) -> 0 | O25: =IF(MOD(14,'Drivers & Assumptions'!C26)=0,ROUND('Drivers & Assumptions'!C27*(1+'Drivers & Assumptions'!C28)^1,0),0) -> 0 | P25: =IF(MOD(15,'Drivers & Assumptions'!C26)=0,ROUND('Drivers & Assumptions'!C27*(1+'Drivers & Assumptions'!C28)^1,0),0) -> 6 | Q25: =IF(MOD(16,'Drivers & Assumptions'!C26)=0,ROUND('Drivers & Assumptions'!C27*(1+'Drivers & Assumptions'!C28)^1,0),0) -> 0 | R25: =IF(MOD(17,'Drivers & Assumptions'!C26)=0,ROUND('Drivers & Assumptions'!C27*(1+'Drivers & Assumptions'!C28)^1,0),0) -> 0 | S25: =IF(MOD(18,'Drivers & Assumptions'!C26)=0,ROUND('Drivers & Assumptions'!C27*(1+'Drivers & Assumptions'!C28)^1,0),0) -> 6 | T25: =IF(MOD(19,'Drivers & Assumptions'!C26)=0,ROUND('Drivers & Assumptions'!C27*(1+'Drivers & Assumptions'!C28)^1,0),0) -> 0 | U25: =IF(MOD(20,'Drivers & Assumptions'!C26)=0,ROUND('Drivers & Assumptions'!C27*(1+'Drivers & Assumptions'!C28)^1,0),0) -> 0 | V25: =IF(MOD(21,'Drivers & Assumptions'!C26)=0,ROUND('Drivers & Assumptions'!C27*(1+'Drivers & Assumptions'!C28)^1,0),0) -> 6 | W25: =IF(MOD(22,'Drivers & Assumptions'!C26)=0,ROUND('Drivers & Assumptions'!C27*(1+'Drivers & Assumptions'!C28)^1,0),0) -> 0 | X25: =IF(MOD(23,'Drivers & Assumptions'!C26)=0,ROUND('Drivers & Assumptions'!C27*(1+'Drivers & Assumptions'!C28)^1,0),0) -> 0 | Y25: =IF(MOD(24,'Drivers & Assumptions'!C26)=0,ROUND('Drivers & Assumptions'!C27*(1+'Drivers & Assumptions'!C28)^1,0),0) -> 6 | Z25: =IF(MOD(25,'Drivers & Assumptions'!C26)=0,ROUND('Drivers & Assumptions'!C27*(1+'Drivers & Assumptions'!C28)^2,0),0) -> 0 | AA25: =IF(MOD(26,'Drivers & Assumptions'!C26)=0,ROUND('Drivers & Assumptions'!C27*(1+'Drivers & Assumptions'!C28)^2,0),0) -> 0 | AB25: =IF(MOD(27,'Drivers & Assumptions'!C26)=0,ROUND('Drivers & Assumptions'!C27*(1+'Drivers & Assumptions'!C28)^2,0),0) -> 8 | AC25: =IF(MOD(28,'Drivers & Assumptions'!C26)=0,ROUND('Drivers & Assumptions'!C27*(1+'Drivers & Assumptions'!C28)^2,0),0) -> 0 | AD25: =IF(MOD(29,'Drivers & Assumptions'!C26)=0,ROUND('Drivers & Assumptions'!C27*(1+'Drivers & Assumptions'!C28)^2,0),0) -> 0 | AE25: =IF(MOD(30,'Drivers & Assumptions'!C26)=0,ROUND('Drivers & Assumptions'!C27*(1+'Drivers & Assumptions'!C28)^2,0),0) -> 8 | AF25: =IF(MOD(31,'Drivers & Assumptions'!C26)=0,ROUND('Drivers & Assumptions'!C27*(1+'Drivers & Assumptions'!C28)^2,0),0) -> 0 | AG25: =IF(MOD(32,'Drivers & Assumptions'!C26)=0,ROUND('Drivers & Assumptions'!C27*(1+'Drivers & Assumptions'!C28)^2,0),0) -> 0 | AH25: =IF(MOD(33,'Drivers & Assumptions'!C26)=0,ROUND('Drivers & Assumptions'!C27*(1+'Drivers & Assumptions'!C28)^2,0),0) -> 8 | AI25: =IF(MOD(34,'Drivers & Assumptions'!C26)=0,ROUND('Drivers & Assumptions'!C27*(1+'Drivers & Assumptions'!C28)^2,0),0) -> 0 | AJ25: =IF(MOD(35,'Drivers & Assumptions'!C26)=0,ROUND('Drivers & Assumptions'!C27*(1+'Drivers & Assumptions'!C28)^2,0),0) -> 0 | AK25: =IF(MOD(36,'Drivers & Assumptions'!C26)=0,ROUND('Drivers & Assumptions'!C27*(1+'Drivers & Assumptions'!C28)^2,0),0) -> 8 | AL25: =IF(MOD(37,'Drivers & Assumptions'!C26)=0,ROUND('Drivers & Assumptions'!C27*(1+'Drivers & Assumptions'!C28)^3,0),0) -> 0 | AM25: =IF(MOD(38,'Drivers & Assumptions'!C26)=0,ROUND('Drivers & Assumptions'!C27*(1+'Drivers & Assumptions'!C28)^3,0),0) -> 0 | AN25: =IF(MOD(39,'Drivers & Assumptions'!C26)=0,ROUND('Drivers & Assumptions'!C27*(1+'Drivers & Assumptions'!C28)^3,0),0) -> 10 | AO25: =IF(MOD(40,'Drivers & Assumptions'!C26)=0,ROUND('Drivers & Assumptions'!C27*(1+'Drivers & Assumptions'!C28)^3,0),0) -> 0 | AP25: =IF(MOD(41,'Drivers & Assumptions'!C26)=0,ROUND('Drivers & Assumptions'!C27*(1+'Drivers & Assumptions'!C28)^3,0),0) -> 0 | AQ25: =IF(MOD(42,'Drivers & Assumptions'!C26)=0,ROUND('Drivers & Assumptions'!C27*(1+'Drivers & Assumptions'!C28)^3,0),0) -> 10 | AR25: =IF(MOD(43,'Drivers & Assumptions'!C26)=0,ROUND('Drivers & Assumptions'!C27*(1+'Drivers & Assumptions'!C28)^3,0),0) -> 0 | AS25: =IF(MOD(44,'Drivers & Assumptions'!C26)=0,ROUND('Drivers & Assumptions'!C27*(1+'Drivers & Assumptions'!C28)^3,0),0) -> 0 | AT25: =IF(MOD(45,'Drivers & Assumptions'!C26)=0,ROUND('Drivers & Assumptions'!C27*(1+'Drivers & Assumptions'!C28)^3,0),0) -> 10 | AU25: =IF(MOD(46,'Drivers & Assumptions'!C26)=0,ROUND('Drivers & Assumptions'!C27*(1+'Drivers & Assumptions'!C28)^3,0),0) -> 0 | AV25: =IF(MOD(47,'Drivers & Assumptions'!C26)=0,ROUND('Drivers & Assumptions'!C27*(1+'Drivers & Assumptions'!C28)^3,0),0) -> 0 | AW25: =IF(MOD(48,'Drivers & Assumptions'!C26)=0,ROUND('Drivers & Assumptions'!C27*(1+'Drivers & Assumptions'!C28)^3,0),0) -> 10 | AX25: =IF(MOD(49,'Drivers & Assumptions'!C26)=0,ROUND('Drivers & Assumptions'!C27*(1+'Drivers & Assumptions'!C28)^4,0),0) -> 0 | AY25: =IF(MOD(50,'Drivers & Assumptions'!C26)=0,ROUND('Drivers & Assumptions'!C27*(1+'Drivers & Assumptions'!C28)^4,0),0) -> 0 | AZ25: =IF(MOD(51,'Drivers & Assumptions'!C26)=0,ROUND('Drivers & Assumptions'!C27*(1+'Drivers & Assumptions'!C28)^4,0),0) -> 12 | BA25: =IF(MOD(52,'Drivers & Assumptions'!C26)=0,ROUND('Drivers & Assumptions'!C27*(1+'Drivers & Assumptions'!C28)^4,0),0) -> 0 | BB25: =IF(MOD(53,'Drivers & Assumptions'!C26)=0,ROUND('Drivers & Assumptions'!C27*(1+'Drivers & Assumptions'!C28)^4,0),0) -> 0 | BC25: =IF(MOD(54,'Drivers & Assumptions'!C26)=0,ROUND('Drivers & Assumptions'!C27*(1+'Drivers & Assumptions'!C28)^4,0),0) -> 12 | BD25: =IF(MOD(55,'Drivers & Assumptions'!C26)=0,ROUND('Drivers & Assumptions'!C27*(1+'Drivers & Assumptions'!C28)^4,0),0) -> 0 | BE25: =IF(MOD(56,'Drivers & Assumptions'!C26)=0,ROUND('Drivers & Assumptions'!C27*(1+'Drivers & Assumptions'!C28)^4,0),0) -> 0 | BF25: =IF(MOD(57,'Drivers & Assumptions'!C26)=0,ROUND('Drivers & Assumptions'!C27*(1+'Drivers & Assumptions'!C28)^4,0),0) -> 12 | BG25: =IF(MOD(58,'Drivers & Assumptions'!C26)=0,ROUND('Drivers & Assumptions'!C27*(1+'Drivers & Assumptions'!C28)^4,0),0) -> 0 | BH25: =IF(MOD(59,'Drivers & Assumptions'!C26)=0,ROUND('Drivers & Assumptions'!C27*(1+'Drivers & Assumptions'!C28)^4,0),0) -> 0 | BI25: =IF(MOD(60,'Drivers & Assumptions'!C26)=0,ROUND('Drivers & Assumptions'!C27*(1+'Drivers & Assumptions'!C28)^4,0),0) -> 12
A26: Country 20 — Cases Ordered | B26: 0 | C26: 0 | D26: 0 | E26: 0 | F26: 0 | G26: 0 | H26: 0 | I26: 0 | J26: =IF(MOD(9,'Drivers & Assumptions'!C26)=0,ROUND('Drivers & Assumptions'!C27*(1+'Drivers & Assumptions'!C28)^0,0),0) -> 5 | K26: =IF(MOD(10,'Drivers & Assumptions'!C26)=0,ROUND('Drivers & Assumptions'!C27*(1+'Drivers & Assumptions'!C28)^0,0),0) -> 0 | L26: =IF(MOD(11,'Drivers & Assumptions'!C26)=0,ROUND('Drivers & Assumptions'!C27*(1+'Drivers & Assumptions'!C28)^0,0),0) -> 0 | M26: =IF(MOD(12,'Drivers & Assumptions'!C26)=0,ROUND('Drivers & Assumptions'!C27*(1+'Drivers & Assumptions'!C28)^0,0),0) -> 5 | N26: =IF(MOD(13,'Drivers & Assumptions'!C26)=0,ROUND('Drivers & Assumptions'!C27*(1+'Drivers & Assumptions'!C28)^1,0),0) -> 0 | O26: =IF(MOD(14,'Drivers & Assumptions'!C26)=0,ROUND('Drivers & Assumptions'!C27*(1+'Drivers & Assumptions'!C28)^1,0),0) -> 0 | P26: =IF(MOD(15,'Drivers & Assumptions'!C26)=0,ROUND('Drivers & Assumptions'!C27*(1+'Drivers & Assumptions'!C28)^1,0),0) -> 6 | Q26: =IF(MOD(16,'Drivers & Assumptions'!C26)=0,ROUND('Drivers & Assumptions'!C27*(1+'Drivers & Assumptions'!C28)^1,0),0) -> 0 | R26: =IF(MOD(17,'Drivers & Assumptions'!C26)=0,ROUND('Drivers & Assumptions'!C27*(1+'Drivers & Assumptions'!C28)^1,0),0) -> 0 | S26: =IF(MOD(18,'Drivers & Assumptions'!C26)=0,ROUND('Drivers & Assumptions'!C27*(1+'Drivers & Assumptions'!C28)^1,0),0) -> 6 | T26: =IF(MOD(19,'Drivers & Assumptions'!C26)=0,ROUND('Drivers & Assumptions'!C27*(1+'Drivers & Assumptions'!C28)^1,0),0) -> 0 | U26: =IF(MOD(20,'Drivers & Assumptions'!C26)=0,ROUND('Drivers & Assumptions'!C27*(1+'Drivers & Assumptions'!C28)^1,0),0) -> 0 | V26: =IF(MOD(21,'Drivers & Assumptions'!C26)=0,ROUND('Drivers & Assumptions'!C27*(1+'Drivers & Assumptions'!C28)^1,0),0) -> 6 | W26: =IF(MOD(22,'Drivers & Assumptions'!C26)=0,ROUND('Drivers & Assumptions'!C27*(1+'Drivers & Assumptions'!C28)^1,0),0) -> 0 | X26: =IF(MOD(23,'Drivers & Assumptions'!C26)=0,ROUND('Drivers & Assumptions'!C27*(1+'Drivers & Assumptions'!C28)^1,0),0) -> 0 | Y26: =IF(MOD(24,'Drivers & Assumptions'!C26)=0,ROUND('Drivers & Assumptions'!C27*(1+'Drivers & Assumptions'!C28)^1,0),0) -> 6 | Z26: =IF(MOD(25,'Drivers & Assumptions'!C26)=0,ROUND('Drivers & Assumptions'!C27*(1+'Drivers & Assumptions'!C28)^2,0),0) -> 0 | AA26: =IF(MOD(26,'Drivers & Assumptions'!C26)=0,ROUND('Drivers & Assumptions'!C27*(1+'Drivers & Assumptions'!C28)^2,0),0) -> 0 | AB26: =IF(MOD(27,'Drivers & Assumptions'!C26)=0,ROUND('Drivers & Assumptions'!C27*(1+'Drivers & Assumptions'!C28)^2,0),0) -> 8 | AC26: =IF(MOD(28,'Drivers & Assumptions'!C26)=0,ROUND('Drivers & Assumptions'!C27*(1+'Drivers & Assumptions'!C28)^2,0),0) -> 0 | AD26: =IF(MOD(29,'Drivers & Assumptions'!C26)=0,ROUND('Drivers & Assumptions'!C27*(1+'Drivers & Assumptions'!C28)^2,0),0) -> 0 | AE26: =IF(MOD(30,'Drivers & Assumptions'!C26)=0,ROUND('Drivers & Assumptions'!C27*(1+'Drivers & Assumptions'!C28)^2,0),0) -> 8 | AF26: =IF(MOD(31,'Drivers & Assumptions'!C26)=0,ROUND('Drivers & Assumptions'!C27*(1+'Drivers & Assumptions'!C28)^2,0),0) -> 0 | AG26: =IF(MOD(32,'Drivers & Assumptions'!C26)=0,ROUND('Drivers & Assumptions'!C27*(1+'Drivers & Assumptions'!C28)^2,0),0) -> 0 | AH26: =IF(MOD(33,'Drivers & Assumptions'!C26)=0,ROUND('Drivers & Assumptions'!C27*(1+'Drivers & Assumptions'!C28)^2,0),0) -> 8 | AI26: =IF(MOD(34,'Drivers & Assumptions'!C26)=0,ROUND('Drivers & Assumptions'!C27*(1+'Drivers & Assumptions'!C28)^2,0),0) -> 0 | AJ26: =IF(MOD(35,'Drivers & Assumptions'!C26)=0,ROUND('Drivers & Assumptions'!C27*(1+'Drivers & Assumptions'!C28)^2,0),0) -> 0 | AK26: =IF(MOD(36,'Drivers & Assumptions'!C26)=0,ROUND('Drivers & Assumptions'!C27*(1+'Drivers & Assumptions'!C28)^2,0),0) -> 8 | AL26: =IF(MOD(37,'Drivers & Assumptions'!C26)=0,ROUND('Drivers & Assumptions'!C27*(1+'Drivers & Assumptions'!C28)^3,0),0) -> 0 | AM26: =IF(MOD(38,'Drivers & Assumptions'!C26)=0,ROUND('Drivers & Assumptions'!C27*(1+'Drivers & Assumptions'!C28)^3,0),0) -> 0 | AN26: =IF(MOD(39,'Drivers & Assumptions'!C26)=0,ROUND('Drivers & Assumptions'!C27*(1+'Drivers & Assumptions'!C28)^3,0),0) -> 10 | AO26: =IF(MOD(40,'Drivers & Assumptions'!C26)=0,ROUND('Drivers & Assumptions'!C27*(1+'Drivers & Assumptions'!C28)^3,0),0) -> 0 | AP26: =IF(MOD(41,'Drivers & Assumptions'!C26)=0,ROUND('Drivers & Assumptions'!C27*(1+'Drivers & Assumptions'!C28)^3,0),0) -> 0 | AQ26: =IF(MOD(42,'Drivers & Assumptions'!C26)=0,ROUND('Drivers & Assumptions'!C27*(1+'Drivers & Assumptions'!C28)^3,0),0) -> 10 | AR26: =IF(MOD(43,'Drivers & Assumptions'!C26)=0,ROUND('Drivers & Assumptions'!C27*(1+'Drivers & Assumptions'!C28)^3,0),0) -> 0 | AS26: =IF(MOD(44,'Drivers & Assumptions'!C26)=0,ROUND('Drivers & Assumptions'!C27*(1+'Drivers & Assumptions'!C28)^3,0),0) -> 0 | AT26: =IF(MOD(45,'Drivers & Assumptions'!C26)=0,ROUND('Drivers & Assumptions'!C27*(1+'Drivers & Assumptions'!C28)^3,0),0) -> 10 | AU26: =IF(MOD(46,'Drivers & Assumptions'!C26)=0,ROUND('Drivers & Assumptions'!C27*(1+'Drivers & Assumptions'!C28)^3,0),0) -> 0 | AV26: =IF(MOD(47,'Drivers & Assumptions'!C26)=0,ROUND('Drivers & Assumptions'!C27*(1+'Drivers & Assumptions'!C28)^3,0),0) -> 0 | AW26: =IF(MOD(48,'Drivers & Assumptions'!C26)=0,ROUND('Drivers & Assumptions'!C27*(1+'Drivers & Assumptions'!C28)^3,0),0) -> 10 | AX26: =IF(MOD(49,'Drivers & Assumptions'!C26)=0,ROUND('Drivers & Assumptions'!C27*(1+'Drivers & Assumptions'!C28)^4,0),0) -> 0 | AY26: =IF(MOD(50,'Drivers & Assumptions'!C26)=0,ROUND('Drivers & Assumptions'!C27*(1+'Drivers & Assumptions'!C28)^4,0),0) -> 0 | AZ26: =IF(MOD(51,'Drivers & Assumptions'!C26)=0,ROUND('Drivers & Assumptions'!C27*(1+'Drivers & Assumptions'!C28)^4,0),0) -> 12 | BA26: =IF(MOD(52,'Drivers & Assumptions'!C26)=0,ROUND('Drivers & Assumptions'!C27*(1+'Drivers & Assumptions'!C28)^4,0),0) -> 0 | BB26: =IF(MOD(53,'Drivers & Assumptions'!C26)=0,ROUND('Drivers & Assumptions'!C27*(1+'Drivers & Assumptions'!C28)^4,0),0) -> 0 | BC26: =IF(MOD(54,'Drivers & Assumptions'!C26)=0,ROUND('Drivers & Assumptions'!C27*(1+'Drivers & Assumptions'!C28)^4,0),0) -> 12 | BD26: =IF(MOD(55,'Drivers & Assumptions'!C26)=0,ROUND('Drivers & Assumptions'!C27*(1+'Drivers & Assumptions'!C28)^4,0),0) -> 0 | BE26: =IF(MOD(56,'Drivers & Assumptions'!C26)=0,ROUND('Drivers & Assumptions'!C27*(1+'Drivers & Assumptions'!C28)^4,0),0) -> 0 | BF26: =IF(MOD(57,'Drivers & Assumptions'!C26)=0,ROUND('Drivers & Assumptions'!C27*(1+'Drivers & Assumptions'!C28)^4,0),0) -> 12 | BG26: =IF(MOD(58,'Drivers & Assumptions'!C26)=0,ROUND('Drivers & Assumptions'!C27*(1+'Drivers & Assumptions'!C28)^4,0),0) -> 0 | BH26: =IF(MOD(59,'Drivers & Assumptions'!C26)=0,ROUND('Drivers & Assumptions'!C27*(1+'Drivers & Assumptions'!C28)^4,0),0) -> 0 | BI26: =IF(MOD(60,'Drivers & Assumptions'!C26)=0,ROUND('Drivers & Assumptions'!C27*(1+'Drivers & Assumptions'!C28)^4,0),0) -> 12
A28: Total Cases Ordered (all countries) | B28: =SUM(B7:B26) -> 0 | C28: =SUM(C7:C26) -> 0 | D28: =SUM(D7:D26) -> 0 | E28: =SUM(E7:E26) -> 0 | F28: =SUM(F7:F26) -> 0 | G28: =SUM(G7:G26) -> 0 | H28: =SUM(H7:H26) -> 0 | I28: =SUM(I7:I26) -> 0 | ... BI28: =SUM(BI7:BI26) -> 240
A29: Total Units (Cases × Units per Case) | B29: =B28*'Drivers & Assumptions'!C20 -> 0 | C29: =C28*'Drivers & Assumptions'!C20 -> 0 | D29: =D28*'Drivers & Assumptions'!C20 -> 0 | E29: =E28*'Drivers & Assumptions'!C20 -> 0 | F29: =F28*'Drivers & Assumptions'!C20 -> 0 | G29: =G28*'Drivers & Assumptions'!C20 -> 0 | H29: =H28*'Drivers & Assumptions'!C20 -> 0 | I29: =I28*'Drivers & Assumptions'!C20 -> 0 | J29: =J28*'Drivers & Assumptions'!C20 -> 1200 | K29: =K28*'Drivers & Assumptions'!C20 -> 0 | L29: =L28*'Drivers & Assumptions'!C20 -> 0 | M29: =M28*'Drivers & Assumptions'!C20 -> 1200 | N29: =N28*'Drivers & Assumptions'!C20 -> 0 | O29: =O28*'Drivers & Assumptions'!C20 -> 0 | P29: =P28*'Drivers & Assumptions'!C20 -> 1440 | Q29: =Q28*'Drivers & Assumptions'!C20 -> 0 | R29: =R28*'Drivers & Assumptions'!C20 -> 0 | S29: =S28*'Drivers & Assumptions'!C20 -> 1440 | T29: =T28*'Drivers & Assumptions'!C20 -> 0 | U29: =U28*'Drivers & Assumptions'!C20 -> 0 | V29: =V28*'Drivers & Assumptions'!C20 -> 1440 | W29: =W28*'Drivers & Assumptions'!C20 -> 0 | X29: =X28*'Drivers & Assumptions'!C20 -> 0 | Y29: =Y28*'Drivers & Assumptions'!C20 -> 1440 | Z29: =Z28*'Drivers & Assumptions'!C20 -> 0 | AA29: =AA28*'Drivers & Assumptions'!C20 -> 0 | AB29: =AB28*'Drivers & Assumptions'!C20 -> 1920 | AC29: =AC28*'Drivers & Assumptions'!C20 -> 0 | AD29: =AD28*'Drivers & Assumptions'!C20 -> 0 | AE29: =AE28*'Drivers & Assumptions'!C20 -> 1920 | AF29: =AF28*'Drivers & Assumptions'!C20 -> 0 | AG29: =AG28*'Drivers & Assumptions'!C20 -> 0 | AH29: =AH28*'Drivers & Assumptions'!C20 -> 1920 | AI29: =AI28*'Drivers & Assumptions'!C20 -> 0 | AJ29: =AJ28*'Drivers & Assumptions'!C20 -> 0 | AK29: =AK28*'Drivers & Assumptions'!C20 -> 1920 | AL29: =AL28*'Drivers & Assumptions'!C20 -> 0 | AM29: =AM28*'Drivers & Assumptions'!C20 -> 0 | AN29: =AN28*'Drivers & Assumptions'!C20 -> 2400 | AO29: =AO28*'Drivers & Assumptions'!C20 -> 0 | AP29: =AP28*'Drivers & Assumptions'!C20 -> 0 | AQ29: =AQ28*'Drivers & Assumptions'!C20 -> 2400 | AR29: =AR28*'Drivers & Assumptions'!C20 -> 0 | AS29: =AS28*'Drivers & Assumptions'!C20 -> 0 | AT29: =AT28*'Drivers & Assumptions'!C20 -> 2400 | AU29: =AU28*'Drivers & Assumptions'!C20 -> 0 | AV29: =AV28*'Drivers & Assumptions'!C20 -> 0 | AW29: =AW28*'Drivers & Assumptions'!C20 -> 2400 | AX29: =AX28*'Drivers & Assumptions'!C20 -> 0 | AY29: =AY28*'Drivers & Assumptions'!C20 -> 0 | AZ29: =AZ28*'Drivers & Assumptions'!C20 -> 2880 | BA29: =BA28*'Drivers & Assumptions'!C20 -> 0 | BB29: =BB28*'Drivers & Assumptions'!C20 -> 0 | BC29: =BC28*'Drivers & Assumptions'!C20 -> 2880 | BD29: =BD28*'Drivers & Assumptions'!C20 -> 0 | BE29: =BE28*'Drivers & Assumptions'!C20 -> 0 | BF29: =BF28*'Drivers & Assumptions'!C20 -> 2880 | BG29: =BG28*'Drivers & Assumptions'!C20 -> 0 | BH29: =BH28*'Drivers & Assumptions'!C20 -> 0 | BI29: =BI28*'Drivers & Assumptions'!C20 -> 2880
A31: WHOLESALE REVENUE
A32: Wholesale Revenue (Units × WS Price) | B32: =B29*'Drivers & Assumptions'!C19 -> 0 | C32: =C29*'Drivers & Assumptions'!C19 -> 0 | D32: =D29*'Drivers & Assumptions'!C19 -> 0 | E32: =E29*'Drivers & Assumptions'!C19 -> 0 | F32: =F29*'Drivers & Assumptions'!C19 -> 0 | G32: =G29*'Drivers & Assumptions'!C19 -> 0 | H32: =H29*'Drivers & Assumptions'!C19 -> 0 | I32: =I29*'Drivers & Assumptions'!C19 -> 0 | J32: =J29*'Drivers & Assumptions'!C19 -> 45360 | K32: =K29*'Drivers & Assumptions'!C19 -> 0 | L32: =L29*'Drivers & Assumptions'!C19 -> 0 | M32: =M29*'Drivers & Assumptions'!C19 -> 45360 | N32: =N29*'Drivers & Assumptions'!C19 -> 0 | O32: =O29*'Drivers & Assumptions'!C19 -> 0 | P32: =P29*'Drivers & Assumptions'!C19 -> 54432 | Q32: =Q29*'Drivers & Assumptions'!C19 -> 0 | R32: =R29*'Drivers & Assumptions'!C19 -> 0 | S32: =S29*'Drivers & Assumptions'!C19 -> 54432 | T32: =T29*'Drivers & Assumptions'!C19 -> 0 | U32: =U29*'Drivers & Assumptions'!C19 -> 0 | V32: =V29*'Drivers & Assumptions'!C19 -> 54432 | W32: =W29*'Drivers & Assumptions'!C19 -> 0 | X32: =X29*'Drivers & Assumptions'!C19 -> 0 | Y32: =Y29*'Drivers & Assumptions'!C19 -> 54432 | Z32: =Z29*'Drivers & Assumptions'!C19 -> 0 | AA32: =AA29*'Drivers & Assumptions'!C19 -> 0 | AB32: =AB29*'Drivers & Assumptions'!C19 -> 72576 | AC32: =AC29*'Drivers & Assumptions'!C19 -> 0 | AD32: =AD29*'Drivers & Assumptions'!C19 -> 0 | AE32: =AE29*'Drivers & Assumptions'!C19 -> 72576 | AF32: =AF29*'Drivers & Assumptions'!C19 -> 0 | AG32: =AG29*'Drivers & Assumptions'!C19 -> 0 | AH32: =AH29*'Drivers & Assumptions'!C19 -> 72576 | AI32: =AI29*'Drivers & Assumptions'!C19 -> 0 | AJ32: =AJ29*'Drivers & Assumptions'!C19 -> 0 | AK32: =AK29*'Drivers & Assumptions'!C19 -> 72576 | AL32: =AL29*'Drivers & Assumptions'!C19 -> 0 | AM32: =AM29*'Drivers & Assumptions'!C19 -> 0 | AN32: =AN29*'Drivers & Assumptions'!C19 -> 90720 | AO32: =AO29*'Drivers & Assumptions'!C19 -> 0 | AP32: =AP29*'Drivers & Assumptions'!C19 -> 0 | AQ32: =AQ29*'Drivers & Assumptions'!C19 -> 90720 | AR32: =AR29*'Drivers & Assumptions'!C19 -> 0 | AS32: =AS29*'Drivers & Assumptions'!C19 -> 0 | AT32: =AT29*'Drivers & Assumptions'!C19 -> 90720 | AU32: =AU29*'Drivers & Assumptions'!C19 -> 0 | AV32: =AV29*'Drivers & Assumptions'!C19 -> 0 | AW32: =AW29*'Drivers & Assumptions'!C19 -> 90720 | AX32: =AX29*'Drivers & Assumptions'!C19 -> 0 | AY32: =AY29*'Drivers & Assumptions'!C19 -> 0 | AZ32: =AZ29*'Drivers & Assumptions'!C19 -> 108864 | BA32: =BA29*'Drivers & Assumptions'!C19 -> 0 | BB32: =BB29*'Drivers & Assumptions'!C19 -> 0 | BC32: =BC29*'Drivers & Assumptions'!C19 -> 108864 | BD32: =BD29*'Drivers & Assumptions'!C19 -> 0 | BE32: =BE29*'Drivers & Assumptions'!C19 -> 0 | BF32: =BF29*'Drivers & Assumptions'!C19 -> 108864 | BG32: =BG29*'Drivers & Assumptions'!C19 -> 0 | BH32: =BH29*'Drivers & Assumptions'!C19 -> 0 | BI32: =BI29*'Drivers & Assumptions'!C19 -> 108864
A34: Wholesale Revenue — Actuals (AUD) | B34: 9834 | C34: 17446 | D34: 1741 | E34: 5071 | F34: 8989 | G34: 3713 | H34: 1799 | I34: 17894
A35: WHOLESALE REVENUE (Actuals then Model) | B35: =B34 -> 9834 | C35: =C34 -> 17446 | D35: =D34 -> 1741 | E35: =E34 -> 5071 | F35: =F34 -> 8989 | G35: =G34 -> 3713 | H35: =H34 -> 1799 | I35: =I34 -> 17894 | J35: =J32 -> 45360 | K35: =K32 -> 0 | L35: =L32 -> 0 | M35: =M32 -> 45360 | N35: =N32 -> 0 | O35: =O32 -> 0 | P35: =P32 -> 54432 | Q35: =Q32 -> 0 | ... BI35: =BI32 -> 108864
A36: Wholesale Total Cases (for COGS calc) | B36: =B28 -> 0 | C36: =C28 -> 0 | D36: =D28 -> 0 | E36: =E28 -> 0 | F36: =F28 -> 0 | G36: =G28 -> 0 | H36: =H28 -> 0 | I36: =I28 -> 0 | ... BI36: =BI28 -> 240

Sheet Retail Revenue
A1: PLASMAIDE — Retail Revenue Build
A2: Direct retail channel — launches at configurable month
B4: Jul-25 | C4: Aug-25 | D4: Sep-25 | E4: Oct-25 | F4: Nov-25 | G4: Dec-25 | H4: Jan-26 | I4: Feb-26 | J4: Mar-26 | K4: Apr-26 | L4: May-26 | M4: Jun-26 | N4: Jul-26 | O4: Aug-26 | P4: Sep-26 | Q4: Oct-26 | R4: Nov-26 | S4: Dec-26 | T4: Jan-27 | U4: Feb-27 | V4: Mar-27 | W4: Apr-27 | X4: May-27 | Y4: Jun-27 | Z4: Jul-27 | AA4: Aug-27 | AB4: Sep-27 | AC4: Oct-27 | AD4: Nov-27 | AE4: Dec-27 | AF4: Jan-28 | AG4: Feb-28 | AH4: Mar-28 | AI4: Apr-28 | AJ4: May-28 | AK4: Jun-28 | AL4: Jul-28 | AM4: Aug-28 | AN4: Sep-28 | AO4: Oct-28 | AP4: Nov-28 | AQ4: Dec-28 | AR4: Jan-29 | AS4: Feb-29 | AT4: Mar-29 | AU4: Apr-29 | AV4: May-29 | AW4: Jun-29 | AX4: Jul-29 | AY4: Aug-29 | AZ4: Sep-29 | BA4: Oct-29 | BB4: Nov-29 | BC4: Dec-29 | BD4: Jan-30 | BE4: Feb-30 | BF4: Mar-30 | BG4: Apr-30 | BH4: May-30 | BI4: Jun-30
A6: RETAIL ROLLOUT
A7: Month Number (1 = Jul-25) | B7: 1 | C7: 2 | D7: 3 | E7: 4 | F7: 5 | G7: 6 | H7: 7 | I7: 8 | J7: 9 | K7: 10 | L7: 11 | M7: 12 | N7: 13 | O7: 14 | P7: 15 | Q7: 16 | R7: 17 | S7: 18 | T7: 19 | U7: 20 | V7: 21 | W7: 22 | X7: 23 | Y7: 24 | Z7: 25 | AA7: 26 | AB7: 27 | AC7: 28 | AD7: 29 | AE7: 30 | AF7: 31 | AG7: 32 | AH7: 33 | AI7: 34 | AJ7: 35 | AK7: 36 | AL7: 37 | AM7: 38 | AN7: 39 | AO7: 40 | AP7: 41 | AQ7: 42 | AR7: 43 | AS7: 44 | AT7: 45 | AU7: 46 | AV7: 47 | AW7: 48 | AX7: 49 | AY7: 50 | AZ7: 51 | BA7: 52 | BB7: 53 | BC7: 54 | BD7: 55 | BE7: 56 | BF7: 57 | BG7: 58 | BH7: 59 | BI7: 60
A8: Retail Active? (1=Yes, 0=No) | B8: =IF(B7>='Drivers & Assumptions'!C31,1,0) -> 0 | C8: =IF(C7>='Drivers & Assumptions'!C31,1,0) -> 0 | D8: =IF(D7>='Drivers & Assumptions'!C31,1,0) -> 0 | E8: =IF(E7>='Drivers & Assumptions'!C31,1,0) -> 0 | F8: =IF(F7>='Drivers & Assumptions'!C31,1,0) -> 0 | G8: =IF(G7>='Drivers & Assumptions'!C31,1,0) -> 0 | H8: =IF(H7>='Drivers & Assumptions'!C31,1,0) -> 0 | I8: =IF(I7>='Drivers & Assumptions'!C31,1,0) -> 0 | J8: =IF(J7>='Drivers & Assumptions'!C31,1,0) -> 0 | K8: =IF(K7>='Drivers & Assumptions'!C31,1,0) -> 0 | L8: =IF(L7>='Drivers & Assumptions'!C31,1,0) -> 0 | M8: =IF(M7>='Drivers & Assumptions'!C31,1,0) -> 0 | N8: =IF(N7>='Drivers & Assumptions'!C31,1,0) -> 0 | O8: =IF(O7>='Drivers & Assumptions'!C31,1,0) -> 0 | P8: =IF(P7>='Drivers & Assumptions'!C31,1,0) -> 0 | Q8: =IF(Q7>='Drivers & Assumptions'!C31,1,0) -> 0 | R8: =IF(R7>='Drivers & Assumptions'!C31,1,0) -> 0 | S8: =IF(S7>='Drivers & Assumptions'!C31,1,0) -> 0 | T8: =IF(T7>='Drivers & Assumptions'!C31,1,0) -> 0 | U8: =IF(U7>='Drivers & Assumptions'!C31,1,0) -> 0 | V8: =IF(V7>='Drivers & Assumptions'!C31,1,0) -> 0 | W8: =IF(W7>='Drivers & Assumptions'!C31,1,0) -> 0 | X8: =IF(X7>='Drivers & Assumptions'!C31,1,0) -> 0 | Y8: =IF(Y7>='Drivers & Assumptions'!C31,1,0) -> 0 | Z8: =IF(Z7>='Drivers & Assumptions'!C31,1,0) -> 0 | AA8: =IF(AA7>='Drivers & Assumptions'!C31,1,0) -> 0 | AB8: =IF(AB7>='Drivers & Assumptions'!C31,1,0) -> 0 | AC8: =IF(AC7>='Drivers & Assumptions'!C31,1,0) -> 0 | AD8: =IF(AD7>='Drivers & Assumptions'!C31,1,0) -> 0 | AE8: =IF(AE7>='Drivers & Assumptions'!C31,1,0) -> 0 | AF8: =IF(AF7>='Drivers & Assumptions'!C31,1,0) -> 0 | AG8: =IF(AG7>='Drivers & Assumptions'!C31,1,0) -> 0 | AH8: =IF(AH7>='Drivers & Assumptions'!C31,1,0) -> 0 | AI8: =IF(AI7>='Drivers & Assumptions'!C31,1,0) -> 0 | AJ8: =IF(AJ7>='Drivers & Assumptions'!C31,1,0) -> 0 | AK8: =IF(AK7>='Drivers & Assumptions'!C31,1,0) -> 0 | AL8: =IF(AL7>='Drivers & Assumptions'!C31,1,0) -> 1 | AM8: =IF(AM7>='Drivers & Assumptions'!C31,1,0) -> 1 | AN8: =IF(AN7>='Drivers & Assumptions'!C31,1,0) -> 1 | AO8: =IF(AO7>='Drivers & Assumptions'!C31,1,0) -> 1 | AP8: =IF(AP7>='Drivers & Assumptions'!C31,1,0) -> 1 | AQ8: =IF(AQ7>='Drivers & Assumptions'!C31,1,0) -> 1 | AR8: =IF(AR7>='Drivers & Assumptions'!C31,1,0) -> 1 | AS8: =IF(AS7>='Drivers & Assumptions'!C31,1,0) -> 1 | AT8: =IF(AT7>='Drivers & Assumptions'!C31,1,0) -> 1 | AU8: =IF(AU7>='Drivers & Assumptions'!C31,1,0) -> 1 | AV8: =IF(AV7>='Drivers & Assumptions'!C31,1,0) -> 1 | AW8: =IF(AW7>='Drivers & Assumptions'!C31,1,0) -> 1 | AX8: =IF(AX7>='Drivers & Assumptions'!C31,1,0) -> 1 | AY8: =IF(AY7>='Drivers & Assumptions'!C31,1,0) -> 1 | AZ8: =IF(AZ7>='Drivers & Assumptions'!C31,1,0) -> 1 | BA8: =IF(BA7>='Drivers & Assumptions'!C31,1,0) -> 1 | BB8: =IF(BB7>='Drivers & Assumptions'!C31,1,0) -> 1 | BC8: =IF(BC7>='Drivers & Assumptions'!C31,1,0) -> 1 | BD8: =IF(BD7>='Drivers & Assumptions'!C31,1,0) -> 1 | BE8: =IF(BE7>='Drivers & Assumptions'!C31,1,0) -> 1 | BF8: =IF(BF7>='Drivers & Assumptions'!C31,1,0) -> 1 | BG8: =IF(BG7>='Drivers & Assumptions'!C31,1,0) -> 1 | BH8: =IF(BH7>='Drivers & Assumptions'!C31,1,0) -> 1 | BI8: =IF(BI7>='Drivers & Assumptions'!C31,1,0) -> 1
A9: Months Since Retail Launch | B9: =IF(B8=1,B7-'Drivers & Assumptions'!C31+1,0) -> 0 | C9: =IF(C8=1,C7-'Drivers & Assumptions'!C31+1,0) -> 0 | D9: =IF(D8=1,D7-'Drivers & Assumptions'!C31+1,0) -> 0 | E9: =IF(E8=1,E7-'Drivers & Assumptions'!C31+1,0) -> 0 | F9: =IF(F8=1,F7-'Drivers & Assumptions'!C31+1,0) -> 0 | G9: =IF(G8=1,G7-'Drivers & Assumptions'!C31+1,0) -> 0 | H9: =IF(H8=1,H7-'Drivers & Assumptions'!C31+1,0) -> 0 | I9: =IF(I8=1,I7-'Drivers & Assumptions'!C31+1,0) -> 0 | J9: =IF(J8=1,J7-'Drivers & Assumptions'!C31+1,0) -> 0 | K9: =IF(K8=1,K7-'Drivers & Assumptions'!C31+1,0) -> 0 | L9: =IF(L8=1,L7-'Drivers & Assumptions'!C31+1,0) -> 0 | M9: =IF(M8=1,M7-'Drivers & Assumptions'!C31+1,0) -> 0 | N9: =IF(N8=1,N7-'Drivers & Assumptions'!C31+1,0) -> 0 | O9: =IF(O8=1,O7-'Drivers & Assumptions'!C31+1,0) -> 0 | P9: =IF(P8=1,P7-'Drivers & Assumptions'!C31+1,0) -> 0 | Q9: =IF(Q8=1,Q7-'Drivers & Assumptions'!C31+1,0) -> 0 | R9: =IF(R8=1,R7-'Drivers & Assumptions'!C31+1,0) -> 0 | S9: =IF(S8=1,S7-'Drivers & Assumptions'!C31+1,0) -> 0 | T9: =IF(T8=1,T7-'Drivers & Assumptions'!C31+1,0) -> 0 | U9: =IF(U8=1,U7-'Drivers & Assumptions'!C31+1,0) -> 0 | V9: =IF(V8=1,V7-'Drivers & Assumptions'!C31+1,0) -> 0 | W9: =IF(W8=1,W7-'Drivers & Assumptions'!C31+1,0) -> 0 | X9: =IF(X8=1,X7-'Drivers & Assumptions'!C31+1,0) -> 0 | Y9: =IF(Y8=1,Y7-'Drivers & Assumptions'!C31+1,0) -> 0 | Z9: =IF(Z8=1,Z7-'Drivers & Assumptions'!C31+1,0) -> 0 | AA9: =IF(AA8=1,AA7-'Drivers & Assumptions'!C31+1,0) -> 0 | AB9: =IF(AB8=1,AB7-'Drivers & Assumptions'!C31+1,0) -> 0 | AC9: =IF(AC8=1,AC7-'Drivers & Assumptions'!C31+1,0) -> 0 | AD9: =IF(AD8=1,AD7-'Drivers & Assumptions'!C31+1,0) -> 0 | AE9: =IF(AE8=1,AE7-'Drivers & Assumptions'!C31+1,0) -> 0 | AF9: =IF(AF8=1,AF7-'Drivers & Assumptions'!C31+1,0) -> 0 | AG9: =IF(AG8=1,AG7-'Drivers & Assumptions'!C31+1,0) -> 0 | AH9: =IF(AH8=1,AH7-'Drivers & Assumptions'!C31+1,0) -> 0 | AI9: =IF(AI8=1,AI7-'Drivers & Assumptions'!C31+1,0) -> 0 | AJ9: =IF(AJ8=1,AJ7-'Drivers & Assumptions'!C31+1,0) -> 0 | AK9: =IF(AK8=1,AK7-'Drivers & Assumptions'!C31+1,0) -> 0 | AL9: =IF(AL8=1,AL7-'Drivers & Assumptions'!C31+1,0) -> 1 | AM9: =IF(AM8=1,AM7-'Drivers & Assumptions'!C31+1,0) -> 2 | AN9: =IF(AN8=1,AN7-'Drivers & Assumptions'!C31+1,0) -> 3 | AO9: =IF(AO8=1,AO7-'Drivers & Assumptions'!C31+1,0) -> 4 | AP9: =IF(AP8=1,AP7-'Drivers & Assumptions'!C31+1,0) -> 5 | AQ9: =IF(AQ8=1,AQ7-'Drivers & Assumptions'!C31+1,0) -> 6 | AR9: =IF(AR8=1,AR7-'Drivers & Assumptions'!C31+1,0) -> 7 | AS9: =IF(AS8=1,AS7-'Drivers & Assumptions'!C31+1,0) -> 8 | AT9: =IF(AT8=1,AT7-'Drivers & Assumptions'!C31+1,0) -> 9 | AU9: =IF(AU8=1,AU7-'Drivers & Assumptions'!C31+1,0) -> 10 | AV9: =IF(AV8=1,AV7-'Drivers & Assumptions'!C31+1,0) -> 11 | AW9: =IF(AW8=1,AW7-'Drivers & Assumptions'!C31+1,0) -> 12 | AX9: =IF(AX8=1,AX7-'Drivers & Assumptions'!C31+1,0) -> 13 | AY9: =IF(AY8=1,AY7-'Drivers & Assumptions'!C31+1,0) -> 14 | AZ9: =IF(AZ8=1,AZ7-'Drivers & Assumptions'!C31+1,0) -> 15 | BA9: =IF(BA8=1,BA7-'Drivers & Assumptions'!C31+1,0) -> 16 | BB9: =IF(BB8=1,BB7-'Drivers & Assumptions'!C31+1,0) -> 17 | BC9: =IF(BC8=1,BC7-'Drivers & Assumptions'!C31+1,0) -> 18 | BD9: =IF(BD8=1,BD7-'Drivers & Assumptions'!C31+1,0) -> 19 | BE9: =IF(BE8=1,BE7-'Drivers & Assumptions'!C31+1,0) -> 20 | BF9: =IF(BF8=1,BF7-'Drivers & Assumptions'!C31+1,0) -> 21 | BG9: =IF(BG8=1,BG7-'Drivers & Assumptions'!C31+1,0) -> 22 | BH9: =IF(BH8=1,BH7-'Drivers & Assumptions'!C31+1,0) -> 23 | BI9: =IF(BI8=1,BI7-'Drivers & Assumptions'!C31+1,0) -> 24
A11: STORE ROLLOUT & VOLUME
A12: Active Retail Doors | B12: =IF(B8=0,0,'Drivers & Assumptions'!C37+(B9-1)*'Drivers & Assumptions'!C38) -> 0 | C12: =IF(C8=0,0,'Drivers & Assumptions'!C37+(C9-1)*'Drivers & Assumptions'!C38) -> 0 | D12: =IF(D8=0,0,'Drivers & Assumptions'!C37+(D9-1)*'Drivers & Assumptions'!C38) -> 0 | E12: =IF(E8=0,0,'Drivers & Assumptions'!C37+(E9-1)*'Drivers & Assumptions'!C38) -> 0 | F12: =IF(F8=0,0,'Drivers & Assumptions'!C37+(F9-1)*'Drivers & Assumptions'!C38) -> 0 | G12: =IF(G8=0,0,'Drivers & Assumptions'!C37+(G9-1)*'Drivers & Assumptions'!C38) -> 0 | H12: =IF(H8=0,0,'Drivers & Assumptions'!C37+(H9-1)*'Drivers & Assumptions'!C38) -> 0 | I12: =IF(I8=0,0,'Drivers & Assumptions'!C37+(I9-1)*'Drivers & Assumptions'!C38) -> 0 | J12: =IF(J8=0,0,'Drivers & Assumptions'!C37+(J9-1)*'Drivers & Assumptions'!C38) -> 0 | K12: =IF(K8=0,0,'Drivers & Assumptions'!C37+(K9-1)*'Drivers & Assumptions'!C38) -> 0 | L12: =IF(L8=0,0,'Drivers & Assumptions'!C37+(L9-1)*'Drivers & Assumptions'!C38) -> 0 | M12: =IF(M8=0,0,'Drivers & Assumptions'!C37+(M9-1)*'Drivers & Assumptions'!C38) -> 0 | N12: =IF(N8=0,0,'Drivers & Assumptions'!C37+(N9-1)*'Drivers & Assumptions'!C38) -> 0 | O12: =IF(O8=0,0,'Drivers & Assumptions'!C37+(O9-1)*'Drivers & Assumptions'!C38) -> 0 | P12: =IF(P8=0,0,'Drivers & Assumptions'!C37+(P9-1)*'Drivers & Assumptions'!C38) -> 0 | Q12: =IF(Q8=0,0,'Drivers & Assumptions'!C37+(Q9-1)*'Drivers & Assumptions'!C38) -> 0 | R12: =IF(R8=0,0,'Drivers & Assumptions'!C37+(R9-1)*'Drivers & Assumptions'!C38) -> 0 | S12: =IF(S8=0,0,'Drivers & Assumptions'!C37+(S9-1)*'Drivers & Assumptions'!C38) -> 0 | T12: =IF(T8=0,0,'Drivers & Assumptions'!C37+(T9-1)*'Drivers & Assumptions'!C38) -> 0 | U12: =IF(U8=0,0,'Drivers & Assumptions'!C37+(U9-1)*'Drivers & Assumptions'!C38) -> 0 | V12: =IF(V8=0,0,'Drivers & Assumptions'!C37+(V9-1)*'Drivers & Assumptions'!C38) -> 0 | W12: =IF(W8=0,0,'Drivers & Assumptions'!C37+(W9-1)*'Drivers & Assumptions'!C38) -> 0 | X12: =IF(X8=0,0,'Drivers & Assumptions'!C37+(X9-1)*'Drivers & Assumptions'!C38) -> 0 | Y12: =IF(Y8=0,0,'Drivers & Assumptions'!C37+(Y9-1)*'Drivers & Assumptions'!C38) -> 0 | Z12: =IF(Z8=0,0,'Drivers & Assumptions'!C37+(Z9-1)*'Drivers & Assumptions'!C38) -> 0 | AA12: =IF(AA8=0,0,'Drivers & Assumptions'!C37+(AA9-1)*'Drivers & Assumptions'!C38) -> 0 | AB12: =IF(AB8=0,0,'Drivers & Assumptions'!C37+(AB9-1)*'Drivers & Assumptions'!C38) -> 0 | AC12: =IF(AC8=0,0,'Drivers & Assumptions'!C37+(AC9-1)*'Drivers & Assumptions'!C38) -> 0 | AD12: =IF(AD8=0,0,'Drivers & Assumptions'!C37+(AD9-1)*'Drivers & Assumptions'!C38) -> 0 | AE12: =IF(AE8=0,0,'Drivers & Assumptions'!C37+(AE9-1)*'Drivers & Assumptions'!C38) -> 0 | AF12: =IF(AF8=0,0,'Drivers & Assumptions'!C37+(AF9-1)*'Drivers & Assumptions'!C38) -> 0 | AG12: =IF(AG8=0,0,'Drivers & Assumptions'!C37+(AG9-1)*'Drivers & Assumptions'!C38) -> 0 | AH12: =IF(AH8=0,0,'Drivers & Assumptions'!C37+(AH9-1)*'Drivers & Assumptions'!C38) -> 0 | AI12: =IF(AI8=0,0,'Drivers & Assumptions'!C37+(AI9-1)*'Drivers & Assumptions'!C38) -> 0 | AJ12: =IF(AJ8=0,0,'Drivers & Assumptions'!C37+(AJ9-1)*'Drivers & Assumptions'!C38) -> 0 | AK12: =IF(AK8=0,0,'Drivers & Assumptions'!C37+(AK9-1)*'Drivers & Assumptions'!C38) -> 0 | AL12: =IF(AL8=0,0,'Drivers & Assumptions'!C37+(AL9-1)*'Drivers & Assumptions'!C38) -> 20 | AM12: =IF(AM8=0,0,'Drivers & Assumptions'!C37+(AM9-1)*'Drivers & Assumptions'!C38) -> 25 | AN12: =IF(AN8=0,0,'Drivers & Assumptions'!C37+(AN9-1)*'Drivers & Assumptions'!C38) -> 30 | AO12: =IF(AO8=0,0,'Drivers & Assumptions'!C37+(AO9-1)*'Drivers & Assumptions'!C38) -> 35 | AP12: =IF(AP8=0,0,'Drivers & Assumptions'!C37+(AP9-1)*'Drivers & Assumptions'!C38) -> 40 | AQ12: =IF(AQ8=0,0,'Drivers & Assumptions'!C37+(AQ9-1)*'Drivers & Assumptions'!C38) -> 45 | AR12: =IF(AR8=0,0,'Drivers & Assumptions'!C37+(AR9-1)*'Drivers & Assumptions'!C38) -> 50 | AS12: =IF(AS8=0,0,'Drivers & Assumptions'!C37+(AS9-1)*'Drivers & Assumptions'!C38) -> 55 | AT12: =IF(AT8=0,0,'Drivers & Assumptions'!C37+(AT9-1)*'Drivers & Assumptions'!C38) -> 60 | AU12: =IF(AU8=0,0,'Drivers & Assumptions'!C37+(AU9-1)*'Drivers & Assumptions'!C38) -> 65 | AV12: =IF(AV8=0,0,'Drivers & Assumptions'!C37+(AV9-1)*'Drivers & Assumptions'!C38) -> 70 | AW12: =IF(AW8=0,0,'Drivers & Assumptions'!C37+(AW9-1)*'Drivers & Assumptions'!C38) -> 75 | AX12: =IF(AX8=0,0,'Drivers & Assumptions'!C37+(AX9-1)*'Drivers & Assumptions'!C38) -> 80 | AY12: =IF(AY8=0,0,'Drivers & Assumptions'!C37+(AY9-1)*'Drivers & Assumptions'!C38) -> 85 | AZ12: =IF(AZ8=0,0,'Drivers & Assumptions'!C37+(AZ9-1)*'Drivers & Assumptions'!C38) -> 90 | BA12: =IF(BA8=0,0,'Drivers & Assumptions'!C37+(BA9-1)*'Drivers & Assumptions'!C38) -> 95 | BB12: =IF(BB8=0,0,'Drivers & Assumptions'!C37+(BB9-1)*'Drivers & Assumptions'!C38) -> 100 | BC12: =IF(BC8=0,0,'Drivers & Assumptions'!C37+(BC9-1)*'Drivers & Assumptions'!C38) -> 105 | BD12: =IF(BD8=0,0,'Drivers & Assumptions'!C37+(BD9-1)*'Drivers & Assumptions'!C38) -> 110 | BE12: =IF(BE8=0,0,'Drivers & Assumptions'!C37+(BE9-1)*'Drivers & Assumptions'!C38) -> 115 | BF12: =IF(BF8=0,0,'Drivers & Assumptions'!C37+(BF9-1)*'Drivers & Assumptions'!C38) -> 120 | BG12: =IF(BG8=0,0,'Drivers & Assumptions'!C37+(BG9-1)*'Drivers & Assumptions'!C38) -> 125 | BH12: =IF(BH8=0,0,'Drivers & Assumptions'!C37+(BH9-1)*'Drivers & Assumptions'!C38) -> 130 | BI12: =IF(BI8=0,0,'Drivers & Assumptions'!C37+(BI9-1)*'Drivers & Assumptions'!C38) -> 135
A13: Units per Door per Month | B13: =IF(B8=0,0,ROUND('Drivers & Assumptions'!C39*(1+'Drivers & Assumptions'!C40)^INT((B9-1)/12),0)) -> 0 | C13: =IF(C8=0,0,ROUND('Drivers & Assumptions'!C39*(1+'Drivers & Assumptions'!C40)^INT((C9-1)/12),0)) -> 0 | D13: =IF(D8=0,0,ROUND('Drivers & Assumptions'!C39*(1+'Drivers & Assumptions'!C40)^INT((D9-1)/12),0)) -> 0 | E13: =IF(E8=0,0,ROUND('Drivers & Assumptions'!C39*(1+'Drivers & Assumptions'!C40)^INT((E9-1)/12),0)) -> 0 | F13: =IF(F8=0,0,ROUND('Drivers & Assumptions'!C39*(1+'Drivers & Assumptions'!C40)^INT((F9-1)/12),0)) -> 0 | G13: =IF(G8=0,0,ROUND('Drivers & Assumptions'!C39*(1+'Drivers & Assumptions'!C40)^INT((G9-1)/12),0)) -> 0 | H13: =IF(H8=0,0,ROUND('Drivers & Assumptions'!C39*(1+'Drivers & Assumptions'!C40)^INT((H9-1)/12),0)) -> 0 | I13: =IF(I8=0,0,ROUND('Drivers & Assumptions'!C39*(1+'Drivers & Assumptions'!C40)^INT((I9-1)/12),0)) -> 0 | J13: =IF(J8=0,0,ROUND('Drivers & Assumptions'!C39*(1+'Drivers & Assumptions'!C40)^INT((J9-1)/12),0)) -> 0 | K13: =IF(K8=0,0,ROUND('Drivers & Assumptions'!C39*(1+'Drivers & Assumptions'!C40)^INT((K9-1)/12),0)) -> 0 | L13: =IF(L8=0,0,ROUND('Drivers & Assumptions'!C39*(1+'Drivers & Assumptions'!C40)^INT((L9-1)/12),0)) -> 0 | M13: =IF(M8=0,0,ROUND('Drivers & Assumptions'!C39*(1+'Drivers & Assumptions'!C40)^INT((M9-1)/12),0)) -> 0 | N13: =IF(N8=0,0,ROUND('Drivers & Assumptions'!C39*(1+'Drivers & Assumptions'!C40)^INT((N9-1)/12),0)) -> 0 | O13: =IF(O8=0,0,ROUND('Drivers & Assumptions'!C39*(1+'Drivers & Assumptions'!C40)^INT((O9-1)/12),0)) -> 0 | P13: =IF(P8=0,0,ROUND('Drivers & Assumptions'!C39*(1+'Drivers & Assumptions'!C40)^INT((P9-1)/12),0)) -> 0 | Q13: =IF(Q8=0,0,ROUND('Drivers & Assumptions'!C39*(1+'Drivers & Assumptions'!C40)^INT((Q9-1)/12),0)) -> 0 | R13: =IF(R8=0,0,ROUND('Drivers & Assumptions'!C39*(1+'Drivers & Assumptions'!C40)^INT((R9-1)/12),0)) -> 0 | S13: =IF(S8=0,0,ROUND('Drivers & Assumptions'!C39*(1+'Drivers & Assumptions'!C40)^INT((S9-1)/12),0)) -> 0 | T13: =IF(T8=0,0,ROUND('Drivers & Assumptions'!C39*(1+'Drivers & Assumptions'!C40)^INT((T9-1)/12),0)) -> 0 | U13: =IF(U8=0,0,ROUND('Drivers & Assumptions'!C39*(1+'Drivers & Assumptions'!C40)^INT((U9-1)/12),0)) -> 0 | V13: =IF(V8=0,0,ROUND('Drivers & Assumptions'!C39*(1+'Drivers & Assumptions'!C40)^INT((V9-1)/12),0)) -> 0 | W13: =IF(W8=0,0,ROUND('Drivers & Assumptions'!C39*(1+'Drivers & Assumptions'!C40)^INT((W9-1)/12),0)) -> 0 | X13: =IF(X8=0,0,ROUND('Drivers & Assumptions'!C39*(1+'Drivers & Assumptions'!C40)^INT((X9-1)/12),0)) -> 0 | Y13: =IF(Y8=0,0,ROUND('Drivers & Assumptions'!C39*(1+'Drivers & Assumptions'!C40)^INT((Y9-1)/12),0)) -> 0 | Z13: =IF(Z8=0,0,ROUND('Drivers & Assumptions'!C39*(1+'Drivers & Assumptions'!C40)^INT((Z9-1)/12),0)) -> 0 | AA13: =IF(AA8=0,0,ROUND('Drivers & Assumptions'!C39*(1+'Drivers & Assumptions'!C40)^INT((AA9-1)/12),0)) -> 0 | AB13: =IF(AB8=0,0,ROUND('Drivers & Assumptions'!C39*(1+'Drivers & Assumptions'!C40)^INT((AB9-1)/12),0)) -> 0 | AC13: =IF(AC8=0,0,ROUND('Drivers & Assumptions'!C39*(1+'Drivers & Assumptions'!C40)^INT((AC9-1)/12),0)) -> 0 | AD13: =IF(AD8=0,0,ROUND('Drivers & Assumptions'!C39*(1+'Drivers & Assumptions'!C40)^INT((AD9-1)/12),0)) -> 0 | AE13: =IF(AE8=0,0,ROUND('Drivers & Assumptions'!C39*(1+'Drivers & Assumptions'!C40)^INT((AE9-1)/12),0)) -> 0 | AF13: =IF(AF8=0,0,ROUND('Drivers & Assumptions'!C39*(1+'Drivers & Assumptions'!C40)^INT((AF9-1)/12),0)) -> 0 | AG13: =IF(AG8=0,0,ROUND('Drivers & Assumptions'!C39*(1+'Drivers & Assumptions'!C40)^INT((AG9-1)/12),0)) -> 0 | AH13: =IF(AH8=0,0,ROUND('Drivers & Assumptions'!C39*(1+'Drivers & Assumptions'!C40)^INT((AH9-1)/12),0)) -> 0 | AI13: =IF(AI8=0,0,ROUND('Drivers & Assumptions'!C39*(1+'Drivers & Assumptions'!C40)^INT((AI9-1)/12),0)) -> 0 | AJ13: =IF(AJ8=0,0,ROUND('Drivers & Assumptions'!C39*(1+'Drivers & Assumptions'!C40)^INT((AJ9-1)/12),0)) -> 0 | AK13: =IF(AK8=0,0,ROUND('Drivers & Assumptions'!C39*(1+'Drivers & Assumptions'!C40)^INT((AK9-1)/12),0)) -> 0 | AL13: =IF(AL8=0,0,ROUND('Drivers & Assumptions'!C39*(1+'Drivers & Assumptions'!C40)^INT((AL9-1)/12),0)) -> 8 | AM13: =IF(AM8=0,0,ROUND('Drivers & Assumptions'!C39*(1+'Drivers & Assumptions'!C40)^INT((AM9-1)/12),0)) -> 8 | AN13: =IF(AN8=0,0,ROUND('Drivers & Assumptions'!C39*(1+'Drivers & Assumptions'!C40)^INT((AN9-1)/12),0)) -> 8 | AO13: =IF(AO8=0,0,ROUND('Drivers & Assumptions'!C39*(1+'Drivers & Assumptions'!C40)^INT((AO9-1)/12),0)) -> 8 | AP13: =IF(AP8=0,0,ROUND('Drivers & Assumptions'!C39*(1+'Drivers & Assumptions'!C40)^INT((AP9-1)/12),0)) -> 8 | AQ13: =IF(AQ8=0,0,ROUND('Drivers & Assumptions'!C39*(1+'Drivers & Assumptions'!C40)^INT((AQ9-1)/12),0)) -> 8 | AR13: =IF(AR8=0,0,ROUND('Drivers & Assumptions'!C39*(1+'Drivers & Assumptions'!C40)^INT((AR9-1)/12),0)) -> 8 | AS13: =IF(AS8=0,0,ROUND('Drivers & Assumptions'!C39*(1+'Drivers & Assumptions'!C40)^INT((AS9-1)/12),0)) -> 8 | AT13: =IF(AT8=0,0,ROUND('Drivers & Assumptions'!C39*(1+'Drivers & Assumptions'!C40)^INT((AT9-1)/12),0)) -> 8 | AU13: =IF(AU8=0,0,ROUND('Drivers & Assumptions'!C39*(1+'Drivers & Assumptions'!C40)^INT((AU9-1)/12),0)) -> 8 | AV13: =IF(AV8=0,0,ROUND('Drivers & Assumptions'!C39*(1+'Drivers & Assumptions'!C40)^INT((AV9-1)/12),0)) -> 8 | AW13: =IF(AW8=0,0,ROUND('Drivers & Assumptions'!C39*(1+'Drivers & Assumptions'!C40)^INT((AW9-1)/12),0)) -> 8 | AX13: =IF(AX8=0,0,ROUND('Drivers & Assumptions'!C39*(1+'Drivers & Assumptions'!C40)^INT((AX9-1)/12),0)) -> 9 | AY13: =IF(AY8=0,0,ROUND('Drivers & Assumptions'!C39*(1+'Drivers & Assumptions'!C40)^INT((AY9-1)/12),0)) -> 9 | AZ13: =IF(AZ8=0,0,ROUND('Drivers & Assumptions'!C39*(1+'Drivers & Assumptions'!C40)^INT((AZ9-1)/12),0)) -> 9 | BA13: =IF(BA8=0,0,ROUND('Drivers & Assumptions'!C39*(1+'Drivers & Assumptions'!C40)^INT((BA9-1)/12),0)) -> 9 | BB13: =IF(BB8=0,0,ROUND('Drivers & Assumptions'!C39*(1+'Drivers & Assumptions'!C40)^INT((BB9-1)/12),0)) -> 9 | BC13: =IF(BC8=0,0,ROUND('Drivers & Assumptions'!C39*(1+'Drivers & Assumptions'!C40)^INT((BC9-1)/12),0)) -> 9 | BD13: =IF(BD8=0,0,ROUND('Drivers & Assumptions'!C39*(1+'Drivers & Assumptions'!C40)^INT((BD9-1)/12),0)) -> 9 | BE13: =IF(BE8=0,0,ROUND('Drivers & Assumptions'!C39*(1+'Drivers & Assumptions'!C40)^INT((BE9-1)/12),0)) -> 9 | BF13: =IF(BF8=0,0,ROUND('Drivers & Assumptions'!C39*(1+'Drivers & Assumptions'!C40)^INT((BF9-1)/12),0)) -> 9 | BG13: =IF(BG8=0,0,ROUND('Drivers & Assumptions'!C39*(1+'Drivers & Assumptions'!C40)^INT((BG9-1)/12),0)) -> 9 | BH13: =IF(BH8=0,0,ROUND('Drivers & Assumptions'!C39*(1+'Drivers & Assumptions'!C40)^INT((BH9-1)/12),0)) -> 9 | BI13: =IF(BI8=0,0,ROUND('Drivers & Assumptions'!C39*(1+'Drivers & Assumptions'!C40)^INT((BI9-1)/12),0)) -> 9
A14: Total Retail Units | B14: =B12*B13 -> 0 | C14: =C12*C13 -> 0 | D14: =D12*D13 -> 0 | E14: =E12*E13 -> 0 | F14: =F12*F13 -> 0 | G14: =G12*G13 -> 0 | H14: =H12*H13 -> 0 | I14: =I12*I13 -> 0 | ... BI14: =BI12*BI13 -> 1215
